Workbook

Sheet 01_PARÂMETROS
A1: PARÂMETROS — ÂNCORA DE TODAS AS FÓRMULAS DO MOTOR
A2: Todas as abas referenciam esta aba. Altere aqui para propagar ao motor inteiro.
A3: BLOCO A — FÓRMULA IC (pesos oficiais FAP/MPS)
A4: A1 Peso Gravidade (w_G) | B4: 0.5 | C4: 0,50 — peso oficial Portaria FAP/MPS
A5: A2 Peso Frequência (w_F) | B5: 0.35 | C5: 0,35 — peso oficial Portaria FAP/MPS
A6: A3 Peso Custo (w_C) | B6: 0.15 | C6: 0,15 — peso oficial Portaria FAP/MPS
A7: A4 Verificação soma (= A1+A2+A3) | B7: =B4+B5+B6 -> 1 | C7: Deve ser 1,00
A8: BLOCO B — PONTO DE REFERÊNCIA
A9: B1 IC de Referência (IC_ref) | B9: 50 | C9: Mediana teórica da escala percentil 0–100
A10: BLOCO C — LIMITES DA RELATIVIDADE
A11: C1 Limite inferior (desagravo máximo) | B11: 0.75 | C11: 0,75 = desagravo de até 25%
A12: C2 Limite superior (agravo máximo) | B12: 1.4 | C12: 1,40 = agravo de até 40%
A13: BLOCO D — LIMIARES DAS CLASSES
A14: D1 Classe Preferencial ≤ | B14: 0.875 | C14: IC < 43,75
A15: D2 Classe Baixo ≤ | B15: 0.95 | C15: IC 43,75–47,50
A16: D3 Classe Médio ≤ | B16: 1.075 | C16: IC 47,50–53,75
A17: D4 Classe Alto ≤ | B17: 1.225 | C17: IC 53,75–61,25
A18: D5 Classe Elevado (> D4) | B18: 1.225 | C18: IC > 61,25
A19: BLOCO E — ESTATÍSTICAS DOS DADOS FAP (referência)
A20: E1 N observações (ICs > 0) | B20: 280 | C20: ICs válidos nos PDFs FAP vigências 2024+2025
A21: E2 IC Médio observado | B21: 54.25 | C21: Média dos ICs calculados — referência analítica
A22: E3 IC Desvio Padrão | B22: 24.2 | C22: Dispersão — usada no teste z
A23: E4 IC Mediana observada | B23: 55.36 | C23: Mediana empírica
A24: E5 IC Mínimo observado | B24: 2.29
A25: E6 IC Máximo observado | B25: 99.89
A26: E7 IC Quartil 1 (Q1) | B26: 36.69
A27: E8 IC Quartil 3 (Q3) | B27: 72.85
A28: BLOCO F — TESTE Z (IC_ref=50 vs média observada)
A29: F1 Estatística z = (E2−B1) / (E3/√E1) | B29: =(B21-B8)/((B22/SQRT(B20))) -> 37.51141 | C29: z>1,96 → rejeitar H0 α=5%
A30: F2 |z| > 1,96? | B30: =IF(ABS(B28)>1.96,"SIM — rejeitar H0","NÃO — não rejeitar H0") -> NÃO — não rejeitar H0
A31: BLOCO G — CONTAGENS GERAIS
A32: G1 Total subclasses CNAE | B32: 1332
A33: G2 Subclasses com FAP calculado | B33: 146
A34: G3 Subclasses com fallback CNAE-STG | B34: 1186 | C34: =G1-G2 -> 0
A35: G4 Divisões com conflito intra-grupo | B35: 21 | C35: Veja aba AUDITORIA

Sheet 02_METODOLOGIA
A1: METODOLOGIA — MOTOR DE CÁLCULO DE RELATIVIDADES POR CNAE | VIDA CAPITAL GLOBAL
A2: Fundamentos, Fórmulas e Análise Crítica | STG Seguros S.A. — 2026
A3: 1. OBJETIVO
A4: Propósito | B4: Calcular, com base nos dados públicos FAP/MPS, agravos e desagravos sobre a taxa pura do produto Vida Capital Global em função da atividade econômica (CNAE) do estipulante.
A5: Fórmula de aplicação | B5: TP_ajustada = TP_base × Relatividade_CNAE
A7: 2. FONTE DOS DADOS
A8: FAP / Ministério da Previdência Social | B8: Percentis de Frequência, Gravidade e Custo por subclasse CNAE 2.3. Publicados anualmente no portal gov.br/previdencia. Cobertura: ~3,4 milhões de estabelecimentos brasileiros.
A9: Vigência 2024 — dados 2021-2022 | B9: Portaria Interministerial MPS/MF nº 1, de 20/09/2023
A10: Vigência 2025 — dados 2022-2023 | B10: Portaria Interministerial MPS/MF nº 4, de 10/09/2024
A12: 3. FÓRMULA DO ÍNDICE COMPOSTO (IC)
A13: IC = w_G × P_Gravidade + w_F × P_Frequência + w_C × P_Custo
A14: Pesos (parâmetros A1–A3 da aba 01_PARÂMETROS) | B14: w_G=0,50 | w_F=0,35 | w_C=0,15 | Soma=1,00 (fórmula oficial FAP)
A15: Escala de IC | B15: 0 a 100. Quanto maior, maior a acidentalidade relativa da subclasse.
A17: 4. PONTO DE REFERÊNCIA IC_ref = 50
A18: Definição | B18: IC_ref=50 é o ponto médio teórico da escala de percentis [0,100] — mediana teórica da distribuição uniforme.
A19: Por que 50 e não a média das subclasses disponíveis? | B19: Os PDFs FAP cobrem ~163 subclasses concentradas em agropecuária e extrativismo — setores acima da média de acidentalidade. Usar a média dessas subclasses como referência criaria viés de seleção: agravos subestimados, desagravos superestimados. IC_ref=50 é transparente, defensável e independente da amostra.
A21: 5. CÁLCULO DA RELATIVIDADE
A22: Relatividade Bruta | B22: Relat_bruta = IC_médio / IC_ref
A23: IC Médio | B23: Média simples dos ICs dos dois anos disponíveis (2023 e 2024)
A24: Relatividade Final | B24: Relat_final = MAX(C1 ; MIN(C2 ; Relat_bruta)) — parâmetros C1=0,75 e C2=1,40 na aba 01_PARÂMETROS
A25: Ajuste sobre a TP | B25: Ajuste_% = (Relat_final − 1,00) × 100
A27: 6. ANÁLISE CRÍTICA — CONFLITOS INTRA-DIVISÃO
A28: O que são conflitos | B28: Subclasses da mesma divisão CNAE com classes de risco opostas (ex: Preferencial e Elevado dentro de 08.10).
A29: Fazem sentido? | B29: MAJORITARIAMENTE SIM. Dentro de uma divisão, diferentes subclasses têm natureza de trabalho radicalmente diferente: • Extração em frente de lavra (alto risco) vs. beneficiamento em galpão (menor risco) • Pesca oceânica (alto) vs. apoio à pesca em escritório (baixo) • Criação intensiva (alto) vs. criação extensiva (baixo)
A30: Casos para revisão | B30: Alguns conflitos podem decorrer de amostras pequenas no FAP (IC instável). A aba 06_AUDITORIA_CONSISTÊNCIA identifica e classifica cada conflito com flag de alerta.
A31: Regra adotada | B31: Cada subclasse mantém sua relatividade calculada individualmente pelo FAP. NÃO se aplica correção automática. Correções manuais devem ser documentadas e aprovadas pelo atuário responsável.
A33: 7. TRATAMENTO SEM DADOS FAP
A34: Fallback | B34: Subclasse sem dados FAP usa o coeficiente CNAE-STG original: Baixo=0,90 | Médio=1,00 | Alto=1,15
A36: 8. RASTREABILIDADE
A37: Todos os números são calculados por fórmula | B37: Nenhum valor foi colado como constante no motor. Todas as células de resultado referenciam a aba 01_PARÂMETROS ou a aba 03_FONTE_FAP.
A38: Cadeia de dependências | B38: 01_PARÂMETROS → 03_FONTE_FAP → 04_MOTOR_CÁLCULO → 05_RESULTADOS
A39: Para auditar um número | B39: Selecione a célula → Ctrl+[ para seguir dependentes | Ctrl+] para ver precedentes
A41: 9. REVISÃO
A42: Periodicidade | B42: Anual — setembro, com publicação dos novos percentis FAP pelo MPS
A43: Responsável | B43: Atuário Responsável Técnico | MIBA 2664 | STG Seguros S.A.

Sheet 03_FONTE_FAP
A1: FONTE DE DADOS — FAP / MPS | Percentis de Frequência, Gravidade e Custo por CNAE
A2: Portarias MPS/MF nº1/2023 (vigência 2024) e nº4/2024 (vigência 2025) | IC = w_G×Grav + w_F×Freq + w_C×Custo
A3: IDENTIFICAÇÃO | C3: ▶ FAP VIGÊNCIA 2024 (dados 2021–2022) | H3: ▶ FAP VIGÊNCIA 2025 (dados 2022–2023) | M3: ▶ RESULTADO
A4: CNAE | B4: Descrição Subclasse | C4: P_Freq | D4: P_Grav | E4: P_Custo | F4: IC 2023 (fórmula) | G4: Válido? | H4: P_Freq | I4: P_Grav | J4: P_Custo | K4: IC 2024 (fórmula) | L4: Válido? | M4: IC Médio (fórmula) | N4: Relat. Bruta (fórmula) | O4: Relat. Final (fórmula)
A5: 01.11-3/01 | B5: Cultivo de arroz | C5: 40.66 | D5: 59.8 | E5: 72.16 | F5: ='01_PARÂMETROS'!$B$4*D5+'01_PARÂMETROS'!$B$5*C5+'01_PARÂMETROS'!$B$6*E5 -> 54.955 | G5: =IF(AND(C5=0,D5=0,E5=0),"✗","✓") -> ✓ | H5: 46.19 | I5: 68.81 | J5: 44.91 | K5: ='01_PARÂMETROS'!$B$4*I5+'01_PARÂMETROS'!$B$5*H5+'01_PARÂMETROS'!$B$6*J5 -> 57.308 | L5: =IF(AND(H5=0,I5=0,J5=0),"✗","✓") -> ✓ | M5: =AVERAGE(F5,K5) -> 56.1315 | N5: =IFERROR(M5/'01_PARÂMETROS'!$B$9,"") -> 1.12263 | O5: =IFERROR(MAX('01_PARÂMETROS'!$B$11,MIN('01_PARÂMETROS'!$B$12,N5)),"") -> 1.12263
A6: 01.11-3/02 | B6: Cultivo de milho | C6: 45.93 | D6: 47.52 | E6: 56.06 | F6: ='01_PARÂMETROS'!$B$4*D6+'01_PARÂMETROS'!$B$5*C6+'01_PARÂMETROS'!$B$6*E6 -> 48.2445 | G6: =IF(AND(C6=0,D6=0,E6=0),"✗","✓") -> ✓ | H6: 30.92 | I6: 29.01 | J6: 21.91 | K6: ='01_PARÂMETROS'!$B$4*I6+'01_PARÂMETROS'!$B$5*H6+'01_PARÂMETROS'!$B$6*J6 -> 28.6135 | L6: =IF(AND(H6=0,I6=0,J6=0),"✗","✓") -> ✓ | M6: =AVERAGE(F6,K6) -> 38.429 | N6: =IFERROR(M6/'01_PARÂMETROS'!$B$9,"") -> 0.76858 | O6: =IFERROR(MAX('01_PARÂMETROS'!$B$11,MIN('01_PARÂMETROS'!$B$12,N6)),"") -> 0.76858
A7: 01.11-3/03 | B7: Cultivo de trigo | C7: 36.32 | D7: 23.02 | E7: 13.63 | F7: ='01_PARÂMETROS'!$B$4*D7+'01_PARÂMETROS'!$B$5*C7+'01_PARÂMETROS'!$B$6*E7 -> 26.2665 | G7: =IF(AND(C7=0,D7=0,E7=0),"✗","✓") -> ✓ | H7: 56.35 | I7: 0 | J7: 0 | K7: ='01_PARÂMETROS'!$B$4*I7+'01_PARÂMETROS'!$B$5*H7+'01_PARÂMETROS'!$B$6*J7 -> 19.7225 | L7: =IF(AND(H7=0,I7=0,J7=0),"✗","✓") -> ✓ | M7: =AVERAGE(F7,K7) -> 22.9945 | N7: =IFERROR(M7/'01_PARÂMETROS'!$B$9,"") -> 0.45989 | O7: =IFERROR(MAX('01_PARÂMETROS'!$B$11,MIN('01_PARÂMETROS'!$B$12,N7)),"") -> 0.75
A8: 01.11-3/99 | B8: Cultivo de outros cereais não especificados anteriormente | C8: 42.75 | D8: 50.21 | E8: 48.21 | F8: ='01_PARÂMETROS'!$B$4*D8+'01_PARÂMETROS'!$B$5*C8+'01_PARÂMETROS'!$B$6*E8 -> 47.299 | G8: =IF(AND(C8=0,D8=0,E8=0),"✗","✓") -> ✓ | H8: 62.39 | I8: 73.86 | J8: 69.02 | K8: ='01_PARÂMETROS'!$B$4*I8+'01_PARÂMETROS'!$B$5*H8+'01_PARÂMETROS'!$B$6*J8 -> 69.1195 | L8: =IF(AND(H8=0,I8=0,J8=0),"✗","✓") -> ✓ | M8: =AVERAGE(F8,K8) -> 58.20925 | N8: =IFERROR(M8/'01_PARÂMETROS'!$B$9,"") -> 1.164185 | O8: =IFERROR(MAX('01_PARÂMETROS'!$B$11,MIN('01_PARÂMETROS'!$B$12,N8)),"") -> 1.164185
A9: 01.12-1/01 | B9: Cultivo de algodão herbáceo | C9: 76.96 | D9: 54.81 | E9: 60.18 | F9: ='01_PARÂMETROS'!$B$4*D9+'01_PARÂMETROS'!$B$5*C9+'01_PARÂMETROS'!$B$6*E9 -> 63.368 | G9: =IF(AND(C9=0,D9=0,E9=0),"✗","✓") -> ✓ | H9: 58.36 | I9: 36.19 | J9: 52.58 | K9: ='01_PARÂMETROS'!$B$4*I9+'01_PARÂMETROS'!$B$5*H9+'01_PARÂMETROS'!$B$6*J9 -> 46.408 | L9: =IF(AND(H9=0,I9=0,J9=0),"✗","✓") -> ✓ | M9: =AVERAGE(F9,K9) -> 54.888 | N9: =IFERROR(M9/'01_PARÂMETROS'!$B$9,"") -> 1.09776 | O9: =IFERROR(MAX('01_PARÂMETROS'!$B$11,MIN('01_PARÂMETROS'!$B$12,N9)),"") -> 1.09776
A10: 01.12-1/02 | B10: Cultivo de juta | C10: 13.2 | D10: 56.71 | E10: 25.68 | F10: ='01_PARÂMETROS'!$B$4*D10+'01_PARÂMETROS'!$B$5*C10+'01_PARÂMETROS'!$B$6*E10 -> 36.827 | G10: =IF(AND(C10=0,D10=0,E10=0),"✗","✓") -> ✓ | H10: 0 | I10: 0 | J10: 0 | K10: 0 | L10: =IF(AND(H10=0,I10=0,J10=0),"✗","✓") -> ✗ | M10: =F10 -> 36.827 | N10: =IFERROR(M10/'01_PARÂMETROS'!$B$9,"") -> 0.73654 | O10: =IFERROR(MAX('01_PARÂMETROS'!$B$11,MIN('01_PARÂMETROS'!$B$12,N10)),"") -> 0.75
A11: 01.12-1/99 | B11: Cultivo de outras fibras de lavoura temporária não especificadas anteriormente | C11: 0 | D11: 0 | E11: 0 | F11: 0 | G11: =IF(AND(C11=0,D11=0,E11=0),"✗","✓") -> ✗ | H11: 0 | I11: 0 | J11: 0 | K11: 0 | L11: =IF(AND(H11=0,I11=0,J11=0),"✗","✓") -> ✗
A12: 01.13-0/00 | B12: Cultivo de cana-de-açúcar | C12: 69.82 | D12: 72.49 | E12: 69.86 | F12: ='01_PARÂMETROS'!$B$4*D12+'01_PARÂMETROS'!$B$5*C12+'01_PARÂMETROS'!$B$6*E12 -> 71.161 | G12: =IF(AND(C12=0,D12=0,E12=0),"✗","✓") -> ✓ | H12: 70.46 | I12: 69.6 | J12: 65.46 | K12: ='01_PARÂMETROS'!$B$4*I12+'01_PARÂMETROS'!$B$5*H12+'01_PARÂMETROS'!$B$6*J12 -> 69.28 | L12: =IF(AND(H12=0,I12=0,J12=0),"✗","✓") -> ✓ | M12: =AVERAGE(F12,K12) -> 70.2205 | N12: =IFERROR(M12/'01_PARÂMETROS'!$B$9,"") -> 1.40441 | O12: =IFERROR(MAX('01_PARÂMETROS'!$B$11,MIN('01_PARÂMETROS'!$B$12,N12)),"") -> 1.4
A13: 01.14-8/00 | B13: Cultivo de fumo | C13: 70.44 | D13: 53.7 | E13: 22.59 | F13: ='01_PARÂMETROS'!$B$4*D13+'01_PARÂMETROS'!$B$5*C13+'01_PARÂMETROS'!$B$6*E13 -> 54.8925 | G13: =IF(AND(C13=0,D13=0,E13=0),"✗","✓") -> ✓ | H13: 76.12 | I13: 52.78 | J13: 43.96 | K13: ='01_PARÂMETROS'!$B$4*I13+'01_PARÂMETROS'!$B$5*H13+'01_PARÂMETROS'!$B$6*J13 -> 59.626 | L13: =IF(AND(H13=0,I13=0,J13=0),"✗","✓") -> ✓ | M13: =AVERAGE(F13,K13) -> 57.25925 | N13: =IFERROR(M13/'01_PARÂMETROS'!$B$9,"") -> 1.145185 | O13: =IFERROR(MAX('01_PARÂMETROS'!$B$11,MIN('01_PARÂMETROS'!$B$12,N13)),"") -> 1.145185
A14: 01.15-6/00 | B14: Cultivo de soja | C14: 77.89 | D14: 48.71 | E14: 39.88 | F14: ='01_PARÂMETROS'!$B$4*D14+'01_PARÂMETROS'!$B$5*C14+'01_PARÂMETROS'!$B$6*E14 -> 57.5985 | G14: =IF(AND(C14=0,D14=0,E14=0),"✗","✓") -> ✓ | H14: 77.9 | I14: 52.22 | J14: 39.14 | K14: ='01_PARÂMETROS'!$B$4*I14+'01_PARÂMETROS'!$B$5*H14+'01_PARÂMETROS'!$B$6*J14 -> 59.246 | L14: =IF(AND(H14=0,I14=0,J14=0),"✗","✓") -> ✓ | M14: =AVERAGE(F14,K14) -> 58.42225 | N14: =IFERROR(M14/'01_PARÂMETROS'!$B$9,"") -> 1.168445 | O14: =IFERROR(MAX('01_PARÂMETROS'!$B$11,MIN('01_PARÂMETROS'!$B$12,N14)),"") -> 1.168445
A15: 01.16-4/01 | B15: Cultivo de amendoim | C15: 55.01 | D15: 66.7 | E15: 6.97 | F15: ='01_PARÂMETROS'!$B$4*D15+'01_PARÂMETROS'!$B$5*C15+'01_PARÂMETROS'!$B$6*E15 -> 53.649 | G15: =IF(AND(C15=0,D15=0,E15=0),"✗","✓") -> ✓ | H15: 0 | I15: 0 | J15: 0 | K15: 0 | L15: =IF(AND(H15=0,I15=0,J15=0),"✗","✓") -> ✗ | M15: =F15 -> 53.649 | N15: =IFERROR(M15/'01_PARÂMETROS'!$B$9,"") -> 1.07298 | O15: =IFERROR(MAX('01_PARÂMETROS'!$B$11,MIN('01_PARÂMETROS'!$B$12,N15)),"") -> 1.07298
A16: 01.16-4/02 | B16: Cultivo de girassol | C16: 0 | D16: 0 | E16: 0 | F16: 0 | G16: =IF(AND(C16=0,D16=0,E16=0),"✗","✓") -> ✗ | H16: 0 | I16: 0 | J16: 0 | K16: 0 | L16: =IF(AND(H16=0,I16=0,J16=0),"✗","✓") -> ✗
A17: 01.16-4/03 | B17: Cultivo de mamona | C17: 0 | D17: 0 | E17: 0 | F17: 0 | G17: =IF(AND(C17=0,D17=0,E17=0),"✗","✓") -> ✗ | H17: 0 | I17: 0 | J17: 0 | K17: 0 | L17: =IF(AND(H17=0,I17=0,J17=0),"✗","✓") -> ✗
A18: 01.16-4/99 | B18: Cultivo de outras oleaginosas de lavoura temporária não especificadas anteriormente | C18: 11.5 | D18: 8.36 | E18: 6.65 | F18: ='01_PARÂMETROS'!$B$4*D18+'01_PARÂMETROS'!$B$5*C18+'01_PARÂMETROS'!$B$6*E18 -> 9.2025 | G18: =IF(AND(C18=0,D18=0,E18=0),"✗","✓") -> ✓ | H18: 8.2 | I18: 33.75 | J18: 68.62 | K18: ='01_PARÂMETROS'!$B$4*I18+'01_PARÂMETROS'!$B$5*H18+'01_PARÂMETROS'!$B$6*J18 -> 30.038 | L18: =IF(AND(H18=0,I18=0,J18=0),"✗","✓") -> ✓ | M18: =AVERAGE(F18,K18) -> 19.62025 | N18: =IFERROR(M18/'01_PARÂMETROS'!$B$9,"") -> 0.392405 | O18: =IFERROR(MAX('01_PARÂMETROS'!$B$11,MIN('01_PARÂMETROS'!$B$12,N18)),"") -> 0.75
A19: 01.19-9/01 | B19: Cultivo de abacaxi | C19: 0 | D19: 0 | E19: 0 | F19: 0 | G19: =IF(AND(C19=0,D19=0,E19=0),"✗","✓") -> ✗ | H19: 0 | I19: 0 | J19: 0 | K19: 0 | L19: =IF(AND(H19=0,I19=0,J19=0),"✗","✓") -> ✗
A20: 01.19-9/02 | B20: Cultivo de alho | C20: 18.55 | D20: 22.7 | E20: 9.11 | F20: ='01_PARÂMETROS'!$B$4*D20+'01_PARÂMETROS'!$B$5*C20+'01_PARÂMETROS'!$B$6*E20 -> 19.209 | G20: =IF(AND(C20=0,D20=0,E20=0),"✗","✓") -> ✓ | H20: 22.7 | I20: 21.9 | J20: 6.66 | K20: ='01_PARÂMETROS'!$B$4*I20+'01_PARÂMETROS'!$B$5*H20+'01_PARÂMETROS'!$B$6*J20 -> 19.894 | L20: =IF(AND(H20=0,I20=0,J20=0),"✗","✓") -> ✓ | M20: =AVERAGE(F20,K20) -> 19.5515 | N20: =IFERROR(M20/'01_PARÂMETROS'!$B$9,"") -> 0.39103 | O20: =IFERROR(MAX('01_PARÂMETROS'!$B$11,MIN('01_PARÂMETROS'!$B$12,N20)),"") -> 0.75
A21: 01.19-9/03 | B21: Cultivo de batata-inglesa | C21: 32.52 | D21: 62.02 | E21: 70.02 | F21: ='01_PARÂMETROS'!$B$4*D21+'01_PARÂMETROS'!$B$5*C21+'01_PARÂMETROS'!$B$6*E21 -> 52.895 | G21: =IF(AND(C21=0,D21=0,E21=0),"✗","✓") -> ✓ | H21: 54.1 | I21: 70.07 | J21: 58.43 | K21: ='01_PARÂMETROS'!$B$4*I21+'01_PARÂMETROS'!$B$5*H21+'01_PARÂMETROS'!$B$6*J21 -> 62.7345 | L21: =IF(AND(H21=0,I21=0,J21=0),"✗","✓") -> ✓ | M21: =AVERAGE(F21,K21) -> 57.81475 | N21: =IFERROR(M21/'01_PARÂMETROS'!$B$9,"") -> 1.156295 | O21: =IFERROR(MAX('01_PARÂMETROS'!$B$11,MIN('01_PARÂMETROS'!$B$12,N21)),"") -> 1.156295
A22: 01.19-9/04 | B22: Cultivo de cebola | C22: 9.79 | D22: 0 | E22: 0 | F22: ='01_PARÂMETROS'!$B$4*D22+'01_PARÂMETROS'!$B$5*C22+'01_PARÂMETROS'!$B$6*E22 -> 3.4265 | G22: =IF(AND(C22=0,D22=0,E22=0),"✗","✓") -> ✓ | H22: 25.34 | I22: 51.28 | J22: 12.91 | K22: ='01_PARÂMETROS'!$B$4*I22+'01_PARÂMETROS'!$B$5*H22+'01_PARÂMETROS'!$B$6*J22 -> 36.4455 | L22: =IF(AND(H22=0,I22=0,J22=0),"✗","✓") -> ✓ | M22: =AVERAGE(F22,K22) -> 19.936 | N22: =IFERROR(M22/'01_PARÂMETROS'!$B$9,"") -> 0.39872 | O22: =IFERROR(MAX('01_PARÂMETROS'!$B$11,MIN('01_PARÂMETROS'!$B$12,N22)),"") -> 0.75
A23: 01.19-9/05 | B23: Cultivo de feijão | C23: 46.4 | D23: 33.72 | E23: 90.24 | F23: ='01_PARÂMETROS'!$B$4*D23+'01_PARÂMETROS'!$B$5*C23+'01_PARÂMETROS'!$B$6*E23 -> 46.636 | G23: =IF(AND(C23=0,D23=0,E23=0),"✗","✓") -> ✓ | H23: 46.27 | I23: 33.27 | J23: 86.4 | K23: ='01_PARÂMETROS'!$B$4*I23+'01_PARÂMETROS'!$B$5*H23+'01_PARÂMETROS'!$B$6*J23 -> 45.7895 | L23: =IF(AND(H23=0,I23=0,J23=0),"✗","✓") -> ✓ | M23: =AVERAGE(F23,K23) -> 46.21275 | N23: =IFERROR(M23/'01_PARÂMETROS'!$B$9,"") -> 0.924255 | O23: =IFERROR(MAX('01_PARÂMETROS'!$B$11,MIN('01_PARÂMETROS'!$B$12,N23)),"") -> 0.924255
A24: 01.19-9/06 | B24: Cultivo de mandioca | C24: 20.11 | D24: 0 | E24: 0 | F24: ='01_PARÂMETROS'!$B$4*D24+'01_PARÂMETROS'!$B$5*C24+'01_PARÂMETROS'!$B$6*E24 -> 7.0385 | G24: =IF(AND(C24=0,D24=0,E24=0),"✗","✓") -> ✓ | H24: 33.01 | I24: 9.27 | J24: 18.28 | K24: ='01_PARÂMETROS'!$B$4*I24+'01_PARÂMETROS'!$B$5*H24+'01_PARÂMETROS'!$B$6*J24 -> 18.9305 | L24: =IF(AND(H24=0,I24=0,J24=0),"✗","✓") -> ✓ | M24: =AVERAGE(F24,K24) -> 12.9845 | N24: =IFERROR(M24/'01_PARÂMETROS'!$B$9,"") -> 0.25969 | O24: =IFERROR(MAX('01_PARÂMETROS'!$B$11,MIN('01_PARÂMETROS'!$B$12,N24)),"") -> 0.75
A25: 01.19-9/07 | B25: Cultivo de melão | C25: 69.59 | D25: 46.8 | E25: 50.98 | F25: ='01_PARÂMETROS'!$B$4*D25+'01_PARÂMETROS'!$B$5*C25+'01_PARÂMETROS'!$B$6*E25 -> 55.4035 | G25: =IF(AND(C25=0,D25=0,E25=0),"✗","✓") -> ✓ | H25: 61.7 | I25: 35.09 | J25: 48.07 | K25: ='01_PARÂMETROS'!$B$4*I25+'01_PARÂMETROS'!$B$5*H25+'01_PARÂMETROS'!$B$6*J25 -> 46.3505 | L25: =IF(AND(H25=0,I25=0,J25=0),"✗","✓") -> ✓ | M25: =AVERAGE(F25,K25) -> 50.877 | N25: =IFERROR(M25/'01_PARÂMETROS'!$B$9,"") -> 1.01754 | O25: =IFERROR(MAX('01_PARÂMETROS'!$B$11,MIN('01_PARÂMETROS'!$B$12,N25)),"") -> 1.01754
A26: 01.19-9/08 | B26: Cultivo de melancia | C26: 0 | D26: 0 | E26: 0 | F26: 0 | G26: =IF(AND(C26=0,D26=0,E26=0),"✗","✓") -> ✗ | H26: 0 | I26: 0 | J26: 0 | K26: 0 | L26: =IF(AND(H26=0,I26=0,J26=0),"✗","✓") -> ✗
A27: 01.19-9/09 | B27: Cultivo de tomate rasteiro | C27: 13.82 | D27: 12.08 | E27: 8.4 | F27: ='01_PARÂMETROS'!$B$4*D27+'01_PARÂMETROS'!$B$5*C27+'01_PARÂMETROS'!$B$6*E27 -> 12.137 | G27: =IF(AND(C27=0,D27=0,E27=0),"✗","✓") -> ✓ | H27: 12 | I27: 12.03 | J27: 7.22 | K27: ='01_PARÂMETROS'!$B$4*I27+'01_PARÂMETROS'!$B$5*H27+'01_PARÂMETROS'!$B$6*J27 -> 11.298 | L27: =IF(AND(H27=0,I27=0,J27=0),"✗","✓") -> ✓ | M27: =AVERAGE(F27,K27) -> 11.7175 | N27: =IFERROR(M27/'01_PARÂMETROS'!$B$9,"") -> 0.23435 | O27: =IFERROR(MAX('01_PARÂMETROS'!$B$11,MIN('01_PARÂMETROS'!$B$12,N27)),"") -> 0.75
A28: 01.19-9/99 | B28: Cultivo de outras plantas de lavoura temporária não especificadas anteriormente | C28: 76.49 | D28: 65.51 | E28: 67.24 | F28: ='01_PARÂMETROS'!$B$4*D28+'01_PARÂMETROS'!$B$5*C28+'01_PARÂMETROS'!$B$6*E28 -> 69.6125 | G28: =IF(AND(C28=0,D28=0,E28=0),"✗","✓") -> ✓ | H28: 79.99 | I28: 48.59 | J28: 45.31 | K28: ='01_PARÂMETROS'!$B$4*I28+'01_PARÂMETROS'!$B$5*H28+'01_PARÂMETROS'!$B$6*J28 -> 59.088 | L28: =IF(AND(H28=0,I28=0,J28=0),"✗","✓") -> ✓ | M28: =AVERAGE(F28,K28) -> 64.35025 | N28: =IFERROR(M28/'01_PARÂMETROS'!$B$9,"") -> 1.287005 | O28: =IFERROR(MAX('01_PARÂMETROS'!$B$11,MIN('01_PARÂMETROS'!$B$12,N28)),"") -> 1.287005
A29: 01.21-1/01 | B29: Horticultura, exceto morango | C29: 34.69 | D29: 29.28 | E29: 34.65 | F29: ='01_PARÂMETROS'!$B$4*D29+'01_PARÂMETROS'!$B$5*C29+'01_PARÂMETROS'!$B$6*E29 -> 31.979 | G29: =IF(AND(C29=0,D29=0,E29=0),"✗","✓") -> ✓ | H29: 40.3 | I29: 32.09 | J29: 32.9 | K29: ='01_PARÂMETROS'!$B$4*I29+'01_PARÂMETROS'!$B$5*H29+'01_PARÂMETROS'!$B$6*J29 -> 35.085 | L29: =IF(AND(H29=0,I29=0,J29=0),"✗","✓") -> ✓ | M29: =AVERAGE(F29,K29) -> 33.532 | N29: =IFERROR(M29/'01_PARÂMETROS'!$B$9,"") -> 0.67064 | O29: =IFERROR(MAX('01_PARÂMETROS'!$B$11,MIN('01_PARÂMETROS'!$B$12,N29)),"") -> 0.75
A30: 01.21-1/02 | B30: Cultivo de morango | C30: 39.96 | D30: 9.94 | E30: 6.73 | F30: ='01_PARÂMETROS'!$B$4*D30+'01_PARÂMETROS'!$B$5*C30+'01_PARÂMETROS'!$B$6*E30 -> 19.9655 | G30: =IF(AND(C30=0,D30=0,E30=0),"✗","✓") -> ✓ | H30: 62.94 | I30: 71.88 | J30: 84.27 | K30: ='01_PARÂMETROS'!$B$4*I30+'01_PARÂMETROS'!$B$5*H30+'01_PARÂMETROS'!$B$6*J30 -> 70.6095 | L30: =IF(AND(H30=0,I30=0,J30=0),"✗","✓") -> ✓ | M30: =AVERAGE(F30,K30) -> 45.2875 | N30: =IFERROR(M30/'01_PARÂMETROS'!$B$9,"") -> 0.90575 | O30: =IFERROR(MAX('01_PARÂMETROS'!$B$11,MIN('01_PARÂMETROS'!$B$12,N30)),"") -> 0.90575
A31: 01.22-9/00 | B31: Cultivo de flores e plantas ornamentais | C31: 23.36 | D31: 37.85 | E31: 56.69 | F31: ='01_PARÂMETROS'!$B$4*D31+'01_PARÂMETROS'!$B$5*C31+'01_PARÂMETROS'!$B$6*E31 -> 35.6045 | G31: =IF(AND(C31=0,D31=0,E31=0),"✗","✓") -> ✓ | H31: 27.43 | I31: 33.67 | J31: 73.13 | K31: ='01_PARÂMETROS'!$B$4*I31+'01_PARÂMETROS'!$B$5*H31+'01_PARÂMETROS'!$B$6*J31 -> 37.405 | L31: =IF(AND(H31=0,I31=0,J31=0),"✗","✓") -> ✓ | M31: =AVERAGE(F31,K31) -> 36.50475 | N31: =IFERROR(M31/'01_PARÂMETROS'!$B$9,"") -> 0.730095 | O31: =IFERROR(MAX('01_PARÂMETROS'!$B$11,MIN('01_PARÂMETROS'!$B$12,N31)),"") -> 0.75
A32: 01.31-8/00 | B32: Cultivo de laranja | C32: 71.14 | D32: 72.8 | E32: 70.18 | F32: ='01_PARÂMETROS'!$B$4*D32+'01_PARÂMETROS'!$B$5*C32+'01_PARÂMETROS'!$B$6*E32 -> 71.826 | G32: =IF(AND(C32=0,D32=0,E32=0),"✗","✓") -> ✓ | H32: 80.77 | I32: 74.17 | J32: 67.83 | K32: ='01_PARÂMETROS'!$B$4*I32+'01_PARÂMETROS'!$B$5*H32+'01_PARÂMETROS'!$B$6*J32 -> 75.529 | L32: =IF(AND(H32=0,I32=0,J32=0),"✗","✓") -> ✓ | M32: =AVERAGE(F32,K32) -> 73.6775 | N32: =IFERROR(M32/'01_PARÂMETROS'!$B$9,"") -> 1.47355 | O32: =IFERROR(MAX('01_PARÂMETROS'!$B$11,MIN('01_PARÂMETROS'!$B$12,N32)),"") -> 1.4
A33: 01.32-6/00 | B33: Cultivo de uva | C33: 70.13 | D33: 52.11 | E33: 40.91 | F33: ='01_PARÂMETROS'!$B$4*D33+'01_PARÂMETROS'!$B$5*C33+'01_PARÂMETROS'!$B$6*E33 -> 56.737 | G33: =IF(AND(C33=0,D33=0,E33=0),"✗","✓") -> ✓ | H33: 76.97 | I33: 49.14 | J33: 42.62 | K33: ='01_PARÂMETROS'!$B$4*I33+'01_PARÂMETROS'!$B$5*H33+'01_PARÂMETROS'!$B$6*J33 -> 57.9025 | L33: =IF(AND(H33=0,I33=0,J33=0),"✗","✓") -> ✓ | M33: =AVERAGE(F33,K33) -> 57.31975 | N33: =IFERROR(M33/'01_PARÂMETROS'!$B$9,"") -> 1.146395 | O33: =IFERROR(MAX('01_PARÂMETROS'!$B$11,MIN('01_PARÂMETROS'!$B$12,N33)),"") -> 1.146395
A34: 01.33-4/01 | B34: Cultivo de açaí | C34: 18.94 | D34: 38.88 | E34: 5.14 | F34: ='01_PARÂMETROS'!$B$4*D34+'01_PARÂMETROS'!$B$5*C34+'01_PARÂMETROS'!$B$6*E34 -> 26.84 | G34: =IF(AND(C34=0,D34=0,E34=0),"✗","✓") -> ✓ | H34: 39.83 | I34: 60.67 | J34: 11.96 | K34: ='01_PARÂMETROS'!$B$4*I34+'01_PARÂMETROS'!$B$5*H34+'01_PARÂMETROS'!$B$6*J34 -> 46.0695 | L34: =IF(AND(H34=0,I34=0,J34=0),"✗","✓") -> ✓ | M34: =AVERAGE(F34,K34) -> 36.45475 | N34: =IFERROR(M34/'01_PARÂMETROS'!$B$9,"") -> 0.729095 | O34: =IFERROR(MAX('01_PARÂMETROS'!$B$11,MIN('01_PARÂMETROS'!$B$12,N34)),"") -> 0.75
A35: 01.33-4/02 | B35: Cultivo de banana | C35: 72.69 | D35: 63.05 | E35: 38.22 | F35: ='01_PARÂMETROS'!$B$4*D35+'01_PARÂMETROS'!$B$5*C35+'01_PARÂMETROS'!$B$6*E35 -> 62.6995 | G35: =IF(AND(C35=0,D35=0,E35=0),"✗","✓") -> ✓ | H35: 74.33 | I35: 65.49 | J35: 29.03 | K35: ='01_PARÂMETROS'!$B$4*I35+'01_PARÂMETROS'!$B$5*H35+'01_PARÂMETROS'!$B$6*J35 -> 63.115 | L35: =IF(AND(H35=0,I35=0,J35=0),"✗","✓") -> ✓ | M35: =AVERAGE(F35,K35) -> 62.90725 | N35: =IFERROR(M35/'01_PARÂMETROS'!$B$9,"") -> 1.258145 | O35: =IFERROR(MAX('01_PARÂMETROS'!$B$11,MIN('01_PARÂMETROS'!$B$12,N35)),"") -> 1.258145
A36: 01.33-4/03 | B36: Cultivo de caju | C36: 73.78 | D36: 98.89 | E36: 99.6 | F36: ='01_PARÂMETROS'!$B$4*D36+'01_PARÂMETROS'!$B$5*C36+'01_PARÂMETROS'!$B$6*E36 -> 90.208 | G36: =IF(AND(C36=0,D36=0,E36=0),"✗","✓") -> ✓ | H36: 69.22 | I36: 90.12 | J36: 99.36 | K36: ='01_PARÂMETROS'!$B$4*I36+'01_PARÂMETROS'!$B$5*H36+'01_PARÂMETROS'!$B$6*J36 -> 84.191 | L36: =IF(AND(H36=0,I36=0,J36=0),"✗","✓") -> ✓ | M36: =AVERAGE(F36,K36) -> 87.1995 | N36: =IFERROR(M36/'01_PARÂMETROS'!$B$9,"") -> 1.74399 | O36: =IFERROR(MAX('01_PARÂMETROS'!$B$11,MIN('01_PARÂMETROS'!$B$12,N36)),"") -> 1.4
A37: 01.33-4/04 | B37: Cultivo de cítricos, exceto laranja | C37: 39.88 | D37: 41.97 | E37: 14.82 | F37: ='01_PARÂMETROS'!$B$4*D37+'01_PARÂMETROS'!$B$5*C37+'01_PARÂMETROS'!$B$6*E37 -> 37.166 | G37: =IF(AND(C37=0,D37=0,E37=0),"✗","✓") -> ✓ | H37: 45.41 | I37: 44.17 | J37: 15.04 | K37: ='01_PARÂMETROS'!$B$4*I37+'01_PARÂMETROS'!$B$5*H37+'01_PARÂMETROS'!$B$6*J37 -> 40.2345 | L37: =IF(AND(H37=0,I37=0,J37=0),"✗","✓") -> ✓ | M37: =AVERAGE(F37,K37) -> 38.70025 | N37: =IFERROR(M37/'01_PARÂMETROS'!$B$9,"") -> 0.774005 | O37: =IFERROR(MAX('01_PARÂMETROS'!$B$11,MIN('01_PARÂMETROS'!$B$12,N37)),"") -> 0.774005
A38: 01.33-4/05 | B38: Cultivo de coco-da-baía | C38: 86.96 | D38: 49.18 | E38: 54.08 | F38: ='01_PARÂMETROS'!$B$4*D38+'01_PARÂMETROS'!$B$5*C38+'01_PARÂMETROS'!$B$6*E38 -> 63.138 | G38: =IF(AND(C38=0,D38=0,E38=0),"✗","✓") -> ✓ | H38: 88.06 | I38: 58.7 | J38: 52.74 | K38: ='01_PARÂMETROS'!$B$4*I38+'01_PARÂMETROS'!$B$5*H38+'01_PARÂMETROS'!$B$6*J38 -> 68.082 | L38: =IF(AND(H38=0,I38=0,J38=0),"✗","✓") -> ✓ | M38: =AVERAGE(F38,K38) -> 65.61 | N38: =IFERROR(M38/'01_PARÂMETROS'!$B$9,"") -> 1.3122 | O38: =IFERROR(MAX('01_PARÂMETROS'!$B$11,MIN('01_PARÂMETROS'!$B$12,N38)),"") -> 1.3122
A39: 01.33-4/06 | B39: Cultivo de guaraná | C39: 0 | D39: 0 | E39: 0 | F39: 0 | G39: =IF(AND(C39=0,D39=0,E39=0),"✗","✓") -> ✗ | H39: 0 | I39: 0 | J39: 0 | K39: 0 | L39: =IF(AND(H39=0,I39=0,J39=0),"✗","✓") -> ✗
A40: 01.33-4/07 | B40: Cultivo de maçã | C40: 71.61 | D40: 82.56 | E40: 86.2 | F40: ='01_PARÂMETROS'!$B$4*D40+'01_PARÂMETROS'!$B$5*C40+'01_PARÂMETROS'!$B$6*E40 -> 79.2735 | G40: =IF(AND(C40=0,D40=0,E40=0),"✗","✓") -> ✓ | H40: 49.76 | I40: 52.7 | J40: 77.08 | K40: ='01_PARÂMETROS'!$B$4*I40+'01_PARÂMETROS'!$B$5*H40+'01_PARÂMETROS'!$B$6*J40 -> 55.328 | L40: =IF(AND(H40=0,I40=0,J40=0),"✗","✓") -> ✓ | M40: =AVERAGE(F40,K40) -> 67.30075 | N40: =IFERROR(M40/'01_PARÂMETROS'!$B$9,"") -> 1.346015 | O40: =IFERROR(MAX('01_PARÂMETROS'!$B$11,MIN('01_PARÂMETROS'!$B$12,N40)),"") -> 1.346015
A41: 01.33-4/08 | B41: Cultivo de mamão | C41: 75.25 | D41: 57.27 | E41: 43.69 | F41: ='01_PARÂMETROS'!$B$4*D41+'01_PARÂMETROS'!$B$5*C41+'01_PARÂMETROS'!$B$6*E41 -> 61.526 | G41: =IF(AND(C41=0,D41=0,E41=0),"✗","✓") -> ✓ | H41: 69.14 | I41: 47.57 | J41: 21.84 | K41: ='01_PARÂMETROS'!$B$4*I41+'01_PARÂMETROS'!$B$5*H41+'01_PARÂMETROS'!$B$6*J41 -> 51.26 | L41: =IF(AND(H41=0,I41=0,J41=0),"✗","✓") -> ✓ | M41: =AVERAGE(F41,K41) -> 56.393 | N41: =IFERROR(M41/'01_PARÂMETROS'!$B$9,"") -> 1.12786 | O41: =IFERROR(MAX('01_PARÂMETROS'!$B$11,MIN('01_PARÂMETROS'!$B$12,N41)),"") -> 1.12786
A42: 01.33-4/09 | B42: Cultivo de maracujá | C42: 38.33 | D42: 0 | E42: 0 | F42: ='01_PARÂMETROS'!$B$4*D42+'01_PARÂMETROS'!$B$5*C42+'01_PARÂMETROS'!$B$6*E42 -> 13.4155 | G42: =IF(AND(C42=0,D42=0,E42=0),"✗","✓") -> ✓ | H42: 75.57 | I42: 71.25 | J42: 14.57 | K42: ='01_PARÂMETROS'!$B$4*I42+'01_PARÂMETROS'!$B$5*H42+'01_PARÂMETROS'!$B$6*J42 -> 64.26 | L42: =IF(AND(H42=0,I42=0,J42=0),"✗","✓") -> ✓ | M42: =AVERAGE(F42,K42) -> 38.83775 | N42: =IFERROR(M42/'01_PARÂMETROS'!$B$9,"") -> 0.776755 | O42: =IFERROR(MAX('01_PARÂMETROS'!$B$11,MIN('01_PARÂMETROS'!$B$12,N42)),"") -> 0.776755
A43: 01.33-4/10 | B43: Cultivo de manga | C43: 43.37 | D43: 30.24 | E43: 40.67 | F43: ='01_PARÂMETROS'!$B$4*D43+'01_PARÂMETROS'!$B$5*C43+'01_PARÂMETROS'!$B$6*E43 -> 36.4 | G43: =IF(AND(C43=0,D43=0,E43=0),"✗","✓") -> ✓ | H43: 49.6 | I43: 36.59 | J43: 29.74 | K43: ='01_PARÂMETROS'!$B$4*I43+'01_PARÂMETROS'!$B$5*H43+'01_PARÂMETROS'!$B$6*J43 -> 40.116 | L43: =IF(AND(H43=0,I43=0,J43=0),"✗","✓") -> ✓ | M43: =AVERAGE(F43,K43) -> 38.258 | N43: =IFERROR(M43/'01_PARÂMETROS'!$B$9,"") -> 0.76516 | O43: =IFERROR(MAX('01_PARÂMETROS'!$B$11,MIN('01_PARÂMETROS'!$B$12,N43)),"") -> 0.76516
A44: 01.33-4/11 | B44: Cultivo de pêssego | C44: 0 | D44: 0 | E44: 0 | F44: 0 | G44: =IF(AND(C44=0,D44=0,E44=0),"✗","✓") -> ✗ | H44: 0 | I44: 0 | J44: 0 | K44: 0 | L44: =IF(AND(H44=0,I44=0,J44=0),"✗","✓") -> ✗
A45: 01.33-4/99 | B45: Cultivo de frutas de lavoura permanente não especificadas anteriormente | C45: 64.55 | D45: 45.06 | E45: 47.18 | F45: ='01_PARÂMETROS'!$B$4*D45+'01_PARÂMETROS'!$B$5*C45+'01_PARÂMETROS'!$B$6*E45 -> 52.1995 | G45: =IF(AND(C45=0,D45=0,E45=0),"✗","✓") -> ✓ | H45: 49.83 | I45: 36.27 | J45: 45.47 | K45: ='01_PARÂMETROS'!$B$4*I45+'01_PARÂMETROS'!$B$5*H45+'01_PARÂMETROS'!$B$6*J45 -> 42.396 | L45: =IF(AND(H45=0,I45=0,J45=0),"✗","✓") -> ✓ | M45: =AVERAGE(F45,K45) -> 47.29775 | N45: =IFERROR(M45/'01_PARÂMETROS'!$B$9,"") -> 0.945955 | O45: =IFERROR(MAX('01_PARÂMETROS'!$B$11,MIN('01_PARÂMETROS'!$B$12,N45)),"") -> 0.945955
A46: 01.34-2/00 | B46: Cultivo de café | C46: 80.91 | D46: 69.4 | E46: 63.36 | F46: ='01_PARÂMETROS'!$B$4*D46+'01_PARÂMETROS'!$B$5*C46+'01_PARÂMETROS'!$B$6*E46 -> 72.5225 | G46: =IF(AND(C46=0,D46=0,E46=0),"✗","✓") -> ✓ | H46: 78.98 | I46: 57.99 | J46: 44.2 | K46: ='01_PARÂMETROS'!$B$4*I46+'01_PARÂMETROS'!$B$5*H46+'01_PARÂMETROS'!$B$6*J46 -> 63.268 | L46: =IF(AND(H46=0,I46=0,J46=0),"✗","✓") -> ✓ | M46: =AVERAGE(F46,K46) -> 67.89525 | N46: =IFERROR(M46/'01_PARÂMETROS'!$B$9,"") -> 1.357905 | O46: =IFERROR(MAX('01_PARÂMETROS'!$B$11,MIN('01_PARÂMETROS'!$B$12,N46)),"") -> 1.357905
A47: 01.35-1/00 | B47: Cultivo de cacau | C47: 81.38 | D47: 78.83 | E47: 41.23 | F47: ='01_PARÂMETROS'!$B$4*D47+'01_PARÂMETROS'!$B$5*C47+'01_PARÂMETROS'!$B$6*E47 -> 74.0825 | G47: =IF(AND(C47=0,D47=0,E47=0),"✗","✓") -> ✓ | H47: 73.33 | I47: 43.22 | J47: 19.7 | K47: ='01_PARÂMETROS'!$B$4*I47+'01_PARÂMETROS'!$B$5*H47+'01_PARÂMETROS'!$B$6*J47 -> 50.2305 | L47: =IF(AND(H47=0,I47=0,J47=0),"✗","✓") -> ✓ | M47: =AVERAGE(F47,K47) -> 62.1565 | N47: =IFERROR(M47/'01_PARÂMETROS'!$B$9,"") -> 1.24313 | O47: =IFERROR(MAX('01_PARÂMETROS'!$B$11,MIN('01_PARÂMETROS'!$B$12,N47)),"") -> 1.24313
A48: 01.39-3/01 | B48: Cultivo de chá-da-índia | C48: 0 | D48: 0 | E48: 0 | F48: 0 | G48: =IF(AND(C48=0,D48=0,E48=0),"✗","✓") -> ✗ | H48: 0 | I48: 0 | J48: 0 | K48: 0 | L48: =IF(AND(H48=0,I48=0,J48=0),"✗","✓") -> ✗
A49: 01.39-3/02 | B49: Cultivo de erva-mate | C49: 38.57 | D49: 83.35 | E49: 17.2 | F49: ='01_PARÂMETROS'!$B$4*D49+'01_PARÂMETROS'!$B$5*C49+'01_PARÂMETROS'!$B$6*E49 -> 57.7545 | G49: =IF(AND(C49=0,D49=0,E49=0),"✗","✓") -> ✓ | H49: 20.99 | I49: 45.51 | J49: 8.4 | K49: ='01_PARÂMETROS'!$B$4*I49+'01_PARÂMETROS'!$B$5*H49+'01_PARÂMETROS'!$B$6*J49 -> 31.3615 | L49: =IF(AND(H49=0,I49=0,J49=0),"✗","✓") -> ✓ | M49: =AVERAGE(F49,K49) -> 44.558 | N49: =IFERROR(M49/'01_PARÂMETROS'!$B$9,"") -> 0.89116 | O49: =IFERROR(MAX('01_PARÂMETROS'!$B$11,MIN('01_PARÂMETROS'!$B$12,N49)),"") -> 0.89116
A50: 01.39-3/03 | B50: Cultivo de pimenta-do-reino | C50: 94.1 | D50: 83.03 | E50: 14.66 | F50: ='01_PARÂMETROS'!$B$4*D50+'01_PARÂMETROS'!$B$5*C50+'01_PARÂMETROS'!$B$6*E50 -> 76.649 | G50: =IF(AND(C50=0,D50=0,E50=0),"✗","✓") -> ✓ | H50: 0 | I50: 0 | J50: 0 | K50: 0 | L50: =IF(AND(H50=0,I50=0,J50=0),"✗","✓") -> ✗ | M50: =F50 -> 76.649 | N50: =IFERROR(M50/'01_PARÂMETROS'!$B$9,"") -> 1.53298 | O50: =IFERROR(MAX('01_PARÂMETROS'!$B$11,MIN('01_PARÂMETROS'!$B$12,N50)),"") -> 1.4
A51: 01.39-3/04 | B51: Cultivo de plantas para condimento, exceto pimenta-do-reino | C51: 0 | D51: 0 | E51: 0 | F51: 0 | G51: =IF(AND(C51=0,D51=0,E51=0),"✗","✓") -> ✗ | H51: 81.54 | I51: 0 | J51: 0 | K51: ='01_PARÂMETROS'!$B$4*I51+'01_PARÂMETROS'!$B$5*H51+'01_PARÂMETROS'!$B$6*J51 -> 28.539 | L51: =IF(AND(H51=0,I51=0,J51=0),"✗","✓") -> ✓ | M51: =K51 -> 28.539 | N51: =IFERROR(M51/'01_PARÂMETROS'!$B$9,"") -> 0.57078 | O51: =IFERROR(MAX('01_PARÂMETROS'!$B$11,MIN('01_PARÂMETROS'!$B$12,N51)),"") -> 0.75
A52: 01.39-3/05 | B52: Cultivo de dendê | C52: 95.96 | D52: 65.99 | E52: 48.37 | F52: ='01_PARÂMETROS'!$B$4*D52+'01_PARÂMETROS'!$B$5*C52+'01_PARÂMETROS'!$B$6*E52 -> 73.8365 | G52: =IF(AND(C52=0,D52=0,E52=0),"✗","✓") -> ✓ | H52: 70.53 | I52: 67.23 | J52: 50.52 | K52: ='01_PARÂMETROS'!$B$4*I52+'01_PARÂMETROS'!$B$5*H52+'01_PARÂMETROS'!$B$6*J52 -> 65.8785 | L52: =IF(AND(H52=0,I52=0,J52=0),"✗","✓") -> ✓ | M52: =AVERAGE(F52,K52) -> 69.8575 | N52: =IFERROR(M52/'01_PARÂMETROS'!$B$9,"") -> 1.39715 | O52: =IFERROR(MAX('01_PARÂMETROS'!$B$11,MIN('01_PARÂMETROS'!$B$12,N52)),"") -> 1.39715
A53: 01.39-3/06 | B53: Cultivo de seringueira | C53: 22.98 | D53: 13.19 | E53: 8.08 | F53: ='01_PARÂMETROS'!$B$4*D53+'01_PARÂMETROS'!$B$5*C53+'01_PARÂMETROS'!$B$6*E53 -> 15.85 | G53: =IF(AND(C53=0,D53=0,E53=0),"✗","✓") -> ✓ | H53: 17.97 | I53: 14.16 | J53: 11.4 | K53: ='01_PARÂMETROS'!$B$4*I53+'01_PARÂMETROS'!$B$5*H53+'01_PARÂMETROS'!$B$6*J53 -> 15.0795 | L53: =IF(AND(H53=0,I53=0,J53=0),"✗","✓") -> ✓ | M53: =AVERAGE(F53,K53) -> 15.46475 | N53: =IFERROR(M53/'01_PARÂMETROS'!$B$9,"") -> 0.309295 | O53: =IFERROR(MAX('01_PARÂMETROS'!$B$11,MIN('01_PARÂMETROS'!$B$12,N53)),"") -> 0.75
A54: 01.39-3/99 | B54: Cultivo de outras plantas de lavoura permanente não especificadas anteriormente | C54: 53.69 | D54: 65.35 | E54: 46.3 | F54: ='01_PARÂMETROS'!$B$4*D54+'01_PARÂMETROS'!$B$5*C54+'01_PARÂMETROS'!$B$6*E54 -> 58.4115 | G54: =IF(AND(C54=0,D54=0,E54=0),"✗","✓") -> ✓ | H54: 46.04 | I54: 67.31 | J54: 20.26 | K54: ='01_PARÂMETROS'!$B$4*I54+'01_PARÂMETROS'!$B$5*H54+'01_PARÂMETROS'!$B$6*J54 -> 52.808 | L54: =IF(AND(H54=0,I54=0,J54=0),"✗","✓") -> ✓ | M54: =AVERAGE(F54,K54) -> 55.60975 | N54: =IFERROR(M54/'01_PARÂMETROS'!$B$9,"") -> 1.112195 | O54: =IFERROR(MAX('01_PARÂMETROS'!$B$11,MIN('01_PARÂMETROS'!$B$12,N54)),"") -> 1.112195
A55: 01.41-5/01 | B55: Produção de sementes certificadas, exceto de forrageiras para pasto | C55: 44.54 | D55: 36.1 | E55: 27.67 | F55: ='01_PARÂMETROS'!$B$4*D55+'01_PARÂMETROS'!$B$5*C55+'01_PARÂMETROS'!$B$6*E55 -> 37.7895 | G55: =IF(AND(C55=0,D55=0,E55=0),"✗","✓") -> ✓ | H55: 40.07 | I55: 26.56 | J55: 23.1 | K55: ='01_PARÂMETROS'!$B$4*I55+'01_PARÂMETROS'!$B$5*H55+'01_PARÂMETROS'!$B$6*J55 -> 30.7695 | L55: =IF(AND(H55=0,I55=0,J55=0),"✗","✓") -> ✓ | M55: =AVERAGE(F55,K55) -> 34.2795 | N55: =IFERROR(M55/'01_PARÂMETROS'!$B$9,"") -> 0.68559 | O55: =IFERROR(MAX('01_PARÂMETROS'!$B$11,MIN('01_PARÂMETROS'!$B$12,N55)),"") -> 0.75
A56: 01.41-5/02 | B56: Produção de sementes certificadas de forrageiras para formação de pasto | C56: 88.05 | D56: 88.26 | E56: 50.19 | F56: ='01_PARÂMETROS'!$B$4*D56+'01_PARÂMETROS'!$B$5*C56+'01_PARÂMETROS'!$B$6*E56 -> 82.476 | G56: =IF(AND(C56=0,D56=0,E56=0),"✗","✓") -> ✓ | H56: 82.47 | I56: 53.8 | J56: 38.67 | K56: ='01_PARÂMETROS'!$B$4*I56+'01_PARÂMETROS'!$B$5*H56+'01_PARÂMETROS'!$B$6*J56 -> 61.565 | L56: =IF(AND(H56=0,I56=0,J56=0),"✗","✓") -> ✓ | M56: =AVERAGE(F56,K56) -> 72.0205 | N56: =IFERROR(M56/'01_PARÂMETROS'!$B$9,"") -> 1.44041 | O56: =IFERROR(MAX('01_PARÂMETROS'!$B$11,MIN('01_PARÂMETROS'!$B$12,N56)),"") -> 1.4
A57: 01.42-3/00 | B57: Produção de mudas e outras formas de propagação vegetal, certificadas | C57: 54.78 | D57: 35.71 | E57: 55.58 | F57: ='01_PARÂMETROS'!$B$4*D57+'01_PARÂMETROS'!$B$5*C57+'01_PARÂMETROS'!$B$6*E57 -> 45.365 | G57: =IF(AND(C57=0,D57=0,E57=0),"✗","✓") -> ✓ | H57: 49.37 | I57: 21.98 | J57: 9.19 | K57: ='01_PARÂMETROS'!$B$4*I57+'01_PARÂMETROS'!$B$5*H57+'01_PARÂMETROS'!$B$6*J57 -> 29.648 | L57: =IF(AND(H57=0,I57=0,J57=0),"✗","✓") -> ✓ | M57: =AVERAGE(F57,K57) -> 37.5065 | N57: =IFERROR(M57/'01_PARÂMETROS'!$B$9,"") -> 0.75013 | O57: =IFERROR(MAX('01_PARÂMETROS'!$B$11,MIN('01_PARÂMETROS'!$B$12,N57)),"") -> 0.75013
A58: 01.51-2/01 | B58: Criação de bovinos para corte | C58: 91.46 | D58: 86.84 | E58: 60.66 | F58: ='01_PARÂMETROS'!$B$4*D58+'01_PARÂMETROS'!$B$5*C58+'01_PARÂMETROS'!$B$6*E58 -> 84.53 | G58: =IF(AND(C58=0,D58=0,E58=0),"✗","✓") -> ✓ | H58: 91.39 | I58: 86.41 | J58: 56.37 | K58: ='01_PARÂMETROS'!$B$4*I58+'01_PARÂMETROS'!$B$5*H58+'01_PARÂMETROS'!$B$6*J58 -> 83.647 | L58: =IF(AND(H58=0,I58=0,J58=0),"✗","✓") -> ✓ | M58: =AVERAGE(F58,K58) -> 84.0885 | N58: =IFERROR(M58/'01_PARÂMETROS'!$B$9,"") -> 1.68177 | O58: =IFERROR(MAX('01_PARÂMETROS'!$B$11,MIN('01_PARÂMETROS'!$B$12,N58)),"") -> 1.4
A59: 01.51-2/02 | B59: Criação de bovinos para leite | C59: 58.42 | D59: 71.22 | E59: 39.72 | F59: ='01_PARÂMETROS'!$B$4*D59+'01_PARÂMETROS'!$B$5*C59+'01_PARÂMETROS'!$B$6*E59 -> 62.015 | G59: =IF(AND(C59=0,D59=0,E59=0),"✗","✓") -> ✓ | H59: 66.04 | I59: 70.46 | J59: 42.38 | K59: ='01_PARÂMETROS'!$B$4*I59+'01_PARÂMETROS'!$B$5*H59+'01_PARÂMETROS'!$B$6*J59 -> 64.701 | L59: =IF(AND(H59=0,I59=0,J59=0),"✗","✓") -> ✓ | M59: =AVERAGE(F59,K59) -> 63.358 | N59: =IFERROR(M59/'01_PARÂMETROS'!$B$9,"") -> 1.26716 | O59: =IFERROR(MAX('01_PARÂMETROS'!$B$11,MIN('01_PARÂMETROS'!$B$12,N59)),"") -> 1.26716
A60: 01.51-2/03 | B60: Criação de bovinos, exceto para corte e leite | C60: 67.42 | D60: 90.32 | E60: 68.59 | F60: ='01_PARÂMETROS'!$B$4*D60+'01_PARÂMETROS'!$B$5*C60+'01_PARÂMETROS'!$B$6*E60 -> 79.0455 | G60: =IF(AND(C60=0,D60=0,E60=0),"✗","✓") -> ✓ | H60: 70.38 | I60: 89.81 | J60: 88.3 | K60: ='01_PARÂMETROS'!$B$4*I60+'01_PARÂMETROS'!$B$5*H60+'01_PARÂMETROS'!$B$6*J60 -> 82.783 | L60: =IF(AND(H60=0,I60=0,J60=0),"✗","✓") -> ✓ | M60: =AVERAGE(F60,K60) -> 80.91425 | N60: =IFERROR(M60/'01_PARÂMETROS'!$B$9,"") -> 1.618285 | O60: =IFERROR(MAX('01_PARÂMETROS'!$B$11,MIN('01_PARÂMETROS'!$B$12,N60)),"") -> 1.4
A61: 01.52-1/01 | B61: Criação de bufalinos | C61: 44.07 | D61: 42.21 | E61: 7.37 | F61: ='01_PARÂMETROS'!$B$4*D61+'01_PARÂMETROS'!$B$5*C61+'01_PARÂMETROS'!$B$6*E61 -> 37.635 | G61: =IF(AND(C61=0,D61=0,E61=0),"✗","✓") -> ✓ | H61: 22 | I61: 46.7 | J61: 0 | K61: ='01_PARÂMETROS'!$B$4*I61+'01_PARÂMETROS'!$B$5*H61+'01_PARÂMETROS'!$B$6*J61 -> 31.05 | L61: =IF(AND(H61=0,I61=0,J61=0),"✗","✓") -> ✓ | M61: =AVERAGE(F61,K61) -> 34.3425 | N61: =IFERROR(M61/'01_PARÂMETROS'!$B$9,"") -> 0.68685 | O61: =IFERROR(MAX('01_PARÂMETROS'!$B$11,MIN('01_PARÂMETROS'!$B$12,N61)),"") -> 0.75
A62: 01.52-1/02 | B62: Criação de equinos | C62: 58.5 | D62: 56.55 | E62: 18.71 | F62: ='01_PARÂMETROS'!$B$4*D62+'01_PARÂMETROS'!$B$5*C62+'01_PARÂMETROS'!$B$6*E62 -> 51.5565 | G62: =IF(AND(C62=0,D62=0,E62=0),"✗","✓") -> ✓ | H62: 63.87 | I62: 77.73 | J62: 39.78 | K62: ='01_PARÂMETROS'!$B$4*I62+'01_PARÂMETROS'!$B$5*H62+'01_PARÂMETROS'!$B$6*J62 -> 67.1865 | L62: =IF(AND(H62=0,I62=0,J62=0),"✗","✓") -> ✓ | M62: =AVERAGE(F62,K62) -> 59.3715 | N62: =IFERROR(M62/'01_PARÂMETROS'!$B$9,"") -> 1.18743 | O62: =IFERROR(MAX('01_PARÂMETROS'!$B$11,MIN('01_PARÂMETROS'!$B$12,N62)),"") -> 1.18743
A63: 01.52-1/03 | B63: Criação de asininos e muares | C63: 85.72 | D63: 97.14 | E63: 28.38 | F63: ='01_PARÂMETROS'!$B$4*D63+'01_PARÂMETROS'!$B$5*C63+'01_PARÂMETROS'!$B$6*E63 -> 82.829 | G63: =IF(AND(C63=0,D63=0,E63=0),"✗","✓") -> ✓ | H63: 91.78 | I63: 99.28 | J63: 49.97 | K63: ='01_PARÂMETROS'!$B$4*I63+'01_PARÂMETROS'!$B$5*H63+'01_PARÂMETROS'!$B$6*J63 -> 89.2585 | L63: =IF(AND(H63=0,I63=0,J63=0),"✗","✓") -> ✓ | M63: =AVERAGE(F63,K63) -> 86.04375 | N63: =IFERROR(M63/'01_PARÂMETROS'!$B$9,"") -> 1.720875 | O63: =IFERROR(MAX('01_PARÂMETROS'!$B$11,MIN('01_PARÂMETROS'!$B$12,N63)),"") -> 1.4
... A79: 01.62-8/01 | B79: Serviço de inseminação artificial em animais | C79: 91.31 | D79: 45.69 | E79: 9.9 | F79: ='01_PARÂMETROS'!$B$4*D79+'01_PARÂMETROS'!$B$5*C79+'01_PARÂMETROS'!$B$6*E79 -> 56.2885 | G79: =IF(AND(C79=0,D79=0,E79=0),"✗","✓") -> ✓ | H79: 34.1 | I79: 44.41 | J79: 54.71 | K79: ='01_PARÂMETROS'!$B$4*I79+'01_PARÂMETROS'!$B$5*H79+'01_PARÂMETROS'!$B$6*J79 -> 42.3465 | L79: =IF(AND(H79=0,I79=0,J79=0),"✗","✓") -> ✓ | M79: =AVERAGE(F79,K79) -> 49.3175 | N79: =IFERROR(M79/'01_PARÂMETROS'!$B$9,"") -> 0.98635 | O79: =IFERROR(MAX('01_PARÂMETROS'!$B$11,MIN('01_PARÂMETROS'!$B$12,N79)),"") -> 0.98635
A80: 01.62-8/02 | B80: Serviço de tosquiamento de ovinos | C80: 0 | D80: 0 | E80: 0 | F80: 0 | G80: =IF(AND(C80=0,D80=0,E80=0),"✗","✓") -> ✗ | H80: 0 | I80: 0 | J80: 0 | K80: 0 | L80: =IF(AND(H80=0,I80=0,J80=0),"✗","✓") -> ✗
A81: 01.62-8/03 | B81: Serviço de manejo de animais | C81: 76.18 | D81: 56.08 | E81: 23.54 | F81: ='01_PARÂMETROS'!$B$4*D81+'01_PARÂMETROS'!$B$5*C81+'01_PARÂMETROS'!$B$6*E81 -> 58.234 | G81: =IF(AND(C81=0,D81=0,E81=0),"✗","✓") -> ✓ | H81: 56.42 | I81: 56.41 | J81: 79.45 | K81: ='01_PARÂMETROS'!$B$4*I81+'01_PARÂMETROS'!$B$5*H81+'01_PARÂMETROS'!$B$6*J81 -> 59.8695 | L81: =IF(AND(H81=0,I81=0,J81=0),"✗","✓") -> ✓ | M81: =AVERAGE(F81,K81) -> 59.05175 | N81: =IFERROR(M81/'01_PARÂMETROS'!$B$9,"") -> 1.181035 | O81: =IFERROR(MAX('01_PARÂMETROS'!$B$11,MIN('01_PARÂMETROS'!$B$12,N81)),"") -> 1.181035
A82: 01.62-8/99 | B82: Atividades de apoio à pecuária não especificadas anteriormente | C82: 63.85 | D82: 78.43 | E82: 65.1 | F82: ='01_PARÂMETROS'!$B$4*D82+'01_PARÂMETROS'!$B$5*C82+'01_PARÂMETROS'!$B$6*E82 -> 71.3275 | G82: =IF(AND(C82=0,D82=0,E82=0),"✗","✓") -> ✓ | H82: 63.17 | I82: 66.83 | J82: 57.4 | K82: ='01_PARÂMETROS'!$B$4*I82+'01_PARÂMETROS'!$B$5*H82+'01_PARÂMETROS'!$B$6*J82 -> 64.1345 | L82: =IF(AND(H82=0,I82=0,J82=0),"✗","✓") -> ✓ | M82: =AVERAGE(F82,K82) -> 67.731 | N82: =IFERROR(M82/'01_PARÂMETROS'!$B$9,"") -> 1.35462 | O82: =IFERROR(MAX('01_PARÂMETROS'!$B$11,MIN('01_PARÂMETROS'!$B$12,N82)),"") -> 1.35462
A83: 01.63-6/00 | B83: Atividades de pós-colheita | C83: 72.31 | D83: 74.15 | E83: 63.75 | F83: ='01_PARÂMETROS'!$B$4*D83+'01_PARÂMETROS'!$B$5*C83+'01_PARÂMETROS'!$B$6*E83 -> 71.946 | G83: =IF(AND(C83=0,D83=0,E83=0),"✗","✓") -> ✓ | H83: 70.07 | I83: 63.99 | J83: 46.18 | K83: ='01_PARÂMETROS'!$B$4*I83+'01_PARÂMETROS'!$B$5*H83+'01_PARÂMETROS'!$B$6*J83 -> 63.4465 | L83: =IF(AND(H83=0,I83=0,J83=0),"✗","✓") -> ✓ | M83: =AVERAGE(F83,K83) -> 67.69625 | N83: =IFERROR(M83/'01_PARÂMETROS'!$B$9,"") -> 1.353925 | O83: =IFERROR(MAX('01_PARÂMETROS'!$B$11,MIN('01_PARÂMETROS'!$B$12,N83)),"") -> 1.353925
A84: 01.70-9/00 | B84: Caça e serviços relacionados | C84: 0 | D84: 0 | E84: 0 | F84: 0 | G84: =IF(AND(C84=0,D84=0,E84=0),"✗","✓") -> ✗ | H84: 0 | I84: 0 | J84: 0 | K84: 0 | L84: =IF(AND(H84=0,I84=0,J84=0),"✗","✓") -> ✗
A85: 02.10-1/01 | B85: Cultivo de eucalipto | C85: 59.43 | D85: 60.36 | E85: 39.09 | F85: ='01_PARÂMETROS'!$B$4*D85+'01_PARÂMETROS'!$B$5*C85+'01_PARÂMETROS'!$B$6*E85 -> 56.844 | G85: =IF(AND(C85=0,D85=0,E85=0),"✗","✓") -> ✓ | H85: 62.55 | I85: 64.78 | J85: 55.74 | K85: ='01_PARÂMETROS'!$B$4*I85+'01_PARÂMETROS'!$B$5*H85+'01_PARÂMETROS'!$B$6*J85 -> 62.6435 | L85: =IF(AND(H85=0,I85=0,J85=0),"✗","✓") -> ✓ | M85: =AVERAGE(F85,K85) -> 59.74375 | N85: =IFERROR(M85/'01_PARÂMETROS'!$B$9,"") -> 1.194875 | O85: =IFERROR(MAX('01_PARÂMETROS'!$B$11,MIN('01_PARÂMETROS'!$B$12,N85)),"") -> 1.194875
A86: 02.10-1/02 | B86: Cultivo de acácia-negra | C86: 100 | D86: 0 | E86: 0 | F86: ='01_PARÂMETROS'!$B$4*D86+'01_PARÂMETROS'!$B$5*C86+'01_PARÂMETROS'!$B$6*E86 -> 35 | G86: =IF(AND(C86=0,D86=0,E86=0),"✗","✓") -> ✓ | H86: 99.92 | I86: 0 | J86: 0 | K86: ='01_PARÂMETROS'!$B$4*I86+'01_PARÂMETROS'!$B$5*H86+'01_PARÂMETROS'!$B$6*J86 -> 34.972 | L86: =IF(AND(H86=0,I86=0,J86=0),"✗","✓") -> ✓ | M86: =AVERAGE(F86,K86) -> 34.986 | N86: =IFERROR(M86/'01_PARÂMETROS'!$B$9,"") -> 0.69972 | O86: =IFERROR(MAX('01_PARÂMETROS'!$B$11,MIN('01_PARÂMETROS'!$B$12,N86)),"") -> 0.75
A87: 02.10-1/03 | B87: Cultivo de pinus | C87: 92.01 | D87: 95.56 | E87: 81.75 | F87: ='01_PARÂMETROS'!$B$4*D87+'01_PARÂMETROS'!$B$5*C87+'01_PARÂMETROS'!$B$6*E87 -> 92.246 | G87: =IF(AND(C87=0,D87=0,E87=0),"✗","✓") -> ✓ | H87: 90.85 | I87: 95.34 | J87: 84.03 | K87: ='01_PARÂMETROS'!$B$4*I87+'01_PARÂMETROS'!$B$5*H87+'01_PARÂMETROS'!$B$6*J87 -> 92.072 | L87: =IF(AND(H87=0,I87=0,J87=0),"✗","✓") -> ✓ | M87: =AVERAGE(F87,K87) -> 92.159 | N87: =IFERROR(M87/'01_PARÂMETROS'!$B$9,"") -> 1.84318 | O87: =IFERROR(MAX('01_PARÂMETROS'!$B$11,MIN('01_PARÂMETROS'!$B$12,N87)),"") -> 1.4
A88: 02.10-1/04 | B88: Cultivo de teca | C88: 93.56 | D88: 82.87 | E88: 72.08 | F88: ='01_PARÂMETROS'!$B$4*D88+'01_PARÂMETROS'!$B$5*C88+'01_PARÂMETROS'!$B$6*E88 -> 84.993 | G88: =IF(AND(C88=0,D88=0,E88=0),"✗","✓") -> ✓ | H88: 83.71 | I88: 56.96 | J88: 12.43 | K88: ='01_PARÂMETROS'!$B$4*I88+'01_PARÂMETROS'!$B$5*H88+'01_PARÂMETROS'!$B$6*J88 -> 59.643 | L88: =IF(AND(H88=0,I88=0,J88=0),"✗","✓") -> ✓ | M88: =AVERAGE(F88,K88) -> 72.318 | N88: =IFERROR(M88/'01_PARÂMETROS'!$B$9,"") -> 1.44636 | O88: =IFERROR(MAX('01_PARÂMETROS'!$B$11,MIN('01_PARÂMETROS'!$B$12,N88)),"") -> 1.4
A89: 02.10-1/05 | B89: Cultivo de espécies madeireiras, exceto eucalipto, acácia-negra, pinus e teca | C89: 65.79 | D89: 35.55 | E89: 11.09 | F89: ='01_PARÂMETROS'!$B$4*D89+'01_PARÂMETROS'!$B$5*C89+'01_PARÂMETROS'!$B$6*E89 -> 42.465 | G89: =IF(AND(C89=0,D89=0,E89=0),"✗","✓") -> ✓ | H89: 62.63 | I89: 33.19 | J89: 13.38 | K89: ='01_PARÂMETROS'!$B$4*I89+'01_PARÂMETROS'!$B$5*H89+'01_PARÂMETROS'!$B$6*J89 -> 40.5225 | L89: =IF(AND(H89=0,I89=0,J89=0),"✗","✓") -> ✓ | M89: =AVERAGE(F89,K89) -> 41.49375 | N89: =IFERROR(M89/'01_PARÂMETROS'!$B$9,"") -> 0.829875 | O89: =IFERROR(MAX('01_PARÂMETROS'!$B$11,MIN('01_PARÂMETROS'!$B$12,N89)),"") -> 0.829875
A90: 02.10-1/06 | B90: Cultivo de mudas em viveiros florestais | C90: 70.75 | D90: 65.43 | E90: 48.6 | F90: ='01_PARÂMETROS'!$B$4*D90+'01_PARÂMETROS'!$B$5*C90+'01_PARÂMETROS'!$B$6*E90 -> 64.7675 | G90: =IF(AND(C90=0,D90=0,E90=0),"✗","✓") -> ✓ | H90: 67.05 | I90: 49.78 | J90: 35.27 | K90: ='01_PARÂMETROS'!$B$4*I90+'01_PARÂMETROS'!$B$5*H90+'01_PARÂMETROS'!$B$6*J90 -> 53.648 | L90: =IF(AND(H90=0,I90=0,J90=0),"✗","✓") -> ✓ | M90: =AVERAGE(F90,K90) -> 59.20775 | N90: =IFERROR(M90/'01_PARÂMETROS'!$B$9,"") -> 1.184155 | O90: =IFERROR(MAX('01_PARÂMETROS'!$B$11,MIN('01_PARÂMETROS'!$B$12,N90)),"") -> 1.184155
A91: 02.10-1/07 | B91: Extração de madeira em florestas plantadas | C91: 86.73 | D91: 95.08 | E91: 89.37 | F91: ='01_PARÂMETROS'!$B$4*D91+'01_PARÂMETROS'!$B$5*C91+'01_PARÂMETROS'!$B$6*E91 -> 91.301 | G91: =IF(AND(C91=0,D91=0,E91=0),"✗","✓") -> ✓ | H91: 83.02 | I91: 93.52 | J91: 89.41 | K91: ='01_PARÂMETROS'!$B$4*I91+'01_PARÂMETROS'!$B$5*H91+'01_PARÂMETROS'!$B$6*J91 -> 89.2285 | L91: =IF(AND(H91=0,I91=0,J91=0),"✗","✓") -> ✓ | M91: =AVERAGE(F91,K91) -> 90.26475 | N91: =IFERROR(M91/'01_PARÂMETROS'!$B$9,"") -> 1.805295 | O91: =IFERROR(MAX('01_PARÂMETROS'!$B$11,MIN('01_PARÂMETROS'!$B$12,N91)),"") -> 1.4
A92: 02.10-1/08 | B92: Produção de carvão vegetal - florestas plantadas | C92: 70.91 | D92: 86.52 | E92: 82.71 | F92: ='01_PARÂMETROS'!$B$4*D92+'01_PARÂMETROS'!$B$5*C92+'01_PARÂMETROS'!$B$6*E92 -> 80.485 | G92: =IF(AND(C92=0,D92=0,E92=0),"✗","✓") -> ✓ | H92: 56.81 | I92: 63.83 | J92: 50.05 | K92: ='01_PARÂMETROS'!$B$4*I92+'01_PARÂMETROS'!$B$5*H92+'01_PARÂMETROS'!$B$6*J92 -> 59.306 | L92: =IF(AND(H92=0,I92=0,J92=0),"✗","✓") -> ✓ | M92: =AVERAGE(F92,K92) -> 69.8955 | N92: =IFERROR(M92/'01_PARÂMETROS'!$B$9,"") -> 1.39791 | O92: =IFERROR(MAX('01_PARÂMETROS'!$B$11,MIN('01_PARÂMETROS'!$B$12,N92)),"") -> 1.39791
A93: 02.10-1/09 | B93: Produção de casca de acácia-negra - florestas plantadas | C93: 65.87 | D93: 0 | E93: 0 | F93: ='01_PARÂMETROS'!$B$4*D93+'01_PARÂMETROS'!$B$5*C93+'01_PARÂMETROS'!$B$6*E93 -> 23.0545 | G93: =IF(AND(C93=0,D93=0,E93=0),"✗","✓") -> ✓ | H93: 42.62 | I93: 0 | J93: 0 | K93: ='01_PARÂMETROS'!$B$4*I93+'01_PARÂMETROS'!$B$5*H93+'01_PARÂMETROS'!$B$6*J93 -> 14.917 | L93: =IF(AND(H93=0,I93=0,J93=0),"✗","✓") -> ✓ | M93: =AVERAGE(F93,K93) -> 18.98575 | N93: =IFERROR(M93/'01_PARÂMETROS'!$B$9,"") -> 0.379715 | O93: =IFERROR(MAX('01_PARÂMETROS'!$B$11,MIN('01_PARÂMETROS'!$B$12,N93)),"") -> 0.75
A94: 02.10-1/99 | B94: Produção de produtos não madeireiros não especificados anteriormente em florestas plantadas | C94: 47.95 | D94: 44.11 | E94: 23.86 | F94: ='01_PARÂMETROS'!$B$4*D94+'01_PARÂMETROS'!$B$5*C94+'01_PARÂMETROS'!$B$6*E94 -> 42.4165 | G94: =IF(AND(C94=0,D94=0,E94=0),"✗","✓") -> ✓ | H94: 45.34 | I94: 40.54 | J94: 25.08 | K94: ='01_PARÂMETROS'!$B$4*I94+'01_PARÂMETROS'!$B$5*H94+'01_PARÂMETROS'!$B$6*J94 -> 39.901 | L94: =IF(AND(H94=0,I94=0,J94=0),"✗","✓") -> ✓ | M94: =AVERAGE(F94,K94) -> 41.15875 | N94: =IFERROR(M94/'01_PARÂMETROS'!$B$9,"") -> 0.823175 | O94: =IFERROR(MAX('01_PARÂMETROS'!$B$11,MIN('01_PARÂMETROS'!$B$12,N94)),"") -> 0.823175
A95: 02.20-9/01 | B95: Extração de madeira em florestas nativas | C95: 85.41 | D95: 84.46 | E95: 92.54 | F95: ='01_PARÂMETROS'!$B$4*D95+'01_PARÂMETROS'!$B$5*C95+'01_PARÂMETROS'!$B$6*E95 -> 86.0045 | G95: =IF(AND(C95=0,D95=0,E95=0),"✗","✓") -> ✓ | H95: 82.94 | I95: 89.34 | J95: 96.68 | K95: ='01_PARÂMETROS'!$B$4*I95+'01_PARÂMETROS'!$B$5*H95+'01_PARÂMETROS'!$B$6*J95 -> 88.201 | L95: =IF(AND(H95=0,I95=0,J95=0),"✗","✓") -> ✓ | M95: =AVERAGE(F95,K95) -> 87.10275 | N95: =IFERROR(M95/'01_PARÂMETROS'!$B$9,"") -> 1.742055 | O95: =IFERROR(MAX('01_PARÂMETROS'!$B$11,MIN('01_PARÂMETROS'!$B$12,N95)),"") -> 1.4
A96: 02.20-9/02 | B96: Produção de carvão vegetal - florestas nativas | C96: 55.16 | D96: 69.48 | E96: 26.16 | F96: ='01_PARÂMETROS'!$B$4*D96+'01_PARÂMETROS'!$B$5*C96+'01_PARÂMETROS'!$B$6*E96 -> 57.97 | G96: =IF(AND(C96=0,D96=0,E96=0),"✗","✓") -> ✓ | H96: 54.87 | I96: 82.62 | J96: 71.54 | K96: ='01_PARÂMETROS'!$B$4*I96+'01_PARÂMETROS'!$B$5*H96+'01_PARÂMETROS'!$B$6*J96 -> 71.2455 | L96: =IF(AND(H96=0,I96=0,J96=0),"✗","✓") -> ✓ | M96: =AVERAGE(F96,K96) -> 64.60775 | N96: =IFERROR(M96/'01_PARÂMETROS'!$B$9,"") -> 1.292155 | O96: =IFERROR(MAX('01_PARÂMETROS'!$B$11,MIN('01_PARÂMETROS'!$B$12,N96)),"") -> 1.292155
A97: 02.20-9/03 | B97: Coleta de castanha-do-pará em florestas nativas | C97: 86.5 | D97: 98.57 | E97: 55.19 | F97: ='01_PARÂMETROS'!$B$4*D97+'01_PARÂMETROS'!$B$5*C97+'01_PARÂMETROS'!$B$6*E97 -> 87.8385 | G97: =IF(AND(C97=0,D97=0,E97=0),"✗","✓") -> ✓ | H97: 83.64 | I97: 97.23 | J97: 19.07 | K97: ='01_PARÂMETROS'!$B$4*I97+'01_PARÂMETROS'!$B$5*H97+'01_PARÂMETROS'!$B$6*J97 -> 80.7495 | L97: =IF(AND(H97=0,I97=0,J97=0),"✗","✓") -> ✓ | M97: =AVERAGE(F97,K97) -> 84.294 | N97: =IFERROR(M97/'01_PARÂMETROS'!$B$9,"") -> 1.68588 | O97: =IFERROR(MAX('01_PARÂMETROS'!$B$11,MIN('01_PARÂMETROS'!$B$12,N97)),"") -> 1.4
A98: 02.20-9/04 | B98: Coleta de látex em florestas nativas | C98: 0 | D98: 0 | E98: 0 | F98: 0 | G98: =IF(AND(C98=0,D98=0,E98=0),"✗","✓") -> ✗ | H98: 61 | I98: 72.75 | J98: 13.78 | K98: ='01_PARÂMETROS'!$B$4*I98+'01_PARÂMETROS'!$B$5*H98+'01_PARÂMETROS'!$B$6*J98 -> 59.792 | L98: =IF(AND(H98=0,I98=0,J98=0),"✗","✓") -> ✓ | M98: =K98 -> 59.792 | N98: =IFERROR(M98/'01_PARÂMETROS'!$B$9,"") -> 1.19584 | O98: =IFERROR(MAX('01_PARÂMETROS'!$B$11,MIN('01_PARÂMETROS'!$B$12,N98)),"") -> 1.19584
A99: 02.20-9/05 | B99: Coleta de palmito em florestas nativas | C99: 0 | D99: 0 | E99: 0 | F99: 0 | G99: =IF(AND(C99=0,D99=0,E99=0),"✗","✓") -> ✗ | H99: 100 | I99: 99.92 | J99: 99.52 | K99: ='01_PARÂMETROS'!$B$4*I99+'01_PARÂMETROS'!$B$5*H99+'01_PARÂMETROS'!$B$6*J99 -> 99.888 | L99: =IF(AND(H99=0,I99=0,J99=0),"✗","✓") -> ✓ | M99: =K99 -> 99.888 | N99: =IFERROR(M99/'01_PARÂMETROS'!$B$9,"") -> 1.99776 | O99: =IFERROR(MAX('01_PARÂMETROS'!$B$11,MIN('01_PARÂMETROS'!$B$12,N99)),"") -> 1.4
A100: 02.20-9/06 | B100: Conservação de florestas nativas | C100: 47.56 | D100: 68.44 | E100: 85.72 | F100: ='01_PARÂMETROS'!$B$4*D100+'01_PARÂMETROS'!$B$5*C100+'01_PARÂMETROS'!$B$6*E100 -> 63.724 | G100: =IF(AND(C100=0,D100=0,E100=0),"✗","✓") -> ✓ | H100: 57.51 | I100: 80.33 | J100: 75.58 | K100: ='01_PARÂMETROS'!$B$4*I100+'01_PARÂMETROS'!$B$5*H100+'01_PARÂMETROS'!$B$6*J100 -> 71.6305 | L100: =IF(AND(H100=0,I100=0,J100=0),"✗","✓") -> ✓ | M100: =AVERAGE(F100,K100) -> 67.67725 | N100: =IFERROR(M100/'01_PARÂMETROS'!$B$9,"") -> 1.353545 | O100: =IFERROR(MAX('01_PARÂMETROS'!$B$11,MIN('01_PARÂMETROS'!$B$12,N100)),"") -> 1.353545
A101: 02.20-9/99 | B101: Coleta de produtos não madeireiros não especificados anteriormente em florestas nativas | C101: 49.97 | D101: 49.97 | E101: 21.4 | F101: ='01_PARÂMETROS'!$B$4*D101+'01_PARÂMETROS'!$B$5*C101+'01_PARÂMETROS'!$B$6*E101 -> 45.6845 | G101: =IF(AND(C101=0,D101=0,E101=0),"✗","✓") -> ✓ | H101: 51.07 | I101: 48.91 | J101: 45.15 | K101: ='01_PARÂMETROS'!$B$4*I101+'01_PARÂMETROS'!$B$5*H101+'01_PARÂMETROS'!$B$6*J101 -> 49.102 | L101: =IF(AND(H101=0,I101=0,J101=0),"✗","✓") -> ✓ | M101: =AVERAGE(F101,K101) -> 47.39325 | N101: =IFERROR(M101/'01_PARÂMETROS'!$B$9,"") -> 0.947865 | O101: =IFERROR(MAX('01_PARÂMETROS'!$B$11,MIN('01_PARÂMETROS'!$B$12,N101)),"") -> 0.947865
A102: 02.30-6/00 | B102: Atividades de apoio à produção florestal | C102: 64.39 | D102: 58.85 | E102: 58.68 | F102: ='01_PARÂMETROS'!$B$4*D102+'01_PARÂMETROS'!$B$5*C102+'01_PARÂMETROS'!$B$6*E102 -> 60.7635 | G102: =IF(AND(C102=0,D102=0,E102=0),"✗","✓") -> ✓ | H102: 66.81 | I102: 60.04 | J102: 55.5 | K102: ='01_PARÂMETROS'!$B$4*I102+'01_PARÂMETROS'!$B$5*H102+'01_PARÂMETROS'!$B$6*J102 -> 61.7285 | L102: =IF(AND(H102=0,I102=0,J102=0),"✗","✓") -> ✓ | M102: =AVERAGE(F102,K102) -> 61.246 | N102: =IFERROR(M102/'01_PARÂMETROS'!$B$9,"") -> 1.22492 | O102: =IFERROR(MAX('01_PARÂMETROS'!$B$11,MIN('01_PARÂMETROS'!$B$12,N102)),"") -> 1.22492
A103: 03.11-6/01 | B103: Pesca de peixes em água salgada | C103: 74.86 | D103: 95 | E103: 95.24 | F103: ='01_PARÂMETROS'!$B$4*D103+'01_PARÂMETROS'!$B$5*C103+'01_PARÂMETROS'!$B$6*E103 -> 87.987 | G103: =IF(AND(C103=0,D103=0,E103=0),"✗","✓") -> ✓ | H103: 57.2 | I103: 91.31 | J103: 96.83 | K103: ='01_PARÂMETROS'!$B$4*I103+'01_PARÂMETROS'!$B$5*H103+'01_PARÂMETROS'!$B$6*J103 -> 80.1995 | L103: =IF(AND(H103=0,I103=0,J103=0),"✗","✓") -> ✓ | M103: =AVERAGE(F103,K103) -> 84.09325 | N103: =IFERROR(M103/'01_PARÂMETROS'!$B$9,"") -> 1.681865 | O103: =IFERROR(MAX('01_PARÂMETROS'!$B$11,MIN('01_PARÂMETROS'!$B$12,N103)),"") -> 1.4
A104: 03.11-6/02 | B104: Pesca de crustáceos e moluscos em água salgada | C104: 48.03 | D104: 76.37 | E104: 24.42 | F104: ='01_PARÂMETROS'!$B$4*D104+'01_PARÂMETROS'!$B$5*C104+'01_PARÂMETROS'!$B$6*E104 -> 58.6585 | G104: =IF(AND(C104=0,D104=0,E104=0),"✗","✓") -> ✓ | H104: 16.65 | I104: 47.8 | J104: 65.93 | K104: ='01_PARÂMETROS'!$B$4*I104+'01_PARÂMETROS'!$B$5*H104+'01_PARÂMETROS'!$B$6*J104 -> 39.617 | L104: =IF(AND(H104=0,I104=0,J104=0),"✗","✓") -> ✓ | M104: =AVERAGE(F104,K104) -> 49.13775 | N104: =IFERROR(M104/'01_PARÂMETROS'!$B$9,"") -> 0.982755 | O104: =IFERROR(MAX('01_PARÂMETROS'!$B$11,MIN('01_PARÂMETROS'!$B$12,N104)),"") -> 0.982755
A105: 03.11-6/03 | B105: Coleta de outros produtos marinhos | C105: 0 | D105: 0 | E105: 0 | F105: 0 | G105: =IF(AND(C105=0,D105=0,E105=0),"✗","✓") -> ✗ | H105: 99.3 | I105: 100 | J105: 100 | K105: ='01_PARÂMETROS'!$B$4*I105+'01_PARÂMETROS'!$B$5*H105+'01_PARÂMETROS'!$B$6*J105 -> 99.755 | L105: =IF(AND(H105=0,I105=0,J105=0),"✗","✓") -> ✓ | M105: =K105 -> 99.755 | N105: =IFERROR(M105/'01_PARÂMETROS'!$B$9,"") -> 1.9951 | O105: =IFERROR(MAX('01_PARÂMETROS'!$B$11,MIN('01_PARÂMETROS'!$B$12,N105)),"") -> 1.4
A106: 03.11-6/04 | B106: Atividades de apoio à pesca em água salgada | C106: 17 | D106: 40.3 | E106: 13.87 | F106: ='01_PARÂMETROS'!$B$4*D106+'01_PARÂMETROS'!$B$5*C106+'01_PARÂMETROS'!$B$6*E106 -> 28.1805 | G106: =IF(AND(C106=0,D106=0,E106=0),"✗","✓") -> ✓ | H106: 19.6 | I106: 43.46 | J106: 13.22 | K106: ='01_PARÂMETROS'!$B$4*I106+'01_PARÂMETROS'!$B$5*H106+'01_PARÂMETROS'!$B$6*J106 -> 30.573 | L106: =IF(AND(H106=0,I106=0,J106=0),"✗","✓") -> ✓ | M106: =AVERAGE(F106,K106) -> 29.37675 | N106: =IFERROR(M106/'01_PARÂMETROS'!$B$9,"") -> 0.587535 | O106: =IFERROR(MAX('01_PARÂMETROS'!$B$11,MIN('01_PARÂMETROS'!$B$12,N106)),"") -> 0.75
A107: 03.12-4/01 | B107: Pesca de peixes em água doce | C107: 52.14 | D107: 63.13 | E107: 97.77 | F107: ='01_PARÂMETROS'!$B$4*D107+'01_PARÂMETROS'!$B$5*C107+'01_PARÂMETROS'!$B$6*E107 -> 64.4795 | G107: =IF(AND(C107=0,D107=0,E107=0),"✗","✓") -> ✓ | H107: 38.13 | I107: 69.75 | J107: 98.97 | K107: ='01_PARÂMETROS'!$B$4*I107+'01_PARÂMETROS'!$B$5*H107+'01_PARÂMETROS'!$B$6*J107 -> 63.066 | L107: =IF(AND(H107=0,I107=0,J107=0),"✗","✓") -> ✓ | M107: =AVERAGE(F107,K107) -> 63.77275 | N107: =IFERROR(M107/'01_PARÂMETROS'!$B$9,"") -> 1.275455 | O107: =IFERROR(MAX('01_PARÂMETROS'!$B$11,MIN('01_PARÂMETROS'!$B$12,N107)),"") -> 1.275455
A108: 03.12-4/03 | B108: Coleta de outros produtos aquáticos de água doce | C108: 87.9 | D108: 0 | E108: 0 | F108: ='01_PARÂMETROS'!$B$4*D108+'01_PARÂMETROS'!$B$5*C108+'01_PARÂMETROS'!$B$6*E108 -> 30.765 | G108: =IF(AND(C108=0,D108=0,E108=0),"✗","✓") -> ✓ | H108: 0 | I108: 0 | J108: 0 | K108: 0 | L108: =IF(AND(H108=0,I108=0,J108=0),"✗","✓") -> ✗ | M108: =F108 -> 30.765 | N108: =IFERROR(M108/'01_PARÂMETROS'!$B$9,"") -> 0.6153 | O108: =IFERROR(MAX('01_PARÂMETROS'!$B$11,MIN('01_PARÂMETROS'!$B$12,N108)),"") -> 0.75
A109: 03.12-4/04 | B109: Atividades de apoio à pesca em água doce | C109: 0 | D109: 0 | E109: 0 | F109: 0 | G109: =IF(AND(C109=0,D109=0,E109=0),"✗","✓") -> ✗ | H109: 0 | I109: 0 | J109: 0 | K109: 0 | L109: =IF(AND(H109=0,I109=0,J109=0),"✗","✓") -> ✗
A110: 03.21-3/01 | B110: Criação de peixes em água salgada e salobra | C110: 0 | D110: 0 | E110: 0 | F110: 0 | G110: =IF(AND(C110=0,D110=0,E110=0),"✗","✓") -> ✗ | H110: 0 | I110: 0 | J110: 0 | K110: 0 | L110: =IF(AND(H110=0,I110=0,J110=0),"✗","✓") -> ✗
A111: 03.21-3/02 | B111: Criação de camarões em água salgada e salobra | C111: 57.34 | D111: 32.53 | E111: 14.74 | F111: ='01_PARÂMETROS'!$B$4*D111+'01_PARÂMETROS'!$B$5*C111+'01_PARÂMETROS'!$B$6*E111 -> 38.545 | G111: =IF(AND(C111=0,D111=0,E111=0),"✗","✓") -> ✓ | H111: 41.23 | I111: 40.7 | J111: 34.09 | K111: ='01_PARÂMETROS'!$B$4*I111+'01_PARÂMETROS'!$B$5*H111+'01_PARÂMETROS'!$B$6*J111 -> 39.894 | L111: =IF(AND(H111=0,I111=0,J111=0),"✗","✓") -> ✓ | M111: =AVERAGE(F111,K111) -> 39.2195 | N111: =IFERROR(M111/'01_PARÂMETROS'!$B$9,"") -> 0.78439 | O111: =IFERROR(MAX('01_PARÂMETROS'!$B$11,MIN('01_PARÂMETROS'!$B$12,N111)),"") -> 0.78439
A112: 03.21-3/03 | B112: Criação de ostras e mexilhões em água salgada e salobra | C112: 0 | D112: 0 | E112: 0 | F112: 0 | G112: =IF(AND(C112=0,D112=0,E112=0),"✗","✓") -> ✗ | H112: 0 | I112: 0 | J112: 0 | K112: 0 | L112: =IF(AND(H112=0,I112=0,J112=0),"✗","✓") -> ✗
A113: 03.21-3/04 | B113: Criação de peixes ornamentais em água salgada e salobra | C113: 99.45 | D113: 100 | E113: 73.74 | F113: ='01_PARÂMETROS'!$B$4*D113+'01_PARÂMETROS'!$B$5*C113+'01_PARÂMETROS'!$B$6*E113 -> 95.8685 | G113: =IF(AND(C113=0,D113=0,E113=0),"✗","✓") -> ✓ | H113: 48.21 | I113: 97.55 | J113: 60.64 | K113: ='01_PARÂMETROS'!$B$4*I113+'01_PARÂMETROS'!$B$5*H113+'01_PARÂMETROS'!$B$6*J113 -> 74.7445 | L113: =IF(AND(H113=0,I113=0,J113=0),"✗","✓") -> ✓ | M113: =AVERAGE(F113,K113) -> 85.3065 | N113: =IFERROR(M113/'01_PARÂMETROS'!$B$9,"") -> 1.70613 | O113: =IFERROR(MAX('01_PARÂMETROS'!$B$11,MIN('01_PARÂMETROS'!$B$12,N113)),"") -> 1.4
A114: 03.21-3/05 | B114: Atividades de apoio à aquicultura em água salgada e salobra | C114: 34.07 | D114: 0 | E114: 0 | F114: ='01_PARÂMETROS'!$B$4*D114+'01_PARÂMETROS'!$B$5*C114+'01_PARÂMETROS'!$B$6*E114 -> 11.9245 | G114: =IF(AND(C114=0,D114=0,E114=0),"✗","✓") -> ✓ | H114: 52.94 | I114: 39.12 | J114: 22.07 | K114: ='01_PARÂMETROS'!$B$4*I114+'01_PARÂMETROS'!$B$5*H114+'01_PARÂMETROS'!$B$6*J114 -> 41.3995 | L114: =IF(AND(H114=0,I114=0,J114=0),"✗","✓") -> ✓ | M114: =AVERAGE(F114,K114) -> 26.662 | N114: =IFERROR(M114/'01_PARÂMETROS'!$B$9,"") -> 0.53324 | O114: =IFERROR(MAX('01_PARÂMETROS'!$B$11,MIN('01_PARÂMETROS'!$B$12,N114)),"") -> 0.75
A115: 03.21-3/99 | B115: Cultivos e semicultivos da aquicultura em água salgada e salobra não especificados anteriormente | C115: 0 | D115: 0 | E115: 0 | F115: 0 | G115: =IF(AND(C115=0,D115=0,E115=0),"✗","✓") -> ✗ | H115: 25.72 | I115: 0 | J115: 0 | K115: ='01_PARÂMETROS'!$B$4*I115+'01_PARÂMETROS'!$B$5*H115+'01_PARÂMETROS'!$B$6*J115 -> 9.002 | L115: =IF(AND(H115=0,I115=0,J115=0),"✗","✓") -> ✓ | M115: =K115 -> 9.002 | N115: =IFERROR(M115/'01_PARÂMETROS'!$B$9,"") -> 0.18004 | O115: =IFERROR(MAX('01_PARÂMETROS'!$B$11,MIN('01_PARÂMETROS'!$B$12,N115)),"") -> 0.75
...

Sheet 04_MOTOR_CÁLCULO
A1: MOTOR DE CÁLCULO — RELATIVIDADES CNAE | VIDA CAPITAL GLOBAL | STG SEGUROS
A2: Todos os valores são calculados por fórmula — sem constantes coladas. Parâmetros em 01_PARÂMETROS.
A3: IDENTIFICAÇÃO | F3: FAP — ÍNDICES COMPOSTOS | J3: RELATIVIDADE | M3: RESULTADO FINAL
A4: Cód.CNAE | B4: Sec. | C4: Descrição Subclasse | D4: Div. | E4: Class. CNAE | F4: IC 2023 | G4: IC 2024 | H4: IC Médio | I4: IC_ref (param.) | J4: Relat. Bruta | K4: Relat. Final | L4: Ajuste % | M4: Classe | N4: Fonte | O4: Flag Conflito
A5: 0111-3/01 | B5: A | C5: Cultivo de arroz | D5: AGRICULTURA, PEC | E5: Médio | F5: ='03_FONTE_FAP'!F5 -> 54.955 | G5: ='03_FONTE_FAP'!K5 -> 57.308 | H5: ='03_FONTE_FAP'!M5 -> 56.1315 | I5: ='01_PARÂMETROS'!$B$9 -> 50 | J5: =IFERROR(IF(H5=0,1,H5/I5),1) -> 1.12263 | K5: =MAX('01_PARÂMETROS'!$B$11,MIN('01_PARÂMETROS'!$B$12,J5)) -> 1.12263 | L5: =(K5-1) -> 0.12263 | M5: =IF(K5<='01_PARÂMETROS'!$B$14,"Preferencial",IF(K5<='01_PARÂMETROS'!$B$15,"Baixo",IF(K5<='01_PARÂMETROS'!$B$16,"Médio",IF(K5<='01_PARÂMETROS'!$B$17,"Alto","Elevado")))) -> Alto | N5: FAP/MPS | O5: Revisar
A6: 0111-3/02 | B6: A | C6: Cultivo de milho | D6: AGRICULTURA, PEC | E6: Médio | F6: ='03_FONTE_FAP'!F6 -> 48.2445 | G6: ='03_FONTE_FAP'!K6 -> 28.6135 | H6: ='03_FONTE_FAP'!M6 -> 38.429 | I6: ='01_PARÂMETROS'!$B$9 -> 50 | J6: =IFERROR(IF(H6=0,1,H6/I6),1) -> 0.76858 | K6: =MAX('01_PARÂMETROS'!$B$11,MIN('01_PARÂMETROS'!$B$12,J6)) -> 0.76858 | L6: =(K6-1) -> -0.23142 | M6: =IF(K6<='01_PARÂMETROS'!$B$14,"Preferencial",IF(K6<='01_PARÂMETROS'!$B$15,"Baixo",IF(K6<='01_PARÂMETROS'!$B$16,"Médio",IF(K6<='01_PARÂMETROS'!$B$17,"Alto","Elevado")))) -> Preferencial | N6: FAP/MPS | O6: Revisar
A7: 0111-3/03 | B7: A | C7: Cultivo de trigo | D7: AGRICULTURA, PEC | E7: Médio | F7: ='03_FONTE_FAP'!F7 -> 26.2665 | G7: ='03_FONTE_FAP'!K7 -> 19.7225 | H7: ='03_FONTE_FAP'!M7 -> 22.9945 | I7: ='01_PARÂMETROS'!$B$9 -> 50 | J7: =IFERROR(IF(H7=0,1,H7/I7),1) -> 0.45989 | K7: =MAX('01_PARÂMETROS'!$B$11,MIN('01_PARÂMETROS'!$B$12,J7)) -> 0.75 | L7: =(K7-1) -> -0.25 | M7: =IF(K7<='01_PARÂMETROS'!$B$14,"Preferencial",IF(K7<='01_PARÂMETROS'!$B$15,"Baixo",IF(K7<='01_PARÂMETROS'!$B$16,"Médio",IF(K7<='01_PARÂMETROS'!$B$17,"Alto","Elevado")))) -> Preferencial | N7: FAP/MPS | O7: Revisar
A8: 0111-3/99 | B8: A | C8: Cultivo de outros cereais não especificados anteriormente | D8: AGRICULTURA, PEC | E8: Médio | F8: ='03_FONTE_FAP'!F8 -> 47.299 | G8: ='03_FONTE_FAP'!K8 -> 69.1195 | H8: ='03_FONTE_FAP'!M8 -> 58.20925 | I8: ='01_PARÂMETROS'!$B$9 -> 50 | J8: =IFERROR(IF(H8=0,1,H8/I8),1) -> 1.164185 | K8: =MAX('01_PARÂMETROS'!$B$11,MIN('01_PARÂMETROS'!$B$12,J8)) -> 1.164185 | L8: =(K8-1) -> 0.164185 | M8: =IF(K8<='01_PARÂMETROS'!$B$14,"Preferencial",IF(K8<='01_PARÂMETROS'!$B$15,"Baixo",IF(K8<='01_PARÂMETROS'!$B$16,"Médio",IF(K8<='01_PARÂMETROS'!$B$17,"Alto","Elevado")))) -> Alto | N8: FAP/MPS | O8: Revisar
A9: 0112-1/01 | B9: A | C9: Cultivo de algodão herbáceo | D9: AGRICULTURA, PEC | E9: Médio | F9: ='03_FONTE_FAP'!F9 -> 63.368 | G9: ='03_FONTE_FAP'!K9 -> 46.408 | H9: ='03_FONTE_FAP'!M9 -> 54.888 | I9: ='01_PARÂMETROS'!$B$9 -> 50 | J9: =IFERROR(IF(H9=0,1,H9/I9),1) -> 1.09776 | K9: =MAX('01_PARÂMETROS'!$B$11,MIN('01_PARÂMETROS'!$B$12,J9)) -> 1.09776 | L9: =(K9-1) -> 0.09776 | M9: =IF(K9<='01_PARÂMETROS'!$B$14,"Preferencial",IF(K9<='01_PARÂMETROS'!$B$15,"Baixo",IF(K9<='01_PARÂMETROS'!$B$16,"Médio",IF(K9<='01_PARÂMETROS'!$B$17,"Alto","Elevado")))) -> Alto | N9: FAP/MPS | O9: Revisar
A10: 0112-1/02 | B10: A | C10: Cultivo de juta | D10: AGRICULTURA, PEC | E10: Médio | F10: ='03_FONTE_FAP'!F10 -> 36.827 | G10: ='03_FONTE_FAP'!K10 -> 0 | H10: ='03_FONTE_FAP'!M10 -> 36.827 | I10: ='01_PARÂMETROS'!$B$9 -> 50 | J10: =IFERROR(IF(H10=0,1,H10/I10),1) -> 0.73654 | K10: =MAX('01_PARÂMETROS'!$B$11,MIN('01_PARÂMETROS'!$B$12,J10)) -> 0.75 | L10: =(K10-1) -> -0.25 | M10: =IF(K10<='01_PARÂMETROS'!$B$14,"Preferencial",IF(K10<='01_PARÂMETROS'!$B$15,"Baixo",IF(K10<='01_PARÂMETROS'!$B$16,"Médio",IF(K10<='01_PARÂMETROS'!$B$17,"Alto","Elevado")))) -> Preferencial | N10: FAP/MPS | O10: Revisar
A11: 0112-1/99 | B11: A | C11: Cultivo de outras fibras de lavoura temporária não especificadas anteriormente | D11: AGRICULTURA, PEC | E11: Médio | F11: — | G11: — | H11: — | I11: ='01_PARÂMETROS'!$B$9 -> 50 | J11: =1 -> 1 | K11: =MAX('01_PARÂMETROS'!$B$11,MIN('01_PARÂMETROS'!$B$12,J11)) -> 1 | L11: =(K11-1) -> 0 | M11: =IF(K11<='01_PARÂMETROS'!$B$14,"Preferencial",IF(K11<='01_PARÂMETROS'!$B$15,"Baixo",IF(K11<='01_PARÂMETROS'!$B$16,"Médio",IF(K11<='01_PARÂMETROS'!$B$17,"Alto","Elevado")))) -> Médio | N11: CNAE-STG
A12: 0113-0/00 | B12: A | C12: Cultivo de cana-de-açúcar | D12: AGRICULTURA, PEC | E12: Médio | F12: ='03_FONTE_FAP'!F12 -> 71.161 | G12: ='03_FONTE_FAP'!K12 -> 69.28 | H12: ='03_FONTE_FAP'!M12 -> 70.2205 | I12: ='01_PARÂMETROS'!$B$9 -> 50 | J12: =IFERROR(IF(H12=0,1,H12/I12),1) -> 1.40441 | K12: =MAX('01_PARÂMETROS'!$B$11,MIN('01_PARÂMETROS'!$B$12,J12)) -> 1.4 | L12: =(K12-1) -> 0.4 | M12: =IF(K12<='01_PARÂMETROS'!$B$14,"Preferencial",IF(K12<='01_PARÂMETROS'!$B$15,"Baixo",IF(K12<='01_PARÂMETROS'!$B$16,"Médio",IF(K12<='01_PARÂMETROS'!$B$17,"Alto","Elevado")))) -> Elevado | N12: FAP/MPS
A13: 0114-8/00 | B13: A | C13: Cultivo de fumo | D13: AGRICULTURA, PEC | E13: Médio | F13: ='03_FONTE_FAP'!F13 -> 54.8925 | G13: ='03_FONTE_FAP'!K13 -> 59.626 | H13: ='03_FONTE_FAP'!M13 -> 57.25925 | I13: ='01_PARÂMETROS'!$B$9 -> 50 | J13: =IFERROR(IF(H13=0,1,H13/I13),1) -> 1.145185 | K13: =MAX('01_PARÂMETROS'!$B$11,MIN('01_PARÂMETROS'!$B$12,J13)) -> 1.145185 | L13: =(K13-1) -> 0.145185 | M13: =IF(K13<='01_PARÂMETROS'!$B$14,"Preferencial",IF(K13<='01_PARÂMETROS'!$B$15,"Baixo",IF(K13<='01_PARÂMETROS'!$B$16,"Médio",IF(K13<='01_PARÂMETROS'!$B$17,"Alto","Elevado")))) -> Alto | N13: FAP/MPS
A14: 0115-6/00 | B14: A | C14: Cultivo de soja | D14: AGRICULTURA, PEC | E14: Médio | F14: ='03_FONTE_FAP'!F14 -> 57.5985 | G14: ='03_FONTE_FAP'!K14 -> 59.246 | H14: ='03_FONTE_FAP'!M14 -> 58.42225 | I14: ='01_PARÂMETROS'!$B$9 -> 50 | J14: =IFERROR(IF(H14=0,1,H14/I14),1) -> 1.168445 | K14: =MAX('01_PARÂMETROS'!$B$11,MIN('01_PARÂMETROS'!$B$12,J14)) -> 1.168445 | L14: =(K14-1) -> 0.168445 | M14: =IF(K14<='01_PARÂMETROS'!$B$14,"Preferencial",IF(K14<='01_PARÂMETROS'!$B$15,"Baixo",IF(K14<='01_PARÂMETROS'!$B$16,"Médio",IF(K14<='01_PARÂMETROS'!$B$17,"Alto","Elevado")))) -> Alto | N14: FAP/MPS
A15: 0116-4/01 | B15: A | C15: Cultivo de amendoim | D15: AGRICULTURA, PEC | E15: Médio | F15: ='03_FONTE_FAP'!F15 -> 53.649 | G15: ='03_FONTE_FAP'!K15 -> 0 | H15: ='03_FONTE_FAP'!M15 -> 53.649 | I15: ='01_PARÂMETROS'!$B$9 -> 50 | J15: =IFERROR(IF(H15=0,1,H15/I15),1) -> 1.07298 | K15: =MAX('01_PARÂMETROS'!$B$11,MIN('01_PARÂMETROS'!$B$12,J15)) -> 1.07298 | L15: =(K15-1) -> 0.07298 | M15: =IF(K15<='01_PARÂMETROS'!$B$14,"Preferencial",IF(K15<='01_PARÂMETROS'!$B$15,"Baixo",IF(K15<='01_PARÂMETROS'!$B$16,"Médio",IF(K15<='01_PARÂMETROS'!$B$17,"Alto","Elevado")))) -> Médio | N15: FAP/MPS
A16: 0116-4/02 | B16: A | C16: Cultivo de girassol | D16: AGRICULTURA, PEC | E16: Médio | F16: — | G16: — | H16: — | I16: ='01_PARÂMETROS'!$B$9 -> 50 | J16: =1 -> 1 | K16: =MAX('01_PARÂMETROS'!$B$11,MIN('01_PARÂMETROS'!$B$12,J16)) -> 1 | L16: =(K16-1) -> 0 | M16: =IF(K16<='01_PARÂMETROS'!$B$14,"Preferencial",IF(K16<='01_PARÂMETROS'!$B$15,"Baixo",IF(K16<='01_PARÂMETROS'!$B$16,"Médio",IF(K16<='01_PARÂMETROS'!$B$17,"Alto","Elevado")))) -> Médio | N16: CNAE-STG
A17: 0116-4/03 | B17: A | C17: Cultivo de mamona | D17: AGRICULTURA, PEC | E17: Médio | F17: — | G17: — | H17: — | I17: ='01_PARÂMETROS'!$B$9 -> 50 | J17: =1 -> 1 | K17: =MAX('01_PARÂMETROS'!$B$11,MIN('01_PARÂMETROS'!$B$12,J17)) -> 1 | L17: =(K17-1) -> 0 | M17: =IF(K17<='01_PARÂMETROS'!$B$14,"Preferencial",IF(K17<='01_PARÂMETROS'!$B$15,"Baixo",IF(K17<='01_PARÂMETROS'!$B$16,"Médio",IF(K17<='01_PARÂMETROS'!$B$17,"Alto","Elevado")))) -> Médio | N17: CNAE-STG
A18: 0116-4/99 | B18: A | C18: Cultivo de outras oleaginosas de lavoura temporária não especificadas anteriormente | D18: AGRICULTURA, PEC | E18: Médio | F18: ='03_FONTE_FAP'!F18 -> 9.2025 | G18: ='03_FONTE_FAP'!K18 -> 30.038 | H18: ='03_FONTE_FAP'!M18 -> 19.62025 | I18: ='01_PARÂMETROS'!$B$9 -> 50 | J18: =IFERROR(IF(H18=0,1,H18/I18),1) -> 0.392405 | K18: =MAX('01_PARÂMETROS'!$B$11,MIN('01_PARÂMETROS'!$B$12,J18)) -> 0.75 | L18: =(K18-1) -> -0.25 | M18: =IF(K18<='01_PARÂMETROS'!$B$14,"Preferencial",IF(K18<='01_PARÂMETROS'!$B$15,"Baixo",IF(K18<='01_PARÂMETROS'!$B$16,"Médio",IF(K18<='01_PARÂMETROS'!$B$17,"Alto","Elevado")))) -> Preferencial | N18: FAP/MPS
A19: 0119-9/01 | B19: A | C19: Cultivo de abacaxi | D19: AGRICULTURA, PEC | E19: Médio | F19: — | G19: — | H19: — | I19: ='01_PARÂMETROS'!$B$9 -> 50 | J19: =1 -> 1 | K19: =MAX('01_PARÂMETROS'!$B$11,MIN('01_PARÂMETROS'!$B$12,J19)) -> 1 | L19: =(K19-1) -> 0 | M19: =IF(K19<='01_PARÂMETROS'!$B$14,"Preferencial",IF(K19<='01_PARÂMETROS'!$B$15,"Baixo",IF(K19<='01_PARÂMETROS'!$B$16,"Médio",IF(K19<='01_PARÂMETROS'!$B$17,"Alto","Elevado")))) -> Médio | N19: CNAE-STG
A20: 0119-9/02 | B20: A | C20: Cultivo de alho | D20: AGRICULTURA, PEC | E20: Médio | F20: ='03_FONTE_FAP'!F20 -> 19.209 | G20: ='03_FONTE_FAP'!K20 -> 19.894 | H20: ='03_FONTE_FAP'!M20 -> 19.5515 | I20: ='01_PARÂMETROS'!$B$9 -> 50 | J20: =IFERROR(IF(H20=0,1,H20/I20),1) -> 0.39103 | K20: =MAX('01_PARÂMETROS'!$B$11,MIN('01_PARÂMETROS'!$B$12,J20)) -> 0.75 | L20: =(K20-1) -> -0.25 | M20: =IF(K20<='01_PARÂMETROS'!$B$14,"Preferencial",IF(K20<='01_PARÂMETROS'!$B$15,"Baixo",IF(K20<='01_PARÂMETROS'!$B$16,"Médio",IF(K20<='01_PARÂMETROS'!$B$17,"Alto","Elevado")))) -> Preferencial | N20: FAP/MPS | O20: Revisar
A21: 0119-9/03 | B21: A | C21: Cultivo de batata-inglesa | D21: AGRICULTURA, PEC | E21: Médio | F21: ='03_FONTE_FAP'!F21 -> 52.895 | G21: ='03_FONTE_FAP'!K21 -> 62.7345 | H21: ='03_FONTE_FAP'!M21 -> 57.81475 | I21: ='01_PARÂMETROS'!$B$9 -> 50 | J21: =IFERROR(IF(H21=0,1,H21/I21),1) -> 1.156295 | K21: =MAX('01_PARÂMETROS'!$B$11,MIN('01_PARÂMETROS'!$B$12,J21)) -> 1.156295 | L21: =(K21-1) -> 0.156295 | M21: =IF(K21<='01_PARÂMETROS'!$B$14,"Preferencial",IF(K21<='01_PARÂMETROS'!$B$15,"Baixo",IF(K21<='01_PARÂMETROS'!$B$16,"Médio",IF(K21<='01_PARÂMETROS'!$B$17,"Alto","Elevado")))) -> Alto | N21: FAP/MPS | O21: Revisar
A22: 0119-9/04 | B22: A | C22: Cultivo de cebola | D22: AGRICULTURA, PEC | E22: Médio | F22: ='03_FONTE_FAP'!F22 -> 3.4265 | G22: ='03_FONTE_FAP'!K22 -> 36.4455 | H22: ='03_FONTE_FAP'!M22 -> 19.936 | I22: ='01_PARÂMETROS'!$B$9 -> 50 | J22: =IFERROR(IF(H22=0,1,H22/I22),1) -> 0.39872 | K22: =MAX('01_PARÂMETROS'!$B$11,MIN('01_PARÂMETROS'!$B$12,J22)) -> 0.75 | L22: =(K22-1) -> -0.25 | M22: =IF(K22<='01_PARÂMETROS'!$B$14,"Preferencial",IF(K22<='01_PARÂMETROS'!$B$15,"Baixo",IF(K22<='01_PARÂMETROS'!$B$16,"Médio",IF(K22<='01_PARÂMETROS'!$B$17,"Alto","Elevado")))) -> Preferencial | N22: FAP/MPS | O22: Revisar
A23: 0119-9/05 | B23: A | C23: Cultivo de feijão | D23: AGRICULTURA, PEC | E23: Médio | F23: ='03_FONTE_FAP'!F23 -> 46.636 | G23: ='03_FONTE_FAP'!K23 -> 45.7895 | H23: ='03_FONTE_FAP'!M23 -> 46.21275 | I23: ='01_PARÂMETROS'!$B$9 -> 50 | J23: =IFERROR(IF(H23=0,1,H23/I23),1) -> 0.924255 | K23: =MAX('01_PARÂMETROS'!$B$11,MIN('01_PARÂMETROS'!$B$12,J23)) -> 0.924255 | L23: =(K23-1) -> -0.075745 | M23: =IF(K23<='01_PARÂMETROS'!$B$14,"Preferencial",IF(K23<='01_PARÂMETROS'!$B$15,"Baixo",IF(K23<='01_PARÂMETROS'!$B$16,"Médio",IF(K23<='01_PARÂMETROS'!$B$17,"Alto","Elevado")))) -> Baixo | N23: FAP/MPS | O23: Revisar
A24: 0119-9/06 | B24: A | C24: Cultivo de mandioca | D24: AGRICULTURA, PEC | E24: Médio | F24: ='03_FONTE_FAP'!F24 -> 7.0385 | G24: ='03_FONTE_FAP'!K24 -> 18.9305 | H24: ='03_FONTE_FAP'!M24 -> 12.9845 | I24: ='01_PARÂMETROS'!$B$9 -> 50 | J24: =IFERROR(IF(H24=0,1,H24/I24),1) -> 0.25969 | K24: =MAX('01_PARÂMETROS'!$B$11,MIN('01_PARÂMETROS'!$B$12,J24)) -> 0.75 | L24: =(K24-1) -> -0.25 | M24: =IF(K24<='01_PARÂMETROS'!$B$14,"Preferencial",IF(K24<='01_PARÂMETROS'!$B$15,"Baixo",IF(K24<='01_PARÂMETROS'!$B$16,"Médio",IF(K24<='01_PARÂMETROS'!$B$17,"Alto","Elevado")))) -> Preferencial | N24: FAP/MPS | O24: Revisar
A25: 0119-9/07 | B25: A | C25: Cultivo de melão | D25: AGRICULTURA, PEC | E25: Médio | F25: ='03_FONTE_FAP'!F25 -> 55.4035 | G25: ='03_FONTE_FAP'!K25 -> 46.3505 | H25: ='03_FONTE_FAP'!M25 -> 50.877 | I25: ='01_PARÂMETROS'!$B$9 -> 50 | J25: =IFERROR(IF(H25=0,1,H25/I25),1) -> 1.01754 | K25: =MAX('01_PARÂMETROS'!$B$11,MIN('01_PARÂMETROS'!$B$12,J25)) -> 1.01754 | L25: =(K25-1) -> 0.01754 | M25: =IF(K25<='01_PARÂMETROS'!$B$14,"Preferencial",IF(K25<='01_PARÂMETROS'!$B$15,"Baixo",IF(K25<='01_PARÂMETROS'!$B$16,"Médio",IF(K25<='01_PARÂMETROS'!$B$17,"Alto","Elevado")))) -> Médio | N25: FAP/MPS | O25: Revisar
A26: 0119-9/08 | B26: A | C26: Cultivo de melancia | D26: AGRICULTURA, PEC | E26: Médio | F26: — | G26: — | H26: — | I26: ='01_PARÂMETROS'!$B$9 -> 50 | J26: =1 -> 1 | K26: =MAX('01_PARÂMETROS'!$B$11,MIN('01_PARÂMETROS'!$B$12,J26)) -> 1 | L26: =(K26-1) -> 0 | M26: =IF(K26<='01_PARÂMETROS'!$B$14,"Preferencial",IF(K26<='01_PARÂMETROS'!$B$15,"Baixo",IF(K26<='01_PARÂMETROS'!$B$16,"Médio",IF(K26<='01_PARÂMETROS'!$B$17,"Alto","Elevado")))) -> Médio | N26: CNAE-STG
A27: 0119-9/09 | B27: A | C27: Cultivo de tomate rasteiro | D27: AGRICULTURA, PEC | E27: Médio | F27: ='03_FONTE_FAP'!F27 -> 12.137 | G27: ='03_FONTE_FAP'!K27 -> 11.298 | H27: ='03_FONTE_FAP'!M27 -> 11.7175 | I27: ='01_PARÂMETROS'!$B$9 -> 50 | J27: =IFERROR(IF(H27=0,1,H27/I27),1) -> 0.23435 | K27: =MAX('01_PARÂMETROS'!$B$11,MIN('01_PARÂMETROS'!$B$12,J27)) -> 0.75 | L27: =(K27-1) -> -0.25 | M27: =IF(K27<='01_PARÂMETROS'!$B$14,"Preferencial",IF(K27<='01_PARÂMETROS'!$B$15,"Baixo",IF(K27<='01_PARÂMETROS'!$B$16,"Médio",IF(K27<='01_PARÂMETROS'!$B$17,"Alto","Elevado")))) -> Preferencial | N27: FAP/MPS | O27: Revisar
A28: 0119-9/99 | B28: A | C28: Cultivo de outras plantas de lavoura temporária não especificadas anteriormente | D28: AGRICULTURA, PEC | E28: Médio | F28: ='03_FONTE_FAP'!F28 -> 69.6125 | G28: ='03_FONTE_FAP'!K28 -> 59.088 | H28: ='03_FONTE_FAP'!M28 -> 64.35025 | I28: ='01_PARÂMETROS'!$B$9 -> 50 | J28: =IFERROR(IF(H28=0,1,H28/I28),1) -> 1.287005 | K28: =MAX('01_PARÂMETROS'!$B$11,MIN('01_PARÂMETROS'!$B$12,J28)) -> 1.287005 | L28: =(K28-1) -> 0.287005 | M28: =IF(K28<='01_PARÂMETROS'!$B$14,"Preferencial",IF(K28<='01_PARÂMETROS'!$B$15,"Baixo",IF(K28<='01_PARÂMETROS'!$B$16,"Médio",IF(K28<='01_PARÂMETROS'!$B$17,"Alto","Elevado")))) -> Elevado | N28: FAP/MPS | O28: Revisar
A29: 0121-1/01 | B29: A | C29: Horticultura, exceto morango | D29: AGRICULTURA, PEC | E29: Médio | F29: ='03_FONTE_FAP'!F29 -> 31.979 | G29: ='03_FONTE_FAP'!K29 -> 35.085 | H29: ='03_FONTE_FAP'!M29 -> 33.532 | I29: ='01_PARÂMETROS'!$B$9 -> 50 | J29: =IFERROR(IF(H29=0,1,H29/I29),1) -> 0.67064 | K29: =MAX('01_PARÂMETROS'!$B$11,MIN('01_PARÂMETROS'!$B$12,J29)) -> 0.75 | L29: =(K29-1) -> -0.25 | M29: =IF(K29<='01_PARÂMETROS'!$B$14,"Preferencial",IF(K29<='01_PARÂMETROS'!$B$15,"Baixo",IF(K29<='01_PARÂMETROS'!$B$16,"Médio",IF(K29<='01_PARÂMETROS'!$B$17,"Alto","Elevado")))) -> Preferencial | N29: FAP/MPS
A30: 0121-1/02 | B30: A | C30: Cultivo de morango | D30: AGRICULTURA, PEC | E30: Médio | F30: ='03_FONTE_FAP'!F30 -> 19.9655 | G30: ='03_FONTE_FAP'!K30 -> 70.6095 | H30: ='03_FONTE_FAP'!M30 -> 45.2875 | I30: ='01_PARÂMETROS'!$B$9 -> 50 | J30: =IFERROR(IF(H30=0,1,H30/I30),1) -> 0.90575 | K30: =MAX('01_PARÂMETROS'!$B$11,MIN('01_PARÂMETROS'!$B$12,J30)) -> 0.90575 | L30: =(K30-1) -> -0.09425 | M30: =IF(K30<='01_PARÂMETROS'!$B$14,"Preferencial",IF(K30<='01_PARÂMETROS'!$B$15,"Baixo",IF(K30<='01_PARÂMETROS'!$B$16,"Médio",IF(K30<='01_PARÂMETROS'!$B$17,"Alto","Elevado")))) -> Baixo | N30: FAP/MPS
A31: 0122-9/00 | B31: A | C31: Cultivo de flores e plantas ornamentais | D31: AGRICULTURA, PEC | E31: Médio | F31: ='03_FONTE_FAP'!F31 -> 35.6045 | G31: ='03_FONTE_FAP'!K31 -> 37.405 | H31: ='03_FONTE_FAP'!M31 -> 36.50475 | I31: ='01_PARÂMETROS'!$B$9 -> 50 | J31: =IFERROR(IF(H31=0,1,H31/I31),1) -> 0.730095 | K31: =MAX('01_PARÂMETROS'!$B$11,MIN('01_PARÂMETROS'!$B$12,J31)) -> 0.75 | L31: =(K31-1) -> -0.25 | M31: =IF(K31<='01_PARÂMETROS'!$B$14,"Preferencial",IF(K31<='01_PARÂMETROS'!$B$15,"Baixo",IF(K31<='01_PARÂMETROS'!$B$16,"Médio",IF(K31<='01_PARÂMETROS'!$B$17,"Alto","Elevado")))) -> Preferencial | N31: FAP/MPS
A32: 0131-8/00 | B32: A | C32: Cultivo de laranja | D32: AGRICULTURA, PEC | E32: Médio | F32: ='03_FONTE_FAP'!F32 -> 71.826 | G32: ='03_FONTE_FAP'!K32 -> 75.529 | H32: ='03_FONTE_FAP'!M32 -> 73.6775 | I32: ='01_PARÂMETROS'!$B$9 -> 50 | J32: =IFERROR(IF(H32=0,1,H32/I32),1) -> 1.47355 | K32: =MAX('01_PARÂMETROS'!$B$11,MIN('01_PARÂMETROS'!$B$12,J32)) -> 1.4 | L32: =(K32-1) -> 0.4 | M32: =IF(K32<='01_PARÂMETROS'!$B$14,"Preferencial",IF(K32<='01_PARÂMETROS'!$B$15,"Baixo",IF(K32<='01_PARÂMETROS'!$B$16,"Médio",IF(K32<='01_PARÂMETROS'!$B$17,"Alto","Elevado")))) -> Elevado | N32: FAP/MPS
A33: 0132-6/00 | B33: A | C33: Cultivo de uva | D33: AGRICULTURA, PEC | E33: Médio | F33: ='03_FONTE_FAP'!F33 -> 56.737 | G33: ='03_FONTE_FAP'!K33 -> 57.9025 | H33: ='03_FONTE_FAP'!M33 -> 57.31975 | I33: ='01_PARÂMETROS'!$B$9 -> 50 | J33: =IFERROR(IF(H33=0,1,H33/I33),1) -> 1.146395 | K33: =MAX('01_PARÂMETROS'!$B$11,MIN('01_PARÂMETROS'!$B$12,J33)) -> 1.146395 | L33: =(K33-1) -> 0.146395 | M33: =IF(K33<='01_PARÂMETROS'!$B$14,"Preferencial",IF(K33<='01_PARÂMETROS'!$B$15,"Baixo",IF(K33<='01_PARÂMETROS'!$B$16,"Médio",IF(K33<='01_PARÂMETROS'!$B$17,"Alto","Elevado")))) -> Alto | N33: FAP/MPS
A34: 0133-4/01 | B34: A | C34: Cultivo de açaí | D34: AGRICULTURA, PEC | E34: Médio | F34: ='03_FONTE_FAP'!F34 -> 26.84 | G34: ='03_FONTE_FAP'!K34 -> 46.0695 | H34: ='03_FONTE_FAP'!M34 -> 36.45475 | I34: ='01_PARÂMETROS'!$B$9 -> 50 | J34: =IFERROR(IF(H34=0,1,H34/I34),1) -> 0.729095 | K34: =MAX('01_PARÂMETROS'!$B$11,MIN('01_PARÂMETROS'!$B$12,J34)) -> 0.75 | L34: =(K34-1) -> -0.25 | M34: =IF(K34<='01_PARÂMETROS'!$B$14,"Preferencial",IF(K34<='01_PARÂMETROS'!$B$15,"Baixo",IF(K34<='01_PARÂMETROS'!$B$16,"Médio",IF(K34<='01_PARÂMETROS'!$B$17,"Alto","Elevado")))) -> Preferencial | N34: FAP/MPS | O34: Revisar
A35: 0133-4/02 | B35: A | C35: Cultivo de banana | D35: AGRICULTURA, PEC | E35: Médio | F35: ='03_FONTE_FAP'!F35 -> 62.6995 | G35: ='03_FONTE_FAP'!K35 -> 63.115 | H35: ='03_FONTE_FAP'!M35 -> 62.90725 | I35: ='01_PARÂMETROS'!$B$9 -> 50 | J35: =IFERROR(IF(H35=0,1,H35/I35),1) -> 1.258145 | K35: =MAX('01_PARÂMETROS'!$B$11,MIN('01_PARÂMETROS'!$B$12,J35)) -> 1.258145 | L35: =(K35-1) -> 0.258145 | M35: =IF(K35<='01_PARÂMETROS'!$B$14,"Preferencial",IF(K35<='01_PARÂMETROS'!$B$15,"Baixo",IF(K35<='01_PARÂMETROS'!$B$16,"Médio",IF(K35<='01_PARÂMETROS'!$B$17,"Alto","Elevado")))) -> Elevado | N35: FAP/MPS | O35: Revisar
A36: 0133-4/03 | B36: A | C36: Cultivo de caju | D36: AGRICULTURA, PEC | E36: Médio | F36: ='03_FONTE_FAP'!F36 -> 90.208 | G36: ='03_FONTE_FAP'!K36 -> 84.191 | H36: ='03_FONTE_FAP'!M36 -> 87.1995 | I36: ='01_PARÂMETROS'!$B$9 -> 50 | J36: =IFERROR(IF(H36=0,1,H36/I36),1) -> 1.74399 | K36: =MAX('01_PARÂMETROS'!$B$11,MIN('01_PARÂMETROS'!$B$12,J36)) -> 1.4 | L36: =(K36-1) -> 0.4 | M36: =IF(K36<='01_PARÂMETROS'!$B$14,"Preferencial",IF(K36<='01_PARÂMETROS'!$B$15,"Baixo",IF(K36<='01_PARÂMETROS'!$B$16,"Médio",IF(K36<='01_PARÂMETROS'!$B$17,"Alto","Elevado")))) -> Elevado | N36: FAP/MPS | O36: Revisar
A37: 0133-4/04 | B37: A | C37: Cultivo de cítricos, exceto laranja | D37: AGRICULTURA, PEC | E37: Médio | F37: ='03_FONTE_FAP'!F37 -> 37.166 | G37: ='03_FONTE_FAP'!K37 -> 40.2345 | H37: ='03_FONTE_FAP'!M37 -> 38.70025 | I37: ='01_PARÂMETROS'!$B$9 -> 50 | J37: =IFERROR(IF(H37=0,1,H37/I37),1) -> 0.774005 | K37: =MAX('01_PARÂMETROS'!$B$11,MIN('01_PARÂMETROS'!$B$12,J37)) -> 0.774005 | L37: =(K37-1) -> -0.225995 | M37: =IF(K37<='01_PARÂMETROS'!$B$14,"Preferencial",IF(K37<='01_PARÂMETROS'!$B$15,"Baixo",IF(K37<='01_PARÂMETROS'!$B$16,"Médio",IF(K37<='01_PARÂMETROS'!$B$17,"Alto","Elevado")))) -> Preferencial | N37: FAP/MPS | O37: Revisar
A38: 0133-4/05 | B38: A | C38: Cultivo de coco-da-baía | D38: AGRICULTURA, PEC | E38: Médio | F38: ='03_FONTE_FAP'!F38 -> 63.138 | G38: ='03_FONTE_FAP'!K38 -> 68.082 | H38: ='03_FONTE_FAP'!M38 -> 65.61 | I38: ='01_PARÂMETROS'!$B$9 -> 50 | J38: =IFERROR(IF(H38=0,1,H38/I38),1) -> 1.3122 | K38: =MAX('01_PARÂMETROS'!$B$11,MIN('01_PARÂMETROS'!$B$12,J38)) -> 1.3122 | L38: =(K38-1) -> 0.3122 | M38: =IF(K38<='01_PARÂMETROS'!$B$14,"Preferencial",IF(K38<='01_PARÂMETROS'!$B$15,"Baixo",IF(K38<='01_PARÂMETROS'!$B$16,"Médio",IF(K38<='01_PARÂMETROS'!$B$17,"Alto","Elevado")))) -> Elevado | N38: FAP/MPS | O38: Revisar
A39: 0133-4/06 | B39: A | C39: Cultivo de guaraná | D39: AGRICULTURA, PEC | E39: Médio | F39: — | G39: — | H39: — | I39: ='01_PARÂMETROS'!$B$9 -> 50 | J39: =1 -> 1 | K39: =MAX('01_PARÂMETROS'!$B$11,MIN('01_PARÂMETROS'!$B$12,J39)) -> 1 | L39: =(K39-1) -> 0 | M39: =IF(K39<='01_PARÂMETROS'!$B$14,"Preferencial",IF(K39<='01_PARÂMETROS'!$B$15,"Baixo",IF(K39<='01_PARÂMETROS'!$B$16,"Médio",IF(K39<='01_PARÂMETROS'!$B$17,"Alto","Elevado")))) -> Médio | N39: CNAE-STG
A40: 0133-4/07 | B40: A | C40: Cultivo de maçã | D40: AGRICULTURA, PEC | E40: Médio | F40: ='03_FONTE_FAP'!F40 -> 79.2735 | G40: ='03_FONTE_FAP'!K40 -> 55.328 | H40: ='03_FONTE_FAP'!M40 -> 67.30075 | I40: ='01_PARÂMETROS'!$B$9 -> 50 | J40: =IFERROR(IF(H40=0,1,H40/I40),1) -> 1.346015 | K40: =MAX('01_PARÂMETROS'!$B$11,MIN('01_PARÂMETROS'!$B$12,J40)) -> 1.346015 | L40: =(K40-1) -> 0.346015 | M40: =IF(K40<='01_PARÂMETROS'!$B$14,"Preferencial",IF(K40<='01_PARÂMETROS'!$B$15,"Baixo",IF(K40<='01_PARÂMETROS'!$B$16,"Médio",IF(K40<='01_PARÂMETROS'!$B$17,"Alto","Elevado")))) -> Elevado | N40: FAP/MPS | O40: Revisar
A41: 0133-4/08 | B41: A | C41: Cultivo de mamão | D41: AGRICULTURA, PEC | E41: Médio | F41: ='03_FONTE_FAP'!F41 -> 61.526 | G41: ='03_FONTE_FAP'!K41 -> 51.26 | H41: ='03_FONTE_FAP'!M41 -> 56.393 | I41: ='01_PARÂMETROS'!$B$9 -> 50 | J41: =IFERROR(IF(H41=0,1,H41/I41),1) -> 1.12786 | K41: =MAX('01_PARÂMETROS'!$B$11,MIN('01_PARÂMETROS'!$B$12,J41)) -> 1.12786 | L41: =(K41-1) -> 0.12786 | M41: =IF(K41<='01_PARÂMETROS'!$B$14,"Preferencial",IF(K41<='01_PARÂMETROS'!$B$15,"Baixo",IF(K41<='01_PARÂMETROS'!$B$16,"Médio",IF(K41<='01_PARÂMETROS'!$B$17,"Alto","Elevado")))) -> Alto | N41: FAP/MPS | O41: Revisar
A42: 0133-4/09 | B42: A | C42: Cultivo de maracujá | D42: AGRICULTURA, PEC | E42: Médio | F42: ='03_FONTE_FAP'!F42 -> 13.4155 | G42: ='03_FONTE_FAP'!K42 -> 64.26 | H42: ='03_FONTE_FAP'!M42 -> 38.83775 | I42: ='01_PARÂMETROS'!$B$9 -> 50 | J42: =IFERROR(IF(H42=0,1,H42/I42),1) -> 0.776755 | K42: =MAX('01_PARÂMETROS'!$B$11,MIN('01_PARÂMETROS'!$B$12,J42)) -> 0.776755 | L42: =(K42-1) -> -0.223245 | M42: =IF(K42<='01_PARÂMETROS'!$B$14,"Preferencial",IF(K42<='01_PARÂMETROS'!$B$15,"Baixo",IF(K42<='01_PARÂMETROS'!$B$16,"Médio",IF(K42<='01_PARÂMETROS'!$B$17,"Alto","Elevado")))) -> Preferencial | N42: FAP/MPS | O42: Revisar
A43: 0133-4/10 | B43: A | C43: Cultivo de manga | D43: AGRICULTURA, PEC | E43: Médio | F43: ='03_FONTE_FAP'!F43 -> 36.4 | G43: ='03_FONTE_FAP'!K43 -> 40.116 | H43: ='03_FONTE_FAP'!M43 -> 38.258 | I43: ='01_PARÂMETROS'!$B$9 -> 50 | J43: =IFERROR(IF(H43=0,1,H43/I43),1) -> 0.76516 | K43: =MAX('01_PARÂMETROS'!$B$11,MIN('01_PARÂMETROS'!$B$12,J43)) -> 0.76516 | L43: =(K43-1) -> -0.23484 | M43: =IF(K43<='01_PARÂMETROS'!$B$14,"Preferencial",IF(K43<='01_PARÂMETROS'!$B$15,"Baixo",IF(K43<='01_PARÂMETROS'!$B$16,"Médio",IF(K43<='01_PARÂMETROS'!$B$17,"Alto","Elevado")))) -> Preferencial | N43: FAP/MPS | O43: Revisar
A44: 0133-4/11 | B44: A | C44: Cultivo de pêssego | D44: AGRICULTURA, PEC | E44: Médio | F44: — | G44: — | H44: — | I44: ='01_PARÂMETROS'!$B$9 -> 50 | J44: =1 -> 1 | K44: =MAX('01_PARÂMETROS'!$B$11,MIN('01_PARÂMETROS'!$B$12,J44)) -> 1 | L44: =(K44-1) -> 0 | M44: =IF(K44<='01_PARÂMETROS'!$B$14,"Preferencial",IF(K44<='01_PARÂMETROS'!$B$15,"Baixo",IF(K44<='01_PARÂMETROS'!$B$16,"Médio",IF(K44<='01_PARÂMETROS'!$B$17,"Alto","Elevado")))) -> Médio | N44: CNAE-STG
A45: 0133-4/99 | B45: A | C45: Cultivo de frutas de lavoura permanente não especificadas anteriormente | D45: AGRICULTURA, PEC | E45: Médio | F45: ='03_FONTE_FAP'!F45 -> 52.1995 | G45: ='03_FONTE_FAP'!K45 -> 42.396 | H45: ='03_FONTE_FAP'!M45 -> 47.29775 | I45: ='01_PARÂMETROS'!$B$9 -> 50 | J45: =IFERROR(IF(H45=0,1,H45/I45),1) -> 0.945955 | K45: =MAX('01_PARÂMETROS'!$B$11,MIN('01_PARÂMETROS'!$B$12,J45)) -> 0.945955 | L45: =(K45-1) -> -0.054045 | M45: =IF(K45<='01_PARÂMETROS'!$B$14,"Preferencial",IF(K45<='01_PARÂMETROS'!$B$15,"Baixo",IF(K45<='01_PARÂMETROS'!$B$16,"Médio",IF(K45<='01_PARÂMETROS'!$B$17,"Alto","Elevado")))) -> Baixo | N45: FAP/MPS | O45: Revisar
A46: 0134-2/00 | B46: A | C46: Cultivo de café | D46: AGRICULTURA, PEC | E46: Médio | F46: ='03_FONTE_FAP'!F46 -> 72.5225 | G46: ='03_FONTE_FAP'!K46 -> 63.268 | H46: ='03_FONTE_FAP'!M46 -> 67.89525 | I46: ='01_PARÂMETROS'!$B$9 -> 50 | J46: =IFERROR(IF(H46=0,1,H46/I46),1) -> 1.357905 | K46: =MAX('01_PARÂMETROS'!$B$11,MIN('01_PARÂMETROS'!$B$12,J46)) -> 1.357905 | L46: =(K46-1) -> 0.357905 | M46: =IF(K46<='01_PARÂMETROS'!$B$14,"Preferencial",IF(K46<='01_PARÂMETROS'!$B$15,"Baixo",IF(K46<='01_PARÂMETROS'!$B$16,"Médio",IF(K46<='01_PARÂMETROS'!$B$17,"Alto","Elevado")))) -> Elevado | N46: FAP/MPS
A47: 0135-1/00 | B47: A | C47: Cultivo de cacau | D47: AGRICULTURA, PEC | E47: Médio | F47: ='03_FONTE_FAP'!F47 -> 74.0825 | G47: ='03_FONTE_FAP'!K47 -> 50.2305 | H47: ='03_FONTE_FAP'!M47 -> 62.1565 | I47: ='01_PARÂMETROS'!$B$9 -> 50 | J47: =IFERROR(IF(H47=0,1,H47/I47),1) -> 1.24313 | K47: =MAX('01_PARÂMETROS'!$B$11,MIN('01_PARÂMETROS'!$B$12,J47)) -> 1.24313 | L47: =(K47-1) -> 0.24313 | M47: =IF(K47<='01_PARÂMETROS'!$B$14,"Preferencial",IF(K47<='01_PARÂMETROS'!$B$15,"Baixo",IF(K47<='01_PARÂMETROS'!$B$16,"Médio",IF(K47<='01_PARÂMETROS'!$B$17,"Alto","Elevado")))) -> Elevado | N47: FAP/MPS
A48: 0139-3/01 | B48: A | C48: Cultivo de chá-da-índia | D48: AGRICULTURA, PEC | E48: Médio | F48: — | G48: — | H48: — | I48: ='01_PARÂMETROS'!$B$9 -> 50 | J48: =1 -> 1 | K48: =MAX('01_PARÂMETROS'!$B$11,MIN('01_PARÂMETROS'!$B$12,J48)) -> 1 | L48: =(K48-1) -> 0 | M48: =IF(K48<='01_PARÂMETROS'!$B$14,"Preferencial",IF(K48<='01_PARÂMETROS'!$B$15,"Baixo",IF(K48<='01_PARÂMETROS'!$B$16,"Médio",IF(K48<='01_PARÂMETROS'!$B$17,"Alto","Elevado")))) -> Médio | N48: CNAE-STG
A49: 0139-3/02 | B49: A | C49: Cultivo de erva-mate | D49: AGRICULTURA, PEC | E49: Médio | F49: ='03_FONTE_FAP'!F49 -> 57.7545 | G49: ='03_FONTE_FAP'!K49 -> 31.3615 | H49: ='03_FONTE_FAP'!M49 -> 44.558 | I49: ='01_PARÂMETROS'!$B$9 -> 50 | J49: =IFERROR(IF(H49=0,1,H49/I49),1) -> 0.89116 | K49: =MAX('01_PARÂMETROS'!$B$11,MIN('01_PARÂMETROS'!$B$12,J49)) -> 0.89116 | L49: =(K49-1) -> -0.10884 | M49: =IF(K49<='01_PARÂMETROS'!$B$14,"Preferencial",IF(K49<='01_PARÂMETROS'!$B$15,"Baixo",IF(K49<='01_PARÂMETROS'!$B$16,"Médio",IF(K49<='01_PARÂMETROS'!$B$17,"Alto","Elevado")))) -> Baixo | N49: FAP/MPS | O49: Revisar
A50: 0139-3/03 | B50: A | C50: Cultivo de pimenta-do-reino | D50: AGRICULTURA, PEC | E50: Médio | F50: ='03_FONTE_FAP'!F50 -> 76.649 | G50: ='03_FONTE_FAP'!K50 -> 0 | H50: ='03_FONTE_FAP'!M50 -> 76.649 | I50: ='01_PARÂMETROS'!$B$9 -> 50 | J50: =IFERROR(IF(H50=0,1,H50/I50),1) -> 1.53298 | K50: =MAX('01_PARÂMETROS'!$B$11,MIN('01_PARÂMETROS'!$B$12,J50)) -> 1.4 | L50: =(K50-1) -> 0.4 | M50: =IF(K50<='01_PARÂMETROS'!$B$14,"Preferencial",IF(K50<='01_PARÂMETROS'!$B$15,"Baixo",IF(K50<='01_PARÂMETROS'!$B$16,"Médio",IF(K50<='01_PARÂMETROS'!$B$17,"Alto","Elevado")))) -> Elevado | N50: FAP/MPS | O50: Revisar
A51: 0139-3/04 | B51: A | C51: Cultivo de plantas para condimento, exceto pimenta-do-reino | D51: AGRICULTURA, PEC | E51: Médio | F51: ='03_FONTE_FAP'!F51 -> 0 | G51: ='03_FONTE_FAP'!K51 -> 28.539 | H51: ='03_FONTE_FAP'!M51 -> 28.539 | I51: ='01_PARÂMETROS'!$B$9 -> 50 | J51: =IFERROR(IF(H51=0,1,H51/I51),1) -> 0.57078 | K51: =MAX('01_PARÂMETROS'!$B$11,MIN('01_PARÂMETROS'!$B$12,J51)) -> 0.75 | L51: =(K51-1) -> -0.25 | M51: =IF(K51<='01_PARÂMETROS'!$B$14,"Preferencial",IF(K51<='01_PARÂMETROS'!$B$15,"Baixo",IF(K51<='01_PARÂMETROS'!$B$16,"Médio",IF(K51<='01_PARÂMETROS'!$B$17,"Alto","Elevado")))) -> Preferencial | N51: FAP/MPS | O51: Revisar
A52: 0139-3/05 | B52: A | C52: Cultivo de dendê | D52: AGRICULTURA, PEC | E52: Médio | F52: ='03_FONTE_FAP'!F52 -> 73.8365 | G52: ='03_FONTE_FAP'!K52 -> 65.8785 | H52: ='03_FONTE_FAP'!M52 -> 69.8575 | I52: ='01_PARÂMETROS'!$B$9 -> 50 | J52: =IFERROR(IF(H52=0,1,H52/I52),1) -> 1.39715 | K52: =MAX('01_PARÂMETROS'!$B$11,MIN('01_PARÂMETROS'!$B$12,J52)) -> 1.39715 | L52: =(K52-1) -> 0.39715 | M52: =IF(K52<='01_PARÂMETROS'!$B$14,"Preferencial",IF(K52<='01_PARÂMETROS'!$B$15,"Baixo",IF(K52<='01_PARÂMETROS'!$B$16,"Médio",IF(K52<='01_PARÂMETROS'!$B$17,"Alto","Elevado")))) -> Elevado | N52: FAP/MPS | O52: Revisar
A53: 0139-3/06 | B53: A | C53: Cultivo de seringueira | D53: AGRICULTURA, PEC | E53: Médio | F53: ='03_FONTE_FAP'!F53 -> 15.85 | G53: ='03_FONTE_FAP'!K53 -> 15.0795 | H53: ='03_FONTE_FAP'!M53 -> 15.46475 | I53: ='01_PARÂMETROS'!$B$9 -> 50 | J53: =IFERROR(IF(H53=0,1,H53/I53),1) -> 0.309295 | K53: =MAX('01_PARÂMETROS'!$B$11,MIN('01_PARÂMETROS'!$B$12,J53)) -> 0.75 | L53: =(K53-1) -> -0.25 | M53: =IF(K53<='01_PARÂMETROS'!$B$14,"Preferencial",IF(K53<='01_PARÂMETROS'!$B$15,"Baixo",IF(K53<='01_PARÂMETROS'!$B$16,"Médio",IF(K53<='01_PARÂMETROS'!$B$17,"Alto","Elevado")))) -> Preferencial | N53: FAP/MPS | O53: Revisar
A54: 0139-3/99 | B54: A | C54: Cultivo de outras plantas de lavoura permanente não especificadas anteriormente | D54: AGRICULTURA, PEC | E54: Médio | F54: ='03_FONTE_FAP'!F54 -> 58.4115 | G54: ='03_FONTE_FAP'!K54 -> 52.808 | H54: ='03_FONTE_FAP'!M54 -> 55.60975 | I54: ='01_PARÂMETROS'!$B$9 -> 50 | J54: =IFERROR(IF(H54=0,1,H54/I54),1) -> 1.112195 | K54: =MAX('01_PARÂMETROS'!$B$11,MIN('01_PARÂMETROS'!$B$12,J54)) -> 1.112195 | L54: =(K54-1) -> 0.112195 | M54: =IF(K54<='01_PARÂMETROS'!$B$14,"Preferencial",IF(K54<='01_PARÂMETROS'!$B$15,"Baixo",IF(K54<='01_PARÂMETROS'!$B$16,"Médio",IF(K54<='01_PARÂMETROS'!$B$17,"Alto","Elevado")))) -> Alto | N54: FAP/MPS | O54: Revisar
A55: 0141-5/01 | B55: A | C55: Produção de sementes certificadas, exceto de forrageiras para pasto | D55: AGRICULTURA, PEC | E55: Médio | F55: ='03_FONTE_FAP'!F55 -> 37.7895 | G55: ='03_FONTE_FAP'!K55 -> 30.7695 | H55: ='03_FONTE_FAP'!M55 -> 34.2795 | I55: ='01_PARÂMETROS'!$B$9 -> 50 | J55: =IFERROR(IF(H55=0,1,H55/I55),1) -> 0.68559 | K55: =MAX('01_PARÂMETROS'!$B$11,MIN('01_PARÂMETROS'!$B$12,J55)) -> 0.75 | L55: =(K55-1) -> -0.25 | M55: =IF(K55<='01_PARÂMETROS'!$B$14,"Preferencial",IF(K55<='01_PARÂMETROS'!$B$15,"Baixo",IF(K55<='01_PARÂMETROS'!$B$16,"Médio",IF(K55<='01_PARÂMETROS'!$B$17,"Alto","Elevado")))) -> Preferencial | N55: FAP/MPS | O55: Revisar
A56: 0141-5/02 | B56: A | C56: Produção de sementes certificadas de forrageiras para formação de pasto | D56: AGRICULTURA, PEC | E56: Médio | F56: ='03_FONTE_FAP'!F56 -> 82.476 | G56: ='03_FONTE_FAP'!K56 -> 61.565 | H56: ='03_FONTE_FAP'!M56 -> 72.0205 | I56: ='01_PARÂMETROS'!$B$9 -> 50 | J56: =IFERROR(IF(H56=0,1,H56/I56),1) -> 1.44041 | K56: =MAX('01_PARÂMETROS'!$B$11,MIN('01_PARÂMETROS'!$B$12,J56)) -> 1.4 | L56: =(K56-1) -> 0.4 | M56: =IF(K56<='01_PARÂMETROS'!$B$14,"Preferencial",IF(K56<='01_PARÂMETROS'!$B$15,"Baixo",IF(K56<='01_PARÂMETROS'!$B$16,"Médio",IF(K56<='01_PARÂMETROS'!$B$17,"Alto","Elevado")))) -> Elevado | N56: FAP/MPS | O56: Revisar
A57: 0142-3/00 | B57: A | C57: Produção de mudas e outras formas de propagação vegetal, certificadas | D57: AGRICULTURA, PEC | E57: Médio | F57: ='03_FONTE_FAP'!F57 -> 45.365 | G57: ='03_FONTE_FAP'!K57 -> 29.648 | H57: ='03_FONTE_FAP'!M57 -> 37.5065 | I57: ='01_PARÂMETROS'!$B$9 -> 50 | J57: =IFERROR(IF(H57=0,1,H57/I57),1) -> 0.75013 | K57: =MAX('01_PARÂMETROS'!$B$11,MIN('01_PARÂMETROS'!$B$12,J57)) -> 0.75013 | L57: =(K57-1) -> -0.24987 | M57: =IF(K57<='01_PARÂMETROS'!$B$14,"Preferencial",IF(K57<='01_PARÂMETROS'!$B$15,"Baixo",IF(K57<='01_PARÂMETROS'!$B$16,"Médio",IF(K57<='01_PARÂMETROS'!$B$17,"Alto","Elevado")))) -> Preferencial | N57: FAP/MPS
A58: 0151-2/01 | B58: A | C58: Criação de bovinos para corte | D58: AGRICULTURA, PEC | E58: Médio | F58: ='03_FONTE_FAP'!F58 -> 84.53 | G58: ='03_FONTE_FAP'!K58 -> 83.647 | H58: ='03_FONTE_FAP'!M58 -> 84.0885 | I58: ='01_PARÂMETROS'!$B$9 -> 50 | J58: =IFERROR(IF(H58=0,1,H58/I58),1) -> 1.68177 | K58: =MAX('01_PARÂMETROS'!$B$11,MIN('01_PARÂMETROS'!$B$12,J58)) -> 1.4 | L58: =(K58-1) -> 0.4 | M58: =IF(K58<='01_PARÂMETROS'!$B$14,"Preferencial",IF(K58<='01_PARÂMETROS'!$B$15,"Baixo",IF(K58<='01_PARÂMETROS'!$B$16,"Médio",IF(K58<='01_PARÂMETROS'!$B$17,"Alto","Elevado")))) -> Elevado | N58: FAP/MPS
A59: 0151-2/02 | B59: A | C59: Criação de bovinos para leite | D59: AGRICULTURA, PEC | E59: Médio | F59: ='03_FONTE_FAP'!F59 -> 62.015 | G59: ='03_FONTE_FAP'!K59 -> 64.701 | H59: ='03_FONTE_FAP'!M59 -> 63.358 | I59: ='01_PARÂMETROS'!$B$9 -> 50 | J59: =IFERROR(IF(H59=0,1,H59/I59),1) -> 1.26716 | K59: =MAX('01_PARÂMETROS'!$B$11,MIN('01_PARÂMETROS'!$B$12,J59)) -> 1.26716 | L59: =(K59-1) -> 0.26716 | M59: =IF(K59<='01_PARÂMETROS'!$B$14,"Preferencial",IF(K59<='01_PARÂMETROS'!$B$15,"Baixo",IF(K59<='01_PARÂMETROS'!$B$16,"Médio",IF(K59<='01_PARÂMETROS'!$B$17,"Alto","Elevado")))) -> Elevado | N59: FAP/MPS
A60: 0151-2/03 | B60: A | C60: Criação de bovinos, exceto para corte e leite | D60: AGRICULTURA, PEC | E60: Médio | F60: ='03_FONTE_FAP'!F60 -> 79.0455 | G60: ='03_FONTE_FAP'!K60 -> 82.783 | H60: ='03_FONTE_FAP'!M60 -> 80.91425 | I60: ='01_PARÂMETROS'!$B$9 -> 50 | J60: =IFERROR(IF(H60=0,1,H60/I60),1) -> 1.618285 | K60: =MAX('01_PARÂMETROS'!$B$11,MIN('01_PARÂMETROS'!$B$12,J60)) -> 1.4 | L60: =(K60-1) -> 0.4 | M60: =IF(K60<='01_PARÂMETROS'!$B$14,"Preferencial",IF(K60<='01_PARÂMETROS'!$B$15,"Baixo",IF(K60<='01_PARÂMETROS'!$B$16,"Médio",IF(K60<='01_PARÂMETROS'!$B$17,"Alto","Elevado")))) -> Elevado | N60: FAP/MPS
A61: 0152-1/01 | B61: A | C61: Criação de bufalinos | D61: AGRICULTURA, PEC | E61: Médio | F61: ='03_FONTE_FAP'!F61 -> 37.635 | G61: ='03_FONTE_FAP'!K61 -> 31.05 | H61: ='03_FONTE_FAP'!M61 -> 34.3425 | I61: ='01_PARÂMETROS'!$B$9 -> 50 | J61: =IFERROR(IF(H61=0,1,H61/I61),1) -> 0.68685 | K61: =MAX('01_PARÂMETROS'!$B$11,MIN('01_PARÂMETROS'!$B$12,J61)) -> 0.75 | L61: =(K61-1) -> -0.25 | M61: =IF(K61<='01_PARÂMETROS'!$B$14,"Preferencial",IF(K61<='01_PARÂMETROS'!$B$15,"Baixo",IF(K61<='01_PARÂMETROS'!$B$16,"Médio",IF(K61<='01_PARÂMETROS'!$B$17,"Alto","Elevado")))) -> Preferencial | N61: FAP/MPS | O61: Revisar
A62: 0152-1/02 | B62: A | C62: Criação de equinos | D62: AGRICULTURA, PEC | E62: Médio | F62: ='03_FONTE_FAP'!F62 -> 51.5565 | G62: ='03_FONTE_FAP'!K62 -> 67.1865 | H62: ='03_FONTE_FAP'!M62 -> 59.3715 | I62: ='01_PARÂMETROS'!$B$9 -> 50 | J62: =IFERROR(IF(H62=0,1,H62/I62),1) -> 1.18743 | K62: =MAX('01_PARÂMETROS'!$B$11,MIN('01_PARÂMETROS'!$B$12,J62)) -> 1.18743 | L62: =(K62-1) -> 0.18743 | M62: =IF(K62<='01_PARÂMETROS'!$B$14,"Preferencial",IF(K62<='01_PARÂMETROS'!$B$15,"Baixo",IF(K62<='01_PARÂMETROS'!$B$16,"Médio",IF(K62<='01_PARÂMETROS'!$B$17,"Alto","Elevado")))) -> Alto | N62: FAP/MPS | O62: Revisar
A63: 0152-1/03 | B63: A | C63: Criação de asininos e muares | D63: AGRICULTURA, PEC | E63: Médio | F63: ='03_FONTE_FAP'!F63 -> 82.829 | G63: ='03_FONTE_FAP'!K63 -> 89.2585 | H63: ='03_FONTE_FAP'!M63 -> 86.04375 | I63: ='01_PARÂMETROS'!$B$9 -> 50 | J63: =IFERROR(IF(H63=0,1,H63/I63),1) -> 1.720875 | K63: =MAX('01_PARÂMETROS'!$B$11,MIN('01_PARÂMETROS'!$B$12,J63)) -> 1.4 | L63: =(K63-1) -> 0.4 | M63: =IF(K63<='01_PARÂMETROS'!$B$14,"Preferencial",IF(K63<='01_PARÂMETROS'!$B$15,"Baixo",IF(K63<='01_PARÂMETROS'!$B$16,"Médio",IF(K63<='01_PARÂMETROS'!$B$17,"Alto","Elevado")))) -> Elevado | N63: FAP/MPS | O63: Revisar
A64: 0153-9/01 | B64: A | C64: Criação de caprinos | D64: AGRICULTURA, PEC | E64: Médio | F64: ='03_FONTE_FAP'!F64 -> 18.627 | G64: ='03_FONTE_FAP'!K64 -> 16.086 | H64: ='03_FONTE_FAP'!M64 -> 17.3565 | I64: ='01_PARÂMETROS'!$B$9 -> 50 | J64: =IFERROR(IF(H64=0,1,H64/I64),1) -> 0.34713 | K64: =MAX('01_PARÂMETROS'!$B$11,MIN('01_PARÂMETROS'!$B$12,J64)) -> 0.75 | L64: =(K64-1) -> -0.25 | M64: =IF(K64<='01_PARÂMETROS'!$B$14,"Preferencial",IF(K64<='01_PARÂMETROS'!$B$15,"Baixo",IF(K64<='01_PARÂMETROS'!$B$16,"Médio",IF(K64<='01_PARÂMETROS'!$B$17,"Alto","Elevado")))) -> Preferencial | N64: FAP/MPS | O64: Revisar
A65: 0153-9/02 | B65: A | C65: Criação de ovinos, inclusive para produção de lã | D65: AGRICULTURA, PEC | E65: Médio | F65: ='03_FONTE_FAP'!F65 -> 60.168 | G65: ='03_FONTE_FAP'!K65 -> 54.839 | H65: ='03_FONTE_FAP'!M65 -> 57.5035 | I65: ='01_PARÂMETROS'!$B$9 -> 50 | J65: =IFERROR(IF(H65=0,1,H65/I65),1) -> 1.15007 | K65: =MAX('01_PARÂMETROS'!$B$11,MIN('01_PARÂMETROS'!$B$12,J65)) -> 1.15007 | L65: =(K65-1) -> 0.15007 | M65: =IF(K65<='01_PARÂMETROS'!$B$14,"Preferencial",IF(K65<='01_PARÂMETROS'!$B$15,"Baixo",IF(K65<='01_PARÂMETROS'!$B$16,"Médio",IF(K65<='01_PARÂMETROS'!$B$17,"Alto","Elevado")))) -> Alto | N65: FAP/MPS | O65: Revisar
A66: 0154-7/00 | B66: A | C66: Criação de suínos | D66: AGRICULTURA, PEC | E66: Médio | F66: ='03_FONTE_FAP'!F66 -> 81.6185 | G66: ='03_FONTE_FAP'!K66 -> 83.1355 | H66: ='03_FONTE_FAP'!M66 -> 82.377 | I66: ='01_PARÂMETROS'!$B$9 -> 50 | J66: =IFERROR(IF(H66=0,1,H66/I66),1) -> 1.64754 | K66: =MAX('01_PARÂMETROS'!$B$11,MIN('01_PARÂMETROS'!$B$12,J66)) -> 1.4 | L66: =(K66-1) -> 0.4 | M66: =IF(K66<='01_PARÂMETROS'!$B$14,"Preferencial",IF(K66<='01_PARÂMETROS'!$B$15,"Baixo",IF(K66<='01_PARÂMETROS'!$B$16,"Médio",IF(K66<='01_PARÂMETROS'!$B$17,"Alto","Elevado")))) -> Elevado | N66: FAP/MPS
A67: 0155-5/01 | B67: A | C67: Criação de frangos para corte | D67: AGRICULTURA, PEC | E67: Médio | F67: ='03_FONTE_FAP'!F67 -> 57.0375 | G67: ='03_FONTE_FAP'!K67 -> 50.859 | H67: ='03_FONTE_FAP'!M67 -> 53.94825 | I67: ='01_PARÂMETROS'!$B$9 -> 50 | J67: =IFERROR(IF(H67=0,1,H67/I67),1) -> 1.078965 | K67: =MAX('01_PARÂMETROS'!$B$11,MIN('01_PARÂMETROS'!$B$12,J67)) -> 1.078965 | L67: =(K67-1) -> 0.078965 | M67: =IF(K67<='01_PARÂMETROS'!$B$14,"Preferencial",IF(K67<='01_PARÂMETROS'!$B$15,"Baixo",IF(K67<='01_PARÂMETROS'!$B$16,"Médio",IF(K67<='01_PARÂMETROS'!$B$17,"Alto","Elevado")))) -> Alto | N67: FAP/MPS | O67: Revisar
A68: 0155-5/02 | B68: A | C68: Produção de pintos de um dia | D68: AGRICULTURA, PEC | E68: Médio | F68: ='03_FONTE_FAP'!F68 -> 70.733 | G68: ='03_FONTE_FAP'!K68 -> 76.0245 | H68: ='03_FONTE_FAP'!M68 -> 73.37875 | I68: ='01_PARÂMETROS'!$B$9 -> 50 | J68: =IFERROR(IF(H68=0,1,H68/I68),1) -> 1.467575 | K68: =MAX('01_PARÂMETROS'!$B$11,MIN('01_PARÂMETROS'!$B$12,J68)) -> 1.4 | L68: =(K68-1) -> 0.4 | M68: =IF(K68<='01_PARÂMETROS'!$B$14,"Preferencial",IF(K68<='01_PARÂMETROS'!$B$15,"Baixo",IF(K68<='01_PARÂMETROS'!$B$16,"Médio",IF(K68<='01_PARÂMETROS'!$B$17,"Alto","Elevado")))) -> Elevado | N68: FAP/MPS | O68: Revisar
A69: 0155-5/03 | B69: A | C69: Criação de outros galináceos, exceto para corte | D69: AGRICULTURA, PEC | E69: Médio | F69: ='03_FONTE_FAP'!F69 -> 84.0035 | G69: ='03_FONTE_FAP'!K69 -> 83.9475 | H69: ='03_FONTE_FAP'!M69 -> 83.9755 | I69: ='01_PARÂMETROS'!$B$9 -> 50 | J69: =IFERROR(IF(H69=0,1,H69/I69),1) -> 1.67951 | K69: =MAX('01_PARÂMETROS'!$B$11,MIN('01_PARÂMETROS'!$B$12,J69)) -> 1.4 | L69: =(K69-1) -> 0.4 | M69: =IF(K69<='01_PARÂMETROS'!$B$14,"Preferencial",IF(K69<='01_PARÂMETROS'!$B$15,"Baixo",IF(K69<='01_PARÂMETROS'!$B$16,"Médio",IF(K69<='01_PARÂMETROS'!$B$17,"Alto","Elevado")))) -> Elevado | N69: FAP/MPS | O69: Revisar
A70: 0155-5/04 | B70: A | C70: Criação de aves, exceto galináceos | D70: AGRICULTURA, PEC | E70: Médio | F70: ='03_FONTE_FAP'!F70 -> 51.0535 | G70: ='03_FONTE_FAP'!K70 -> 18.5035 | H70: ='03_FONTE_FAP'!M70 -> 34.7785 | I70: ='01_PARÂMETROS'!$B$9 -> 50 | J70: =IFERROR(IF(H70=0,1,H70/I70),1) -> 0.69557 | K70: =MAX('01_PARÂMETROS'!$B$11,MIN('01_PARÂMETROS'!$B$12,J70)) -> 0.75 | L70: =(K70-1) -> -0.25 | M70: =IF(K70<='01_PARÂMETROS'!$B$14,"Preferencial",IF(K70<='01_PARÂMETROS'!$B$15,"Baixo",IF(K70<='01_PARÂMETROS'!$B$16,"Médio",IF(K70<='01_PARÂMETROS'!$B$17,"Alto","Elevado")))) -> Preferencial | N70: FAP/MPS | O70: Revisar
A71: 0155-5/05 | B71: A | C71: Produção de ovos | D71: AGRICULTURA, PEC | E71: Médio | F71: ='03_FONTE_FAP'!F71 -> 67.032 | G71: ='03_FONTE_FAP'!K71 -> 65.8755 | H71: ='03_FONTE_FAP'!M71 -> 66.45375 | I71: ='01_PARÂMETROS'!$B$9 -> 50 | J71: =IFERROR(IF(H71=0,1,H71/I71),1) -> 1.329075 | K71: =MAX('01_PARÂMETROS'!$B$11,MIN('01_PARÂMETROS'!$B$12,J71)) -> 1.329075 | L71: =(K71-1) -> 0.329075 | M71: =IF(K71<='01_PARÂMETROS'!$B$14,"Preferencial",IF(K71<='01_PARÂMETROS'!$B$15,"Baixo",IF(K71<='01_PARÂMETROS'!$B$16,"Médio",IF(K71<='01_PARÂMETROS'!$B$17,"Alto","Elevado")))) -> Elevado | N71: FAP/MPS | O71: Revisar
A72: 0159-8/01 | B72: A | C72: Apicultura | D72: AGRICULTURA, PEC | E72: Médio | F72: ='03_FONTE_FAP'!F72 -> 33.736 | G72: ='03_FONTE_FAP'!K72 -> 52.092 | H72: ='03_FONTE_FAP'!M72 -> 42.914 | I72: ='01_PARÂMETROS'!$B$9 -> 50 | J72: =IFERROR(IF(H72=0,1,H72/I72),1) -> 0.85828 | K72: =MAX('01_PARÂMETROS'!$B$11,MIN('01_PARÂMETROS'!$B$12,J72)) -> 0.85828 | L72: =(K72-1) -> -0.14172 | M72: =IF(K72<='01_PARÂMETROS'!$B$14,"Preferencial",IF(K72<='01_PARÂMETROS'!$B$15,"Baixo",IF(K72<='01_PARÂMETROS'!$B$16,"Médio",IF(K72<='01_PARÂMETROS'!$B$17,"Alto","Elevado")))) -> Preferencial | N72: FAP/MPS
A73: 0159-8/02 | B73: A | C73: Criação de animais de estimação | D73: AGRICULTURA, PEC | E73: Médio | F73: ='03_FONTE_FAP'!F73 -> 46.4365 | G73: ='03_FONTE_FAP'!K73 -> 39.7195 | H73: ='03_FONTE_FAP'!M73 -> 43.078 | I73: ='01_PARÂMETROS'!$B$9 -> 50 | J73: =IFERROR(IF(H73=0,1,H73/I73),1) -> 0.86156 | K73: =MAX('01_PARÂMETROS'!$B$11,MIN('01_PARÂMETROS'!$B$12,J73)) -> 0.86156 | L73: =(K73-1) -> -0.13844 | M73: =IF(K73<='01_PARÂMETROS'!$B$14,"Preferencial",IF(K73<='01_PARÂMETROS'!$B$15,"Baixo",IF(K73<='01_PARÂMETROS'!$B$16,"Médio",IF(K73<='01_PARÂMETROS'!$B$17,"Alto","Elevado")))) -> Preferencial | N73: FAP/MPS
A74: 0159-8/03 | B74: A | C74: Criação de escargô | D74: AGRICULTURA, PEC | E74: Médio | F74: — | G74: — | H74: — | I74: ='01_PARÂMETROS'!$B$9 -> 50 | J74: =1 -> 1 | K74: =MAX('01_PARÂMETROS'!$B$11,MIN('01_PARÂMETROS'!$B$12,J74)) -> 1 | L74: =(K74-1) -> 0 | M74: =IF(K74<='01_PARÂMETROS'!$B$14,"Preferencial",IF(K74<='01_PARÂMETROS'!$B$15,"Baixo",IF(K74<='01_PARÂMETROS'!$B$16,"Médio",IF(K74<='01_PARÂMETROS'!$B$17,"Alto","Elevado")))) -> Médio | N74: CNAE-STG
A75: 0159-8/04 | B75: A | C75: Criação de bicho-da-seda | D75: AGRICULTURA, PEC | E75: Médio | F75: — | G75: — | H75: — | I75: ='01_PARÂMETROS'!$B$9 -> 50 | J75: =1 -> 1 | K75: =MAX('01_PARÂMETROS'!$B$11,MIN('01_PARÂMETROS'!$B$12,J75)) -> 1 | L75: =(K75-1) -> 0 | M75: =IF(K75<='01_PARÂMETROS'!$B$14,"Preferencial",IF(K75<='01_PARÂMETROS'!$B$15,"Baixo",IF(K75<='01_PARÂMETROS'!$B$16,"Médio",IF(K75<='01_PARÂMETROS'!$B$17,"Alto","Elevado")))) -> Médio | N75: CNAE-STG
A76: 0159-8/99 | B76: A | C76: Criação de outros animais não especificados anteriormente | D76: AGRICULTURA, PEC | E76: Médio | F76: ='03_FONTE_FAP'!F74 -> 36.608 | G76: ='03_FONTE_FAP'!K74 -> 45.7985 | H76: ='03_FONTE_FAP'!M74 -> 41.20325 | I76: ='01_PARÂMETROS'!$B$9 -> 50 | J76: =IFERROR(IF(H76=0,1,H76/I76),1) -> 0.824065 | K76: =MAX('01_PARÂMETROS'!$B$11,MIN('01_PARÂMETROS'!$B$12,J76)) -> 0.824065 | L76: =(K76-1) -> -0.175935 | M76: =IF(K76<='01_PARÂMETROS'!$B$14,"Preferencial",IF(K76<='01_PARÂMETROS'!$B$15,"Baixo",IF(K76<='01_PARÂMETROS'!$B$16,"Médio",IF(K76<='01_PARÂMETROS'!$B$17,"Alto","Elevado")))) -> Preferencial | N76: FAP/MPS
A77: 0161-0/01 | B77: A | C77: Serviço de pulverização e controle de pragas agrícolas | D77: AGRICULTURA, PEC | E77: Médio | F77: ='03_FONTE_FAP'!F75 -> 45.859 | G77: ='03_FONTE_FAP'!K75 -> 50.4945 | H77: ='03_FONTE_FAP'!M75 -> 48.17675 | I77: ='01_PARÂMETROS'!$B$9 -> 50 | J77: =IFERROR(IF(H77=0,1,H77/I77),1) -> 0.963535 | K77: =MAX('01_PARÂMETROS'!$B$11,MIN('01_PARÂMETROS'!$B$12,J77)) -> 0.963535 | L77: =(K77-1) -> -0.036465 | M77: =IF(K77<='01_PARÂMETROS'!$B$14,"Preferencial",IF(K77<='01_PARÂMETROS'!$B$15,"Baixo",IF(K77<='01_PARÂMETROS'!$B$16,"Médio",IF(K77<='01_PARÂMETROS'!$B$17,"Alto","Elevado")))) -> Médio | N77: FAP/MPS | O77: Revisar
A78: 0161-0/02 | B78: A | C78: Serviço de poda de árvores para lavouras | D78: AGRICULTURA, PEC | E78: Médio | F78: ='03_FONTE_FAP'!F76 -> 81.5735 | G78: ='03_FONTE_FAP'!K76 -> 81.31 | H78: ='03_FONTE_FAP'!M76 -> 81.44175 | I78: ='01_PARÂMETROS'!$B$9 -> 50 | J78: =IFERROR(IF(H78=0,1,H78/I78),1) -> 1.628835 | K78: =MAX('01_PARÂMETROS'!$B$11,MIN('01_PARÂMETROS'!$B$12,J78)) -> 1.4 | L78: =(K78-1) -> 0.4 | M78: =IF(K78<='01_PARÂMETROS'!$B$14,"Preferencial",IF(K78<='01_PARÂMETROS'!$B$15,"Baixo",IF(K78<='01_PARÂMETROS'!$B$16,"Médio",IF(K78<='01_PARÂMETROS'!$B$17,"Alto","Elevado")))) -> Elevado | N78: FAP/MPS | O78: Revisar
A79: 0161-0/03 | B79: A | C79: Serviço de preparação de terreno, cultivo e colheita | D79: AGRICULTURA, PEC | E79: Médio | F79: ='03_FONTE_FAP'!F77 -> 51.233 | G79: ='03_FONTE_FAP'!K77 -> 44.953 | H79: ='03_FONTE_FAP'!M77 -> 48.093 | I79: ='01_PARÂMETROS'!$B$9 -> 50 | J79: =IFERROR(IF(H79=0,1,H79/I79),1) -> 0.96186 | K79: =MAX('01_PARÂMETROS'!$B$11,MIN('01_PARÂMETROS'!$B$12,J79)) -> 0.96186 | L79: =(K79-1) -> -0.03814 | M79: =IF(K79<='01_PARÂMETROS'!$B$14,"Preferencial",IF(K79<='01_PARÂMETROS'!$B$15,"Baixo",IF(K79<='01_PARÂMETROS'!$B$16,"Médio",IF(K79<='01_PARÂMETROS'!$B$17,"Alto","Elevado")))) -> Médio | N79: FAP/MPS | O79: Revisar
A80: 0161-0/99 | B80: A | C80: Atividades de apoio à agricultura não especificadas anteriormente | D80: AGRICULTURA, PEC | E80: Médio | F80: ='03_FONTE_FAP'!F78 -> 46.0045 | G80: ='03_FONTE_FAP'!K78 -> 46.641 | H80: ='03_FONTE_FAP'!M78 -> 46.32275 | I80: ='01_PARÂMETROS'!$B$9 -> 50 | J80: =IFERROR(IF(H80=0,1,H80/I80),1) -> 0.926455 | K80: =MAX('01_PARÂMETROS'!$B$11,MIN('01_PARÂMETROS'!$B$12,J80)) -> 0.926455 | L80: =(K80-1) -> -0.073545 | M80: =IF(K80<='01_PARÂMETROS'!$B$14,"Preferencial",IF(K80<='01_PARÂMETROS'!$B$15,"Baixo",IF(K80<='01_PARÂMETROS'!$B$16,"Médio",IF(K80<='01_PARÂMETROS'!$B$17,"Alto","Elevado")))) -> Baixo | N80: FAP/MPS | O80: Revisar
A81: 0162-8/01 | B81: A | C81: Serviço de inseminação artificial em animais | D81: AGRICULTURA, PEC | E81: Médio | F81: ='03_FONTE_FAP'!F79 -> 56.2885 | G81: ='03_FONTE_FAP'!K79 -> 42.3465 | H81: ='03_FONTE_FAP'!M79 -> 49.3175 | I81: ='01_PARÂMETROS'!$B$9 -> 50 | J81: =IFERROR(IF(H81=0,1,H81/I81),1) -> 0.98635 | K81: =MAX('01_PARÂMETROS'!$B$11,MIN('01_PARÂMETROS'!$B$12,J81)) -> 0.98635 | L81: =(K81-1) -> -0.01365 | M81: =IF(K81<='01_PARÂMETROS'!$B$14,"Preferencial",IF(K81<='01_PARÂMETROS'!$B$15,"Baixo",IF(K81<='01_PARÂMETROS'!$B$16,"Médio",IF(K81<='01_PARÂMETROS'!$B$17,"Alto","Elevado")))) -> Médio | N81: FAP/MPS
A82: 0162-8/02 | B82: A | C82: Serviço de tosquiamento de ovinos | D82: AGRICULTURA, PEC | E82: Médio | F82: — | G82: — | H82: — | I82: ='01_PARÂMETROS'!$B$9 -> 50 | J82: =1 -> 1 | K82: =MAX('01_PARÂMETROS'!$B$11,MIN('01_PARÂMETROS'!$B$12,J82)) -> 1 | L82: =(K82-1) -> 0 | M82: =IF(K82<='01_PARÂMETROS'!$B$14,"Preferencial",IF(K82<='01_PARÂMETROS'!$B$15,"Baixo",IF(K82<='01_PARÂMETROS'!$B$16,"Médio",IF(K82<='01_PARÂMETROS'!$B$17,"Alto","Elevado")))) -> Médio | N82: CNAE-STG
A83: 0162-8/03 | B83: A | C83: Serviço de manejo de animais | D83: AGRICULTURA, PEC | E83: Médio | F83: ='03_FONTE_FAP'!F81 -> 58.234 | G83: ='03_FONTE_FAP'!K81 -> 59.8695 | H83: ='03_FONTE_FAP'!M81 -> 59.05175 | I83: ='01_PARÂMETROS'!$B$9 -> 50 | J83: =IFERROR(IF(H83=0,1,H83/I83),1) -> 1.181035 | K83: =MAX('01_PARÂMETROS'!$B$11,MIN('01_PARÂMETROS'!$B$12,J83)) -> 1.181035 | L83: =(K83-1) -> 0.181035 | M83: =IF(K83<='01_PARÂMETROS'!$B$14,"Preferencial",IF(K83<='01_PARÂMETROS'!$B$15,"Baixo",IF(K83<='01_PARÂMETROS'!$B$16,"Médio",IF(K83<='01_PARÂMETROS'!$B$17,"Alto","Elevado")))) -> Alto | N83: FAP/MPS
A84: 0162-8/99 | B84: A | C84: Atividades de apoio à pecuária não especificadas anteriormente | D84: AGRICULTURA, PEC | E84: Médio | F84: ='03_FONTE_FAP'!F82 -> 71.3275 | G84: ='03_FONTE_FAP'!K82 -> 64.1345 | H84: ='03_FONTE_FAP'!M82 -> 67.731 | I84: ='01_PARÂMETROS'!$B$9 -> 50 | J84: =IFERROR(IF(H84=0,1,H84/I84),1) -> 1.35462 | K84: =MAX('01_PARÂMETROS'!$B$11,MIN('01_PARÂMETROS'!$B$12,J84)) -> 1.35462 | L84: =(K84-1) -> 0.35462 | M84: =IF(K84<='01_PARÂMETROS'!$B$14,"Preferencial",IF(K84<='01_PARÂMETROS'!$B$15,"Baixo",IF(K84<='01_PARÂMETROS'!$B$16,"Médio",IF(K84<='01_PARÂMETROS'!$B$17,"Alto","Elevado")))) -> Elevado | N84: FAP/MPS
A85: 0163-6/00 | B85: A | C85: Atividades de pós-colheita | D85: AGRICULTURA, PEC | E85: Médio | F85: ='03_FONTE_FAP'!F83 -> 71.946 | G85: ='03_FONTE_FAP'!K83 -> 63.4465 | H85: ='03_FONTE_FAP'!M83 -> 67.69625 | I85: ='01_PARÂMETROS'!$B$9 -> 50 | J85: =IFERROR(IF(H85=0,1,H85/I85),1) -> 1.353925 | K85: =MAX('01_PARÂMETROS'!$B$11,MIN('01_PARÂMETROS'!$B$12,J85)) -> 1.353925 | L85: =(K85-1) -> 0.353925 | M85: =IF(K85<='01_PARÂMETROS'!$B$14,"Preferencial",IF(K85<='01_PARÂMETROS'!$B$15,"Baixo",IF(K85<='01_PARÂMETROS'!$B$16,"Médio",IF(K85<='01_PARÂMETROS'!$B$17,"Alto","Elevado")))) -> Elevado | N85: FAP/MPS
A86: 0170-9/00 | B86: A | C86: Caça e serviços relacionados | D86: AGRICULTURA, PEC | E86: Médio | F86: — | G86: — | H86: — | I86: ='01_PARÂMETROS'!$B$9 -> 50 | J86: =1 -> 1 | K86: =MAX('01_PARÂMETROS'!$B$11,MIN('01_PARÂMETROS'!$B$12,J86)) -> 1 | L86: =(K86-1) -> 0 | M86: =IF(K86<='01_PARÂMETROS'!$B$14,"Preferencial",IF(K86<='01_PARÂMETROS'!$B$15,"Baixo",IF(K86<='01_PARÂMETROS'!$B$16,"Médio",IF(K86<='01_PARÂMETROS'!$B$17,"Alto","Elevado")))) -> Médio | N86: CNAE-STG
A87: 0210-1/01 | B87: A | C87: Cultivo de eucalipto | D87: PRODUÇÃO FLOREST | E87: Alto | F87: ='03_FONTE_FAP'!F85 -> 56.844 | G87: ='03_FONTE_FAP'!K85 -> 62.6435 | H87: ='03_FONTE_FAP'!M85 -> 59.74375 | I87: ='01_PARÂMETROS'!$B$9 -> 50 | J87: =IFERROR(IF(H87=0,1.15,H87/I87),1.15) -> 1.194875 | K87: =MAX('01_PARÂMETROS'!$B$11,MIN('01_PARÂMETROS'!$B$12,J87)) -> 1.194875 | L87: =(K87-1) -> 0.194875 | M87: =IF(K87<='01_PARÂMETROS'!$B$14,"Preferencial",IF(K87<='01_PARÂMETROS'!$B$15,"Baixo",IF(K87<='01_PARÂMETROS'!$B$16,"Médio",IF(K87<='01_PARÂMETROS'!$B$17,"Alto","Elevado")))) -> Alto | N87: FAP/MPS | O87: Revisar
A88: 0210-1/02 | B88: A | C88: Cultivo de acácia-negra | D88: PRODUÇÃO FLOREST | E88: Alto | F88: ='03_FONTE_FAP'!F86 -> 35 | G88: ='03_FONTE_FAP'!K86 -> 34.972 | H88: ='03_FONTE_FAP'!M86 -> 34.986 | I88: ='01_PARÂMETROS'!$B$9 -> 50 | J88: =IFERROR(IF(H88=0,1.15,H88/I88),1.15) -> 0.69972 | K88: =MAX('01_PARÂMETROS'!$B$11,MIN('01_PARÂMETROS'!$B$12,J88)) -> 0.75 | L88: =(K88-1) -> -0.25 | M88: =IF(K88<='01_PARÂMETROS'!$B$14,"Preferencial",IF(K88<='01_PARÂMETROS'!$B$15,"Baixo",IF(K88<='01_PARÂMETROS'!$B$16,"Médio",IF(K88<='01_PARÂMETROS'!$B$17,"Alto","Elevado")))) -> Preferencial | N88: FAP/MPS | O88: Revisar
A89: 0210-1/03 | B89: A | C89: Cultivo de pinus | D89: PRODUÇÃO FLOREST | E89: Alto | F89: ='03_FONTE_FAP'!F87 -> 92.246 | G89: ='03_FONTE_FAP'!K87 -> 92.072 | H89: ='03_FONTE_FAP'!M87 -> 92.159 | I89: ='01_PARÂMETROS'!$B$9 -> 50 | J89: =IFERROR(IF(H89=0,1.15,H89/I89),1.15) -> 1.84318 | K89: =MAX('01_PARÂMETROS'!$B$11,MIN('01_PARÂMETROS'!$B$12,J89)) -> 1.4 | L89: =(K89-1) -> 0.4 | M89: =IF(K89<='01_PARÂMETROS'!$B$14,"Preferencial",IF(K89<='01_PARÂMETROS'!$B$15,"Baixo",IF(K89<='01_PARÂMETROS'!$B$16,"Médio",IF(K89<='01_PARÂMETROS'!$B$17,"Alto","Elevado")))) -> Elevado | N89: FAP/MPS | O89: Revisar
A90: 0210-1/04 | B90: A | C90: Cultivo de teca | D90: PRODUÇÃO FLOREST | E90: Alto | F90: ='03_FONTE_FAP'!F88 -> 84.993 | G90: ='03_FONTE_FAP'!K88 -> 59.643 | H90: ='03_FONTE_FAP'!M88 -> 72.318 | I90: ='01_PARÂMETROS'!$B$9 -> 50 | J90: =IFERROR(IF(H90=0,1.15,H90/I90),1.15) -> 1.44636 | K90: =MAX('01_PARÂMETROS'!$B$11,MIN('01_PARÂMETROS'!$B$12,J90)) -> 1.4 | L90: =(K90-1) -> 0.4 | M90: =IF(K90<='01_PARÂMETROS'!$B$14,"Preferencial",IF(K90<='01_PARÂMETROS'!$B$15,"Baixo",IF(K90<='01_PARÂMETROS'!$B$16,"Médio",IF(K90<='01_PARÂMETROS'!$B$17,"Alto","Elevado")))) -> Elevado | N90: FAP/MPS | O90: Revisar
A91: 0210-1/05 | B91: A | C91: Cultivo de espécies madeireiras, exceto eucalipto, acácia-negra, pinus e teca | D91: PRODUÇÃO FLOREST | E91: Alto | F91: ='03_FONTE_FAP'!F89 -> 42.465 | G91: ='03_FONTE_FAP'!K89 -> 40.5225 | H91: ='03_FONTE_FAP'!M89 -> 41.49375 | I91: ='01_PARÂMETROS'!$B$9 -> 50 | J91: =IFERROR(IF(H91=0,1.15,H91/I91),1.15) -> 0.829875 | K91: =MAX('01_PARÂMETROS'!$B$11,MIN('01_PARÂMETROS'!$B$12,J91)) -> 0.829875 | L91: =(K91-1) -> -0.170125 | M91: =IF(K91<='01_PARÂMETROS'!$B$14,"Preferencial",IF(K91<='01_PARÂMETROS'!$B$15,"Baixo",IF(K91<='01_PARÂMETROS'!$B$16,"Médio",IF(K91<='01_PARÂMETROS'!$B$17,"Alto","Elevado")))) -> Preferencial | N91: FAP/MPS | O91: Revisar
A92: 0210-1/06 | B92: A | C92: Cultivo de mudas em viveiros florestais | D92: PRODUÇÃO FLOREST | E92: Alto | F92: ='03_FONTE_FAP'!F90 -> 64.7675 | G92: ='03_FONTE_FAP'!K90 -> 53.648 | H92: ='03_FONTE_FAP'!M90 -> 59.20775 | I92: ='01_PARÂMETROS'!$B$9 -> 50 | J92: =IFERROR(IF(H92=0,1.15,H92/I92),1.15) -> 1.184155 | K92: =MAX('01_PARÂMETROS'!$B$11,MIN('01_PARÂMETROS'!$B$12,J92)) -> 1.184155 | L92: =(K92-1) -> 0.184155 | M92: =IF(K92<='01_PARÂMETROS'!$B$14,"Preferencial",IF(K92<='01_PARÂMETROS'!$B$15,"Baixo",IF(K92<='01_PARÂMETROS'!$B$16,"Médio",IF(K92<='01_PARÂMETROS'!$B$17,"Alto","Elevado")))) -> Alto | N92: FAP/MPS | O92: Revisar
A93: 0210-1/07 | B93: A | C93: Extração de madeira em florestas plantadas | D93: PRODUÇÃO FLOREST | E93: Alto | F93: ='03_FONTE_FAP'!F91 -> 91.301 | G93: ='03_FONTE_FAP'!K91 -> 89.2285 | H93: ='03_FONTE_FAP'!M91 -> 90.26475 | I93: ='01_PARÂMETROS'!$B$9 -> 50 | J93: =IFERROR(IF(H93=0,1.15,H93/I93),1.15) -> 1.805295 | K93: =MAX('01_PARÂMETROS'!$B$11,MIN('01_PARÂMETROS'!$B$12,J93)) -> 1.4 | L93: =(K93-1) -> 0.4 | M93: =IF(K93<='01_PARÂMETROS'!$B$14,"Preferencial",IF(K93<='01_PARÂMETROS'!$B$15,"Baixo",IF(K93<='01_PARÂMETROS'!$B$16,"Médio",IF(K93<='01_PARÂMETROS'!$B$17,"Alto","Elevado")))) -> Elevado | N93: FAP/MPS | O93: Revisar
A94: 0210-1/08 | B94: A | C94: Produção de carvão vegetal - florestas plantadas | D94: PRODUÇÃO FLOREST | E94: Alto | F94: ='03_FONTE_FAP'!F92 -> 80.485 | G94: ='03_FONTE_FAP'!K92 -> 59.306 | H94: ='03_FONTE_FAP'!M92 -> 69.8955 | I94: ='01_PARÂMETROS'!$B$9 -> 50 | J94: =IFERROR(IF(H94=0,1.15,H94/I94),1.15) -> 1.39791 | K94: =MAX('01_PARÂMETROS'!$B$11,MIN('01_PARÂMETROS'!$B$12,J94)) -> 1.39791 | L94: =(K94-1) -> 0.39791 | M94: =IF(K94<='01_PARÂMETROS'!$B$14,"Preferencial",IF(K94<='01_PARÂMETROS'!$B$15,"Baixo",IF(K94<='01_PARÂMETROS'!$B$16,"Médio",IF(K94<='01_PARÂMETROS'!$B$17,"Alto","Elevado")))) -> Elevado | N94: FAP/MPS | O94: Revisar
A95: 0210-1/09 | B95: A | C95: Produção de casca de acácia-negra - florestas plantadas | D95: PRODUÇÃO FLOREST | E95: Alto | F95: ='03_FONTE_FAP'!F93 -> 23.0545 | G95: ='03_FONTE_FAP'!K93 -> 14.917 | H95: ='03_FONTE_FAP'!M93 -> 18.98575 | I95: ='01_PARÂMETROS'!$B$9 -> 50 | J95: =IFERROR(IF(H95=0,1.15,H95/I95),1.15) -> 0.379715 | K95: =MAX('01_PARÂMETROS'!$B$11,MIN('01_PARÂMETROS'!$B$12,J95)) -> 0.75 | L95: =(K95-1) -> -0.25 | M95: =IF(K95<='01_PARÂMETROS'!$B$14,"Preferencial",IF(K95<='01_PARÂMETROS'!$B$15,"Baixo",IF(K95<='01_PARÂMETROS'!$B$16,"Médio",IF(K95<='01_PARÂMETROS'!$B$17,"Alto","Elevado")))) -> Preferencial | N95: FAP/MPS | O95: Revisar
A96: 0210-1/99 | B96: A | C96: Produção de produtos não madeireiros não especificados anteriormente em florestas plantadas | D96: PRODUÇÃO FLOREST | E96: Alto | F96: ='03_FONTE_FAP'!F94 -> 42.4165 | G96: ='03_FONTE_FAP'!K94 -> 39.901 | H96: ='03_FONTE_FAP'!M94 -> 41.15875 | I96: ='01_PARÂMETROS'!$B$9 -> 50 | J96: =IFERROR(IF(H96=0,1.15,H96/I96),1.15) -> 0.823175 | K96: =MAX('01_PARÂMETROS'!$B$11,MIN('01_PARÂMETROS'!$B$12,J96)) -> 0.823175 | L96: =(K96-1) -> -0.176825 | M96: =IF(K96<='01_PARÂMETROS'!$B$14,"Preferencial",IF(K96<='01_PARÂMETROS'!$B$15,"Baixo",IF(K96<='01_PARÂMETROS'!$B$16,"Médio",IF(K96<='01_PARÂMETROS'!$B$17,"Alto","Elevado")))) -> Preferencial | N96: FAP/MPS | O96: Revisar
A97: 0220-9/01 | B97: A | C97: Extração de madeira em florestas nativas | D97: PRODUÇÃO FLOREST | E97: Alto | F97: ='03_FONTE_FAP'!F95 -> 86.0045 | G97: ='03_FONTE_FAP'!K95 -> 88.201 | H97: ='03_FONTE_FAP'!M95 -> 87.10275 | I97: ='01_PARÂMETROS'!$B$9 -> 50 | J97: =IFERROR(IF(H97=0,1.15,H97/I97),1.15) -> 1.742055 | K97: =MAX('01_PARÂMETROS'!$B$11,MIN('01_PARÂMETROS'!$B$12,J97)) -> 1.4 | L97: =(K97-1) -> 0.4 | M97: =IF(K97<='01_PARÂMETROS'!$B$14,"Preferencial",IF(K97<='01_PARÂMETROS'!$B$15,"Baixo",IF(K97<='01_PARÂMETROS'!$B$16,"Médio",IF(K97<='01_PARÂMETROS'!$B$17,"Alto","Elevado")))) -> Elevado | N97: FAP/MPS | O97: Revisar
A98: 0220-9/02 | B98: A | C98: Produção de carvão vegetal - florestas nativas | D98: PRODUÇÃO FLOREST | E98: Alto | F98: ='03_FONTE_FAP'!F96 -> 57.97 | G98: ='03_FONTE_FAP'!K96 -> 71.2455 | H98: ='03_FONTE_FAP'!M96 -> 64.60775 | I98: ='01_PARÂMETROS'!$B$9 -> 50 | J98: =IFERROR(IF(H98=0,1.15,H98/I98),1.15) -> 1.292155 | K98: =MAX('01_PARÂMETROS'!$B$11,MIN('01_PARÂMETROS'!$B$12,J98)) -> 1.292155 | L98: =(K98-1) -> 0.292155 | M98: =IF(K98<='01_PARÂMETROS'!$B$14,"Preferencial",IF(K98<='01_PARÂMETROS'!$B$15,"Baixo",IF(K98<='01_PARÂMETROS'!$B$16,"Médio",IF(K98<='01_PARÂMETROS'!$B$17,"Alto","Elevado")))) -> Elevado | N98: FAP/MPS | O98: Revisar
... A103: 0220-9/99 | B103: A | C103: Coleta de produtos não madeireiros não especificados anteriormente em florestas nativas | D103: PRODUÇÃO FLOREST | E103: Alto | F103: ='03_FONTE_FAP'!F101 -> 45.6845 | G103: ='03_FONTE_FAP'!K101 -> 49.102 | H103: ='03_FONTE_FAP'!M101 -> 47.39325 | I103: ='01_PARÂMETROS'!$B$9 -> 50 | J103: =IFERROR(IF(H103=0,1.15,H103/I103),1.15) -> 0.947865 | K103: =MAX('01_PARÂMETROS'!$B$11,MIN('01_PARÂMETROS'!$B$12,J103)) -> 0.947865 | L103: =(K103-1) -> -0.052135 | M103: =IF(K103<='01_PARÂMETROS'!$B$14,"Preferencial",IF(K103<='01_PARÂMETROS'!$B$15,"Baixo",IF(K103<='01_PARÂMETROS'!$B$16,"Médio",IF(K103<='01_PARÂMETROS'!$B$17,"Alto","Elevado")))) -> Baixo | N103: FAP/MPS | O103: Revisar
A104: 0230-6/00 | B104: A | C104: Atividades de apoio à produção florestal | D104: PRODUÇÃO FLOREST | E104: Alto | F104: ='03_FONTE_FAP'!F102 -> 60.7635 | G104: ='03_FONTE_FAP'!K102 -> 61.7285 | H104: ='03_FONTE_FAP'!M102 -> 61.246 | I104: ='01_PARÂMETROS'!$B$9 -> 50 | J104: =IFERROR(IF(H104=0,1.15,H104/I104),1.15) -> 1.22492 | K104: =MAX('01_PARÂMETROS'!$B$11,MIN('01_PARÂMETROS'!$B$12,J104)) -> 1.22492 | L104: =(K104-1) -> 0.22492 | M104: =IF(K104<='01_PARÂMETROS'!$B$14,"Preferencial",IF(K104<='01_PARÂMETROS'!$B$15,"Baixo",IF(K104<='01_PARÂMETROS'!$B$16,"Médio",IF(K104<='01_PARÂMETROS'!$B$17,"Alto","Elevado")))) -> Alto | N104: FAP/MPS
...

Sheet 05_TESTES_ADERÊNCIA
A1: TESTES DE ADERÊNCIA — VALIDA A METODOLOGIA DE RELATIVIDADES
A2: Todos os resultados são calculados por fórmula — referenciando 01_PARÂMETROS
A3: TESTE 1 — CONSISTÊNCIA INTERTEMPORAL (Correlação Spearman)
A4: Objetivo | B4: Verificar se os ICs de 2023 e 2024 são consistentes entre si
A5: H0 | B5: Correlação de Spearman ρ ≥ 0,70 (alta consistência)
A6: N subclasses com IC válido em ambos os anos | B6: 134
A7: ρ Spearman calculado (Python) | B7: 0.8414 | D7: ≥ 0,70 = aprovado
A8: Conclusão | B8: APROVADO — alta consistência intertemporal dos dados FAP
A9: Interpretação | B9: Rankings de risco por CNAE estáveis ano a ano. Valida uso da média 2023+2024 como estimativa robusta.
A11: TESTE 2 — HIPÓTESE SOBRE IC_ref = 50 (teste z bicaudal)
A12: H0 | B12: IC_ref = 50 é compatível com os dados (α = 5%)
A13: H1 | B13: IC_ref ≠ média observada (IC_ref não é a média dos dados)
A14: N observações (ICs válidos) | B14: ='01_PARÂMETROS'!B20 -> 280 | D14: Referência parâmetro E1
A15: IC Média observada | B15: ='01_PARÂMETROS'!B21 -> 54.25 | D15: Referência parâmetro E2
A16: IC Desvio Padrão | B16: ='01_PARÂMETROS'!B22 -> 24.2 | D16: Referência parâmetro E3
A17: Estatística z | B17: ='01_PARÂMETROS'!B29 -> 37.51141 | D17: Referência parâmetro F1 — calculada em 01_PARÂMETROS
A18: |z| > 1,96 (α=5%)? | B18: ='01_PARÂMETROS'!B30 -> NÃO — não rejeitar H0
A19: Interpretação | B19: O teste REJEITA H0 — IC_ref=50 não é a média dos dados FAP disponíveis (~54). ISSO É ESPERADO. IC_ref=50 é valor de referência teórico (mediana da escala), não estimativa da média. O viés de seleção dos PDFs (concentrados em setores de alto risco) justifica a escolha de IC_ref=50 em vez da média empírica.
A21: TESTE 3 — TRUNCAMENTO PELOS LIMITADORES
A22: Objetivo | B22: Avaliar se os limites 0,75 e 1,40 truncam excessivamente as relatividades
A23: N ICs calculados (total ambos os anos) | B23: 280
A24: N atingindo limite inferior 0.75 | B24: 76 | C24: 27.1% | D24: IC < 37,5
A25: N atingindo limite superior 1.4 | B25: 81 | C25: 28.9% | D25: IC > 70,0
A26: % truncado total | B26: 56.1%
A27: Conclusão | B27: ATENÇÃO — truncamento elevado (~40%). Indica alta dispersão dos dados FAP. Avaliar alargar limites (0,70–1,50) na próxima revisão.
A29: TESTE 4 — SENSIBILIDADE DO IC_ref (variar de 40 a 65)
A30: Objetivo | B30: Verificar se a distribuição das classes é sensível ao IC_ref adotado
A31: IC_ref testado | B31: % Preferencial | C31: % Elevado | D31: % Médio
A32: 40 | B32: 22% | C32: 57% | D32: 7%
A33: 45 | B33: 30% | C33: 50% | D33: 7%
A34: 50 | B34: 35% | C34: 41% | D34: 6%
A35: 55 | B35: 42% | C35: 30% | D35: 9%
A36: 60 | B36: 46% | C36: 24% | D36: 15%
A37: 65 | B37: 51% | C37: 19% | D37: 11%
A39: CONCLUSÃO GERAL
A40: Resumo | B40: (1) Consistência intertemporal FAP: APROVADA. (2) IC_ref=50 não é a média empírica — esperado e justificado. (3) Truncamento ~40% pelos limitadores: revisar limites na próxima atualização anual. (4) Sensibilidade ao IC_ref: distribuição pouco sensível entre 45-55 — metodologia robusta.

Sheet 06_AUDITORIA_CONSISTÊNCIA
A1: AUDITORIA DE CONSISTÊNCIA INTRA-DIVISÃO — RELATIVIDADES OPOSTAS
A2: Divisões CNAE com subclasses de classes opostas (desagravo ↔ agravo). Total: 21 divisões. Revise os sinalizados como 'Anomalia'.
A3: Divisão | B3: CNAE | C3: Descrição Subclasse | D3: IC Médio | E3: Relat. Final | F3: Classe | G3: Ajuste % | H3: Justificativa | I3: Classificação
A4: DIVISÃO 01.11 — AGRICULTURA, PECUÁRIA E SERVIÇOS RELACIONADOS
A5: 01.11 | B5: 01.11-3/03 | C5: Cultivo de trigo | D5: 22.99 | E5: 0.75 | F5: Preferencial | G5: -0.25 | H5: Subclasses com perfis distintos dentro da mesma divisão | I5: Aceitável
A6: 01.11 | B6: 01.11-3/02 | C6: Cultivo de milho | D6: 38.42 | E6: 0.7684 | F6: Preferencial | G6: -0.2316 | H6: Subclasses com perfis distintos dentro da mesma divisão | I6: Aceitável
A7: 01.11 | B7: 01.11-3/01 | C7: Cultivo de arroz | D7: 56.13 | E7: 1.1226 | F7: Alto | G7: 0.1226 | H7: Subclasses com perfis distintos dentro da mesma divisão | I7: Aceitável
A8: 01.11 | B8: 01.11-3/99 | C8: Cultivo de outros cereais não especificados anteriormente | D8: 58.21 | E8: 1.1642 | F8: Alto | G8: 0.1642 | H8: Subclasses com perfis distintos dentro da mesma divisão | I8: Aceitável
A10: DIVISÃO 01.12 — AGRICULTURA, PECUÁRIA E SERVIÇOS RELACIONADOS
A11: 01.12 | B11: 01.12-1/02 | C11: Cultivo de juta | D11: 36.83 | E11: 0.75 | F11: Preferencial | G11: -0.25 | H11: Subclasses com perfis distintos dentro da mesma divisão | I11: Aceitável
A12: 01.12 | B12: 01.12-1/01 | C12: Cultivo de algodão herbáceo | D12: 54.89 | E12: 1.0978 | F12: Alto | G12: 0.0978 | H12: Subclasses com perfis distintos dentro da mesma divisão | I12: Aceitável
A14: DIVISÃO 01.19 — AGRICULTURA, PECUÁRIA E SERVIÇOS RELACIONADOS
A15: 01.19 | B15: 01.19-9/02 | C15: Cultivo de alho | D15: 19.55 | E15: 0.75 | F15: Preferencial | G15: -0.25 | H15: Subclasses com perfis distintos dentro da mesma divisão | I15: Aceitável
A16: 01.19 | B16: 01.19-9/04 | C16: Cultivo de cebola | D16: 19.94 | E16: 0.75 | F16: Preferencial | G16: -0.25 | H16: Subclasses com perfis distintos dentro da mesma divisão | I16: Aceitável
A17: 01.19 | B17: 01.19-9/06 | C17: Cultivo de mandioca | D17: 12.98 | E17: 0.75 | F17: Preferencial | G17: -0.25 | H17: Subclasses com perfis distintos dentro da mesma divisão | I17: Aceitável
A18: 01.19 | B18: 01.19-9/09 | C18: Cultivo de tomate rasteiro | D18: 11.72 | E18: 0.75 | F18: Preferencial | G18: -0.25 | H18: Subclasses com perfis distintos dentro da mesma divisão | I18: Aceitável
A19: 01.19 | B19: 01.19-9/05 | C19: Cultivo de feijão | D19: 46.22 | E19: 0.9244 | F19: Baixo | G19: -0.0756 | H19: Subclasses com perfis distintos dentro da mesma divisão | I19: Aceitável
A20: 01.19 | B20: 01.19-9/07 | C20: Cultivo de melão | D20: 50.88 | E20: 1.0176 | F20: Médio | G20: 0.0176 | H20: Subclasses com perfis distintos dentro da mesma divisão | I20: Aceitável
A21: 01.19 | B21: 01.19-9/03 | C21: Cultivo de batata-inglesa | D21: 57.81 | E21: 1.1562 | F21: Alto | G21: 0.1562 | H21: Subclasses com perfis distintos dentro da mesma divisão | I21: Aceitável
A22: 01.19 | B22: 01.19-9/99 | C22: Cultivo de outras plantas de lavoura temporária não especificadas anteriormente | D22: 64.35 | E22: 1.287 | F22: Elevado | G22: 0.287 | H22: Subclasses com perfis distintos dentro da mesma divisão | I22: Aceitável
A24: DIVISÃO 01.33 — AGRICULTURA, PECUÁRIA E SERVIÇOS RELACIONADOS
A25: 01.33 | B25: 01.33-4/01 | C25: Cultivo de açaí | D25: 36.45 | E25: 0.75 | F25: Preferencial | G25: -0.25 | H25: Extremo inferior vs extremo superior na mesma divisão — verificar contexto | I25: Revisar
A26: 01.33 | B26: 01.33-4/10 | C26: Cultivo de manga | D26: 38.26 | E26: 0.7652 | F26: Preferencial | G26: -0.2348 | H26: Subclasses com perfis distintos dentro da mesma divisão | I26: Aceitável
A27: 01.33 | B27: 01.33-4/04 | C27: Cultivo de cítricos, exceto laranja | D27: 38.7 | E27: 0.774 | F27: Preferencial | G27: -0.226 | H27: Subclasses com perfis distintos dentro da mesma divisão | I27: Aceitável
A28: 01.33 | B28: 01.33-4/09 | C28: Cultivo de maracujá | D28: 38.84 | E28: 0.7768 | F28: Preferencial | G28: -0.2232 | H28: Subclasses com perfis distintos dentro da mesma divisão | I28: Aceitável
A29: 01.33 | B29: 01.33-4/99 | C29: Cultivo de frutas de lavoura permanente não especificadas anteriormente | D29: 47.3 | E29: 0.946 | F29: Baixo | G29: -0.054 | H29: Subclasses com perfis distintos dentro da mesma divisão | I29: Aceitável
A30: 01.33 | B30: 01.33-4/08 | C30: Cultivo de mamão | D30: 56.39 | E30: 1.1278 | F30: Alto | G30: 0.1278 | H30: Subclasses com perfis distintos dentro da mesma divisão | I30: Aceitável
A31: 01.33 | B31: 01.33-4/02 | C31: Cultivo de banana | D31: 62.91 | E31: 1.2582 | F31: Elevado | G31: 0.2582 | H31: Subclasses com perfis distintos dentro da mesma divisão | I31: Aceitável
A32: 01.33 | B32: 01.33-4/05 | C32: Cultivo de coco-da-baía | D32: 65.61 | E32: 1.3122 | F32: Elevado | G32: 0.3122 | H32: Subclasses com perfis distintos dentro da mesma divisão | I32: Aceitável
A33: 01.33 | B33: 01.33-4/07 | C33: Cultivo de maçã | D33: 67.3 | E33: 1.346 | F33: Elevado | G33: 0.346 | H33: Subclasses com perfis distintos dentro da mesma divisão | I33: Aceitável
A34: 01.33 | B34: 01.33-4/03 | C34: Cultivo de caju | D34: 87.2 | E34: 1.4 | F34: Elevado | G34: 0.4 | H34: Subclasses com perfis distintos dentro da mesma divisão | I34: Aceitável
A36: DIVISÃO 01.39 — AGRICULTURA, PECUÁRIA E SERVIÇOS RELACIONADOS
A37: 01.39 | B37: 01.39-3/04 | C37: Cultivo de plantas para condimento, exceto pimenta-do-reino | D37: 28.54 | E37: 0.75 | F37: Preferencial | G37: -0.25 | H37: Extremo inferior vs extremo superior na mesma divisão — verificar contexto | I37: Revisar
A38: 01.39 | B38: 01.39-3/06 | C38: Cultivo de seringueira | D38: 15.46 | E38: 0.75 | F38: Preferencial | G38: -0.25 | H38: Extremo inferior vs extremo superior na mesma divisão — verificar contexto | I38: Revisar
A39: 01.39 | B39: 01.39-3/02 | C39: Cultivo de erva-mate | D39: 44.55 | E39: 0.891 | F39: Baixo | G39: -0.109 | H39: Subclasses com perfis distintos dentro da mesma divisão | I39: Aceitável
A40: 01.39 | B40: 01.39-3/99 | C40: Cultivo de outras plantas de lavoura permanente não especificadas anteriormente | D40: 55.61 | E40: 1.1122 | F40: Alto | G40: 0.1122 | H40: Subclasses com perfis distintos dentro da mesma divisão | I40: Aceitável
A41: 01.39 | B41: 01.39-3/05 | C41: Cultivo de dendê | D41: 69.86 | E41: 1.3972 | F41: Elevado | G41: 0.3972 | H41: Subclasses com perfis distintos dentro da mesma divisão | I41: Aceitável
A42: 01.39 | B42: 01.39-3/03 | C42: Cultivo de pimenta-do-reino | D42: 76.65 | E42: 1.4 | F42: Elevado | G42: 0.4 | H42: Subclasses com perfis distintos dentro da mesma divisão | I42: Aceitável
A44: DIVISÃO 01.41 — AGRICULTURA, PECUÁRIA E SERVIÇOS RELACIONADOS
A45: 01.41 | B45: 01.41-5/01 | C45: Produção de sementes certificadas, exceto de forrageiras para pasto | D45: 34.28 | E45: 0.75 | F45: Preferencial | G45: -0.25 | H45: Extremo inferior vs extremo superior na mesma divisão — verificar contexto | I45: Revisar
A46: 01.41 | B46: 01.41-5/02 | C46: Produção de sementes certificadas de forrageiras para formação de pasto | D46: 72.02 | E46: 1.4 | F46: Elevado | G46: 0.4 | H46: Subclasses com perfis distintos dentro da mesma divisão | I46: Aceitável
A48: DIVISÃO 01.52 — AGRICULTURA, PECUÁRIA E SERVIÇOS RELACIONADOS
A49: 01.52 | B49: 01.52-1/01 | C49: Criação de bufalinos | D49: 34.34 | E49: 0.75 | F49: Preferencial | G49: -0.25 | H49: Extremo inferior vs extremo superior na mesma divisão — verificar contexto | I49: Revisar
A50: 01.52 | B50: 01.52-1/02 | C50: Criação de equinos | D50: 59.38 | E50: 1.1876 | F50: Alto | G50: 0.1876 | H50: Subclasses com perfis distintos dentro da mesma divisão | I50: Aceitável
A51: 01.52 | B51: 01.52-1/03 | C51: Criação de asininos e muares | D51: 86.05 | E51: 1.4 | F51: Elevado | G51: 0.4 | H51: Subclasses com perfis distintos dentro da mesma divisão | I51: Aceitável
A53: DIVISÃO 01.53 — AGRICULTURA, PECUÁRIA E SERVIÇOS RELACIONADOS
A54: 01.53 | B54: 01.53-9/01 | C54: Criação de caprinos | D54: 17.36 | E54: 0.75 | F54: Preferencial | G54: -0.25 | H54: Subclasses com perfis distintos dentro da mesma divisão | I54: Aceitável
A55: 01.53 | B55: 01.53-9/02 | C55: Criação de ovinos, inclusive para produção de lã | D55: 57.51 | E55: 1.1502 | F55: Alto | G55: 0.1502 | H55: Subclasses com perfis distintos dentro da mesma divisão | I55: Aceitável
A57: DIVISÃO 01.55 — AGRICULTURA, PECUÁRIA E SERVIÇOS RELACIONADOS
A58: 01.55 | B58: 01.55-5/04 | C58: Criação de aves, exceto galináceos | D58: 34.77 | E58: 0.75 | F58: Preferencial | G58: -0.25 | H58: Gap > 0,5 em relação à mediana do grupo — possível anomalia amostral FAP | I58: Revisar
A59: 01.55 | B59: 01.55-5/01 | C59: Criação de frangos para corte | D59: 53.95 | E59: 1.079 | F59: Alto | G59: 0.079 | H59: Subclasses com perfis distintos dentro da mesma divisão | I59: Aceitável
A60: 01.55 | B60: 01.55-5/05 | C60: Produção de ovos | D60: 66.45 | E60: 1.329 | F60: Elevado | G60: 0.329 | H60: Subclasses com perfis distintos dentro da mesma divisão | I60: Aceitável
A61: 01.55 | B61: 01.55-5/02 | C61: Produção de pintos de um dia | D61: 73.38 | E61: 1.4 | F61: Elevado | G61: 0.4 | H61: Subclasses com perfis distintos dentro da mesma divisão | I61: Aceitável
A62: 01.55 | B62: 01.55-5/03 | C62: Criação de outros galináceos, exceto para corte | D62: 83.97 | E62: 1.4 | F62: Elevado | G62: 0.4 | H62: Subclasses com perfis distintos dentro da mesma divisão | I62: Aceitável
A64: DIVISÃO 01.61 — AGRICULTURA, PECUÁRIA E SERVIÇOS RELACIONADOS
A65: 01.61 | B65: 01.61-0/99 | C65: Atividades de apoio à agricultura não especificadas anteriormente | D65: 46.32 | E65: 0.9264 | F65: Baixo | G65: -0.0736 | H65: Apoio/beneficiamento — natureza diferente da extração primária | I65: Aceitável
A66: 01.61 | B66: 01.61-0/03 | C66: Serviço de preparação de terreno, cultivo e colheita | D66: 48.09 | E66: 0.9618 | F66: Médio | G66: -0.0382 | H66: Apoio/beneficiamento — natureza diferente da extração primária | I66: Aceitável
A67: 01.61 | B67: 01.61-0/01 | C67: Serviço de pulverização e controle de pragas agrícolas | D67: 48.17 | E67: 0.9634 | F67: Médio | G67: -0.0366 | H67: Apoio/beneficiamento — natureza diferente da extração primária | I67: Aceitável
A68: 01.61 | B68: 01.61-0/02 | C68: Serviço de poda de árvores para lavouras | D68: 81.44 | E68: 1.4 | F68: Elevado | G68: 0.4 | H68: Apoio/beneficiamento — natureza diferente da extração primária | I68: Aceitável
A70: DIVISÃO 02.10 — PRODUÇÃO FLORESTAL
A71: 02.10 | B71: 02.10-1/02 | C71: Cultivo de acácia-negra | D71: 34.98 | E71: 0.75 | F71: Preferencial | G71: -0.25 | H71: Extremo inferior vs extremo superior na mesma divisão — verificar contexto | I71: Revisar
A72: 02.10 | B72: 02.10-1/09 | C72: Produção de casca de acácia-negra - florestas plantadas | D72: 18.98 | E72: 0.75 | F72: Preferencial | G72: -0.25 | H72: Atividade agrícola leve — diferente das culturas intensivas | I72: Aceitável
A73: 02.10 | B73: 02.10-1/99 | C73: Produção de produtos não madeireiros não especificados anteriormente em florestas plantadas | D73: 41.16 | E73: 0.8232 | F73: Preferencial | G73: -0.1768 | H73: Atividade agrícola leve — diferente das culturas intensivas | I73: Aceitável
A74: 02.10 | B74: 02.10-1/05 | C74: Cultivo de espécies madeireiras, exceto eucalipto, acácia-negra, pinus e teca | D74: 41.5 | E74: 0.83 | F74: Preferencial | G74: -0.17 | H74: Subclasses com perfis distintos dentro da mesma divisão | I74: Aceitável
A75: 02.10 | B75: 02.10-1/06 | C75: Cultivo de mudas em viveiros florestais | D75: 59.21 | E75: 1.1842 | F75: Alto | G75: 0.1842 | H75: Atividade agrícola leve — diferente das culturas intensivas | I75: Aceitável
A76: 02.10 | B76: 02.10-1/01 | C76: Cultivo de eucalipto | D76: 59.74 | E76: 1.1948 | F76: Alto | G76: 0.1948 | H76: Subclasses com perfis distintos dentro da mesma divisão | I76: Aceitável
A77: 02.10 | B77: 02.10-1/08 | C77: Produção de carvão vegetal - florestas plantadas | D77: 69.9 | E77: 1.398 | F77: Elevado | G77: 0.398 | H77: Atividade agrícola leve — diferente das culturas intensivas | I77: Aceitável
A78: 02.10 | B78: 02.10-1/03 | C78: Cultivo de pinus | D78: 92.16 | E78: 1.4 | F78: Elevado | G78: 0.4 | H78: Subclasses com perfis distintos dentro da mesma divisão | I78: Aceitável
A79: 02.10 | B79: 02.10-1/04 | C79: Cultivo de teca | D79: 72.31 | E79: 1.4 | F79: Elevado | G79: 0.4 | H79: Subclasses com perfis distintos dentro da mesma divisão | I79: Aceitável
A80: 02.10 | B80: 02.10-1/07 | C80: Extração de madeira em florestas plantadas | D80: 90.27 | E80: 1.4 | F80: Elevado | G80: 0.4 | H80: Atividade extrativa primária — risco inerentemente alto | I80: Aceitável
A82: DIVISÃO 02.20 — PRODUÇÃO FLORESTAL
A83: 02.20 | B83: 02.20-9/99 | C83: Coleta de produtos não madeireiros não especificados anteriormente em florestas nativas | D83: 47.39 | E83: 0.9478 | F83: Baixo | G83: -0.0522 | H83: Atividade extrativa primária — risco inerentemente alto | I83: Aceitável
A84: 02.20 | B84: 02.20-9/04 | C84: Coleta de látex em florestas nativas | D84: 59.79 | E84: 1.1958 | F84: Alto | G84: 0.1958 | H84: Atividade extrativa primária — risco inerentemente alto | I84: Aceitável
A85: 02.20 | B85: 02.20-9/02 | C85: Produção de carvão vegetal - florestas nativas | D85: 64.61 | E85: 1.2922 | F85: Elevado | G85: 0.2922 | H85: Atividade agrícola leve — diferente das culturas intensivas | I85: Aceitável
A86: 02.20 | B86: 02.20-9/06 | C86: Conservação de florestas nativas | D86: 67.67 | E86: 1.3534 | F86: Elevado | G86: 0.3534 | H86: Atividade agrícola leve — diferente das culturas intensivas | I86: Aceitável
A87: 02.20 | B87: 02.20-9/01 | C87: Extração de madeira em florestas nativas | D87: 87.1 | E87: 1.4 | F87: Elevado | G87: 0.4 | H87: Atividade extrativa primária — risco inerentemente alto | I87: Aceitável
A88: 02.20 | B88: 02.20-9/03 | C88: Coleta de castanha-do-pará em florestas nativas | D88: 84.3 | E88: 1.4 | F88: Elevado | G88: 0.4 | H88: Atividade extrativa primária — risco inerentemente alto | I88: Aceitável
A89: 02.20 | B89: 02.20-9/05 | C89: Coleta de palmito em florestas nativas | D89: 99.89 | E89: 1.4 | F89: Elevado | G89: 0.4 | H89: Atividade extrativa primária — risco inerentemente alto | I89: Aceitável
A91: DIVISÃO 03.11 — PESCA E AQÜICULTURA
A92: 03.11 | B92: 03.11-6/04 | C92: Atividades de apoio à pesca em água salgada | D92: 29.38 | E92: 0.75 | F92: Preferencial | G92: -0.25 | H92: Apoio/beneficiamento — natureza diferente da extração primária | I92: Aceitável
A93: 03.11 | B93: 03.11-6/02 | C93: Pesca de crustáceos e moluscos em água salgada | D93: 49.14 | E93: 0.9828 | F93: Médio | G93: -0.0172 | H93: Atividade extrativa primária — risco inerentemente alto | I93: Aceitável
A94: 03.11 | B94: 03.11-6/01 | C94: Pesca de peixes em água salgada | D94: 84.09 | E94: 1.4 | F94: Elevado | G94: 0.4 | H94: Atividade extrativa primária — risco inerentemente alto | I94: Aceitável
A95: 03.11 | B95: 03.11-6/03 | C95: Coleta de outros produtos marinhos | D95: 99.75 | E95: 1.4 | F95: Elevado | G95: 0.4 | H95: Atividade extrativa primária — risco inerentemente alto | I95: Aceitável
A97: DIVISÃO 03.12 — PESCA E AQÜICULTURA
A98: 03.12 | B98: 03.12-4/03 | C98: Coleta de outros produtos aquáticos de água doce | D98: 30.77 | E98: 0.75 | F98: Preferencial | G98: -0.25 | H98: Atividade extrativa primária — risco inerentemente alto | I98: Aceitável
A99: 03.12 | B99: 03.12-4/01 | C99: Pesca de peixes em água doce | D99: 63.78 | E99: 1.2756 | F99: Elevado | G99: 0.2756 | H99: Atividade extrativa primária — risco inerentemente alto | I99: Aceitável
A101: DIVISÃO 03.21 — PESCA E AQÜICULTURA
A102: 03.21 | B102: 03.21-3/05 | C102: Atividades de apoio à aquicultura em água salgada e salobra | D102: 26.66 | E102: 0.75 | F102: Preferencial | G102: -0.25 | H102: Apoio/beneficiamento — natureza diferente da extração primária | I102: Aceitável
A103: 03.21 | B103: 03.21-3/99 | C103: Cultivos e semicultivos da aquicultura em água salgada e salobra não especificados anteriormente | D103: 9 | E103: 0.75 | F103: Preferencial | G103: -0.25 | H103: Extremo inferior vs extremo superior na mesma divisão — verificar contexto | I103: Revisar
A104: 03.21 | B104: 03.21-3/02 | C104: Criação de camarões em água salgada e salobra | D104: 39.22 | E104: 0.7844 | F104: Preferencial | G104: -0.2156 | H104: Subclasses com perfis distintos dentro da mesma divisão | I104: Aceitável
A105: 03.21 | B105: 03.21-3/04 | C105: Criação de peixes ornamentais em água salgada e salobra | D105: 85.31 | E105: 1.4 | F105: Elevado | G105: 0.4 | H105: Gap > 0,5 em relação à mediana do grupo — possível anomalia amostral FAP | I105: Revisar
A107: DIVISÃO 07.21 — EXTRAÇÃO DE MINERAIS METÁLICOS
A108: 07.21 | B108: 07.21-9/01 | C108: Extração de minério de alumínio | D108: 8.87 | E108: 0.75 | F108: Preferencial | G108: -0.25 | H108: Atividade extrativa primária — risco inerentemente alto | I108: Aceitável
A109: 07.21 | B109: 07.21-9/02 | C109: Beneficiamento de minério de alumínio | D109: 78.99 | E109: 1.4 | F109: Elevado | G109: 0.4 | H109: Apoio/beneficiamento — natureza diferente da extração primária | I109: Aceitável
A111: DIVISÃO 07.29 — EXTRAÇÃO DE MINERAIS METÁLICOS
A112: 07.29 | B112: 07.29-4/01 | C112: Extração de minérios de nióbio e titânio | D112: 10.08 | E112: 0.75 | F112: Preferencial | G112: -0.25 | H112: Atividade extrativa primária — risco inerentemente alto | I112: Aceitável
A113: 07.29 | B113: 07.29-4/02 | C113: Extração de minério de tungstênio | D113: 8.29 | E113: 0.75 | F113: Preferencial | G113: -0.25 | H113: Atividade extrativa primária — risco inerentemente alto | I113: Aceitável
A114: 07.29 | B114: 07.29-4/03 | C114: Extração de minério de níquel | D114: 31.65 | E114: 0.75 | F114: Preferencial | G114: -0.25 | H114: Atividade extrativa primária — risco inerentemente alto | I114: Aceitável
A115: 07.29 | B115: 07.29-4/04 | C115: Extração de minérios de cobre, chumbo, zinco e outros minerais metálicos não ferrosos não especificados anteriormente | D115: 43.42 | E115: 0.8684 | F115: Preferencial | G115: -0.1316 | H115: Atividade extrativa primária — risco inerentemente alto | I115: Aceitável
A116: 07.29 | B116: 07.29-4/05 | C116: Beneficiamento de minérios de cobre, chumbo, zinco e outros minerais metálicos não ferrosos não especificados anteriormente | D116: 55.39 | E116: 1.1078 | F116: Alto | G116: 0.1078 | H116: Apoio/beneficiamento — natureza diferente da extração primária | I116: Aceitável
...

Sheet 07_CONSULTA_CNAE
A1: CONSULTA RÁPIDA — CNAE: DADOS FAP E RELATIVIDADES
A2: Digite o código no campo azul abaixo (formato: 0000-0/00). Todos os campos atualizam automaticamente via fórmula.
A5: ▼ DIGITE O CÓDIGO CNAE (ex: 0111-3/01 ou 0500-3/01 ou 0810-0/01)
A6: 0111-3/01
A8: IDENTIFICAÇÃO
A9: CNAE | B9: =IFERROR(INDEX('04_MOTOR_CÁLCULO'!A:A,MATCH($A$6,'04_MOTOR_CÁLCULO'!$A:$A,0)),"Código não encontrado") -> 0111-3/01
A10: Seção | B10: =IFERROR(INDEX('04_MOTOR_CÁLCULO'!B:B,MATCH($A$6,'04_MOTOR_CÁLCULO'!$A:$A,0)),"Código não encontrado") -> A
A11: Descrição | B11: =IFERROR(INDEX('04_MOTOR_CÁLCULO'!C:C,MATCH($A$6,'04_MOTOR_CÁLCULO'!$A:$A,0)),"Código não encontrado") -> Cultivo de arroz
A12: Classificação CNAE-STG | B12: =IFERROR(INDEX('04_MOTOR_CÁLCULO'!E:E,MATCH($A$6,'04_MOTOR_CÁLCULO'!$A:$A,0)),"Código não encontrado") -> Médio
A14: DADOS FAP — PERCENTIS BRUTOS
A15: P_Frequência 2023 | B15: =IFERROR(INDEX('03_FONTE_FAP'!C:C,MATCH($A$6,'03_FONTE_FAP'!$A:$A,0)),"N/D") -> N/D | C15: Vigência 2024 — período-base 2021-2022
A16: P_Gravidade 2023 | B16: =IFERROR(INDEX('03_FONTE_FAP'!D:D,MATCH($A$6,'03_FONTE_FAP'!$A:$A,0)),"N/D") -> N/D
A17: P_Custo 2023 | B17: =IFERROR(INDEX('03_FONTE_FAP'!E:E,MATCH($A$6,'03_FONTE_FAP'!$A:$A,0)),"N/D") -> N/D
A18: P_Frequência 2024 | B18: =IFERROR(INDEX('03_FONTE_FAP'!H:H,MATCH($A$6,'03_FONTE_FAP'!$A:$A,0)),"N/D") -> N/D | C18: Vigência 2025 — período-base 2022-2023
A19: P_Gravidade 2024 | B19: =IFERROR(INDEX('03_FONTE_FAP'!I:I,MATCH($A$6,'03_FONTE_FAP'!$A:$A,0)),"N/D") -> N/D
A20: P_Custo 2024 | B20: =IFERROR(INDEX('03_FONTE_FAP'!J:J,MATCH($A$6,'03_FONTE_FAP'!$A:$A,0)),"N/D") -> N/D
A22: ÍNDICE COMPOSTO — CALCULADO POR FÓRMULA
A23: IC 2023 [= w_G×P_Grav + w_F×P_Freq + w_C×P_Custo] | B23: =IFERROR(INDEX('03_FONTE_FAP'!F:F,MATCH($A$6,'03_FONTE_FAP'!$A:$A,0)),"N/D") -> N/D
A24: IC 2024 | B24: =IFERROR(INDEX('03_FONTE_FAP'!K:K,MATCH($A$6,'03_FONTE_FAP'!$A:$A,0)),"N/D") -> N/D
A25: IC Médio | B25: =IFERROR(INDEX('03_FONTE_FAP'!M:M,MATCH($A$6,'03_FONTE_FAP'!$A:$A,0)),"N/D") -> N/D | C25: Média dos ICs válidos disponíveis
A26: IC Referência (parâmetro B1) | B26: ='01_PARÂMETROS'!$B$9 -> 50 | C26: Fixo = 50,0 (mediana teórica)
A28: RELATIVIDADE FINAL
A29: Relatividade Bruta [= IC_Médio / IC_ref] | B29: =IFERROR(INDEX('03_FONTE_FAP'!N:N,MATCH($A$6,'03_FONTE_FAP'!$A:$A,0)),"N/D") -> N/D
A30: Relatividade Final [= MAX(0,75 ; MIN(1,40 ; Bruta)) | B30: =IFERROR(INDEX('04_MOTOR_CÁLCULO'!K:K,MATCH($A$6,'04_MOTOR_CÁLCULO'!$A:$A,0)),"Código não encontrado") -> 1.12263
A31: Ajuste sobre a Taxa Pura | B31: =IFERROR(INDEX('04_MOTOR_CÁLCULO'!L:L,MATCH($A$6,'04_MOTOR_CÁLCULO'!$A:$A,0)),"Código não encontrado") -> 0.12263
A32: Classe de Risco | B32: =IFERROR(INDEX('04_MOTOR_CÁLCULO'!M:M,MATCH($A$6,'04_MOTOR_CÁLCULO'!$A:$A,0)),"Código não encontrado") -> Alto
A33: Fonte do Cálculo | B33: =IFERROR(INDEX('04_MOTOR_CÁLCULO'!N:N,MATCH($A$6,'04_MOTOR_CÁLCULO'!$A:$A,0)),"Código não encontrado") -> FAP/MPS | C33: FAP/MPS ou CNAE-STG (fallback)
A34: Flag de Conflito Intra-Grupo | B34: =IFERROR(INDEX('04_MOTOR_CÁLCULO'!O:O,MATCH($A$6,'04_MOTOR_CÁLCULO'!$A:$A,0)),"Código não encontrado") -> Revisar | C34: Veja aba AUDITORIA se ⚠
A36: ℹ️ Todos os campos desta aba são fórmulas MATCH/INDEX vinculadas às abas 03_FONTE_FAP e 04_MOTOR_CÁLCULO. Alterar o código em A6 atualiza todos os campos automaticamente. Formato: NNNN-N/NN — exemplo: 0810-0/01 (extração de pedra).

Sheet 08_RESULTADOS
A1: RESULTADOS FINAIS — RELATIVIDADES POR CNAE | VIDA CAPITAL GLOBAL
A2: Todas as colunas são fórmulas vinculadas à aba 04_MOTOR_CÁLCULO via MATCH/INDEX — sem valores colados.
A3: Cód. CNAE | B3: Sec. | C3: Descrição Subclasse | D3: Divisão | E3: Fonte | F3: Relat. Final | G3: Ajuste % | H3: Classe
A4: ='04_MOTOR_CÁLCULO'!A7 -> 0111-3/03 | B4: ='04_MOTOR_CÁLCULO'!B7 -> A | C4: ='04_MOTOR_CÁLCULO'!C7 -> Cultivo de trigo | D4: ='04_MOTOR_CÁLCULO'!D7 -> AGRICULTURA, PEC | E4: ='04_MOTOR_CÁLCULO'!N7 -> FAP/MPS | F4: ='04_MOTOR_CÁLCULO'!K7 -> 0.75 | G4: ='04_MOTOR_CÁLCULO'!K7-1 -> -0.25 | H4: ='04_MOTOR_CÁLCULO'!M7 -> Preferencial
A5: ='04_MOTOR_CÁLCULO'!A10 -> 0112-1/02 | B5: ='04_MOTOR_CÁLCULO'!B10 -> A | C5: ='04_MOTOR_CÁLCULO'!C10 -> Cultivo de juta | D5: ='04_MOTOR_CÁLCULO'!D10 -> AGRICULTURA, PEC | E5: ='04_MOTOR_CÁLCULO'!N10 -> FAP/MPS | F5: ='04_MOTOR_CÁLCULO'!K10 -> 0.75 | G5: ='04_MOTOR_CÁLCULO'!K10-1 -> -0.25 | H5: ='04_MOTOR_CÁLCULO'!M10 -> Preferencial
A6: ='04_MOTOR_CÁLCULO'!A18 -> 0116-4/99 | B6: ='04_MOTOR_CÁLCULO'!B18 -> A | C6: ='04_MOTOR_CÁLCULO'!C18 -> Cultivo de outras oleaginosas de lavoura temporária não especificadas anteriormente | D6: ='04_MOTOR_CÁLCULO'!D18 -> AGRICULTURA, PEC | E6: ='04_MOTOR_CÁLCULO'!N18 -> FAP/MPS | F6: ='04_MOTOR_CÁLCULO'!K18 -> 0.75 | G6: ='04_MOTOR_CÁLCULO'!K18-1 -> -0.25 | H6: ='04_MOTOR_CÁLCULO'!M18 -> Preferencial
A7: ='04_MOTOR_CÁLCULO'!A20 -> 0119-9/02 | B7: ='04_MOTOR_CÁLCULO'!B20 -> A | C7: ='04_MOTOR_CÁLCULO'!C20 -> Cultivo de alho | D7: ='04_MOTOR_CÁLCULO'!D20 -> AGRICULTURA, PEC | E7: ='04_MOTOR_CÁLCULO'!N20 -> FAP/MPS | F7: ='04_MOTOR_CÁLCULO'!K20 -> 0.75 | G7: ='04_MOTOR_CÁLCULO'!K20-1 -> -0.25 | H7: ='04_MOTOR_CÁLCULO'!M20 -> Preferencial
A8: ='04_MOTOR_CÁLCULO'!A22 -> 0119-9/04 | B8: ='04_MOTOR_CÁLCULO'!B22 -> A | C8: ='04_MOTOR_CÁLCULO'!C22 -> Cultivo de cebola | D8: ='04_MOTOR_CÁLCULO'!D22 -> AGRICULTURA, PEC | E8: ='04_MOTOR_CÁLCULO'!N22 -> FAP/MPS | F8: ='04_MOTOR_CÁLCULO'!K22 -> 0.75 | G8: ='04_MOTOR_CÁLCULO'!K22-1 -> -0.25 | H8: ='04_MOTOR_CÁLCULO'!M22 -> Preferencial
A9: ='04_MOTOR_CÁLCULO'!A24 -> 0119-9/06 | B9: ='04_MOTOR_CÁLCULO'!B24 -> A | C9: ='04_MOTOR_CÁLCULO'!C24 -> Cultivo de mandioca | D9: ='04_MOTOR_CÁLCULO'!D24 -> AGRICULTURA, PEC | E9: ='04_MOTOR_CÁLCULO'!N24 -> FAP/MPS | F9: ='04_MOTOR_CÁLCULO'!K24 -> 0.75 | G9: ='04_MOTOR_CÁLCULO'!K24-1 -> -0.25 | H9: ='04_MOTOR_CÁLCULO'!M24 -> Preferencial
A10: ='04_MOTOR_CÁLCULO'!A27 -> 0119-9/09 | B10: ='04_MOTOR_CÁLCULO'!B27 -> A | C10: ='04_MOTOR_CÁLCULO'!C27 -> Cultivo de tomate rasteiro | D10: ='04_MOTOR_CÁLCULO'!D27 -> AGRICULTURA, PEC | E10: ='04_MOTOR_CÁLCULO'!N27 -> FAP/MPS | F10: ='04_MOTOR_CÁLCULO'!K27 -> 0.75 | G10: ='04_MOTOR_CÁLCULO'!K27-1 -> -0.25 | H10: ='04_MOTOR_CÁLCULO'!M27 -> Preferencial
A11: ='04_MOTOR_CÁLCULO'!A29 -> 0121-1/01 | B11: ='04_MOTOR_CÁLCULO'!B29 -> A | C11: ='04_MOTOR_CÁLCULO'!C29 -> Horticultura, exceto morango | D11: ='04_MOTOR_CÁLCULO'!D29 -> AGRICULTURA, PEC | E11: ='04_MOTOR_CÁLCULO'!N29 -> FAP/MPS | F11: ='04_MOTOR_CÁLCULO'!K29 -> 0.75 | G11: ='04_MOTOR_CÁLCULO'!K29-1 -> -0.25 | H11: ='04_MOTOR_CÁLCULO'!M29 -> Preferencial
A12: ='04_MOTOR_CÁLCULO'!A31 -> 0122-9/00 | B12: ='04_MOTOR_CÁLCULO'!B31 -> A | C12: ='04_MOTOR_CÁLCULO'!C31 -> Cultivo de flores e plantas ornamentais | D12: ='04_MOTOR_CÁLCULO'!D31 -> AGRICULTURA, PEC | E12: ='04_MOTOR_CÁLCULO'!N31 -> FAP/MPS | F12: ='04_MOTOR_CÁLCULO'!K31 -> 0.75 | G12: ='04_MOTOR_CÁLCULO'!K31-1 -> -0.25 | H12: ='04_MOTOR_CÁLCULO'!M31 -> Preferencial
A13: ='04_MOTOR_CÁLCULO'!A34 -> 0133-4/01 | B13: ='04_MOTOR_CÁLCULO'!B34 -> A | C13: ='04_MOTOR_CÁLCULO'!C34 -> Cultivo de açaí | D13: ='04_MOTOR_CÁLCULO'!D34 -> AGRICULTURA, PEC | E13: ='04_MOTOR_CÁLCULO'!N34 -> FAP/MPS | F13: ='04_MOTOR_CÁLCULO'!K34 -> 0.75 | G13: ='04_MOTOR_CÁLCULO'!K34-1 -> -0.25 | H13: ='04_MOTOR_CÁLCULO'!M34 -> Preferencial
A14: ='04_MOTOR_CÁLCULO'!A51 -> 0139-3/04 | B14: ='04_MOTOR_CÁLCULO'!B51 -> A | C14: ='04_MOTOR_CÁLCULO'!C51 -> Cultivo de plantas para condimento, exceto pimenta-do-reino | D14: ='04_MOTOR_CÁLCULO'!D51 -> AGRICULTURA, PEC | E14: ='04_MOTOR_CÁLCULO'!N51 -> FAP/MPS | F14: ='04_MOTOR_CÁLCULO'!K51 -> 0.75 | G14: ='04_MOTOR_CÁLCULO'!K51-1 -> -0.25 | H14: ='04_MOTOR_CÁLCULO'!M51 -> Preferencial
A15: ='04_MOTOR_CÁLCULO'!A53 -> 0139-3/06 | B15: ='04_MOTOR_CÁLCULO'!B53 -> A | C15: ='04_MOTOR_CÁLCULO'!C53 -> Cultivo de seringueira | D15: ='04_MOTOR_CÁLCULO'!D53 -> AGRICULTURA, PEC | E15: ='04_MOTOR_CÁLCULO'!N53 -> FAP/MPS | F15: ='04_MOTOR_CÁLCULO'!K53 -> 0.75 | G15: ='04_MOTOR_CÁLCULO'!K53-1 -> -0.25 | H15: ='04_MOTOR_CÁLCULO'!M53 -> Preferencial
A16: ='04_MOTOR_CÁLCULO'!A55 -> 0141-5/01 | B16: ='04_MOTOR_CÁLCULO'!B55 -> A | C16: ='04_MOTOR_CÁLCULO'!C55 -> Produção de sementes certificadas, exceto de forrageiras para pasto | D16: ='04_MOTOR_CÁLCULO'!D55 -> AGRICULTURA, PEC | E16: ='04_MOTOR_CÁLCULO'!N55 -> FAP/MPS | F16: ='04_MOTOR_CÁLCULO'!K55 -> 0.75 | G16: ='04_MOTOR_CÁLCULO'!K55-1 -> -0.25 | H16: ='04_MOTOR_CÁLCULO'!M55 -> Preferencial
A17: ='04_MOTOR_CÁLCULO'!A61 -> 0152-1/01 | B17: ='04_MOTOR_CÁLCULO'!B61 -> A | C17: ='04_MOTOR_CÁLCULO'!C61 -> Criação de bufalinos | D17: ='04_MOTOR_CÁLCULO'!D61 -> AGRICULTURA, PEC | E17: ='04_MOTOR_CÁLCULO'!N61 -> FAP/MPS | F17: ='04_MOTOR_CÁLCULO'!K61 -> 0.75 | G17: ='04_MOTOR_CÁLCULO'!K61-1 -> -0.25 | H17: ='04_MOTOR_CÁLCULO'!M61 -> Preferencial
A18: ='04_MOTOR_CÁLCULO'!A64 -> 0153-9/01 | B18: ='04_MOTOR_CÁLCULO'!B64 -> A | C18: ='04_MOTOR_CÁLCULO'!C64 -> Criação de caprinos | D18: ='04_MOTOR_CÁLCULO'!D64 -> AGRICULTURA, PEC | E18: ='04_MOTOR_CÁLCULO'!N64 -> FAP/MPS | F18: ='04_MOTOR_CÁLCULO'!K64 -> 0.75 | G18: ='04_MOTOR_CÁLCULO'!K64-1 -> -0.25 | H18: ='04_MOTOR_CÁLCULO'!M64 -> Preferencial
A19: ='04_MOTOR_CÁLCULO'!A70 -> 0155-5/04 | B19: ='04_MOTOR_CÁLCULO'!B70 -> A | C19: ='04_MOTOR_CÁLCULO'!C70 -> Criação de aves, exceto galináceos | D19: ='04_MOTOR_CÁLCULO'!D70 -> AGRICULTURA, PEC | E19: ='04_MOTOR_CÁLCULO'!N70 -> FAP/MPS | F19: ='04_MOTOR_CÁLCULO'!K70 -> 0.75 | G19: ='04_MOTOR_CÁLCULO'!K70-1 -> -0.25 | H19: ='04_MOTOR_CÁLCULO'!M70 -> Preferencial
A20: ='04_MOTOR_CÁLCULO'!A88 -> 0210-1/02 | B20: ='04_MOTOR_CÁLCULO'!B88 -> A | C20: ='04_MOTOR_CÁLCULO'!C88 -> Cultivo de acácia-negra | D20: ='04_MOTOR_CÁLCULO'!D88 -> PRODUÇÃO FLOREST | E20: ='04_MOTOR_CÁLCULO'!N88 -> FAP/MPS | F20: ='04_MOTOR_CÁLCULO'!K88 -> 0.75 | G20: ='04_MOTOR_CÁLCULO'!K88-1 -> -0.25 | H20: ='04_MOTOR_CÁLCULO'!M88 -> Preferencial
A21: ='04_MOTOR_CÁLCULO'!A95 -> 0210-1/09 | B21: ='04_MOTOR_CÁLCULO'!B95 -> A | C21: ='04_MOTOR_CÁLCULO'!C95 -> Produção de casca de acácia-negra - florestas plantadas | D21: ='04_MOTOR_CÁLCULO'!D95 -> PRODUÇÃO FLOREST | E21: ='04_MOTOR_CÁLCULO'!N95 -> FAP/MPS | F21: ='04_MOTOR_CÁLCULO'!K95 -> 0.75 | G21: ='04_MOTOR_CÁLCULO'!K95-1 -> -0.25 | H21: ='04_MOTOR_CÁLCULO'!M95 -> Preferencial
A22: ='04_MOTOR_CÁLCULO'!A108 -> 0311-6/04 | B22: ='04_MOTOR_CÁLCULO'!B108 -> A | C22: ='04_MOTOR_CÁLCULO'!C108 -> Atividades de apoio à pesca em água salgada | D22: ='04_MOTOR_CÁLCULO'!D108 -> PESCA E AQÜICULT | E22: ='04_MOTOR_CÁLCULO'!N108 -> FAP/MPS | F22: ='04_MOTOR_CÁLCULO'!K108 -> 0.75 | G22: ='04_MOTOR_CÁLCULO'!K108-1 -> -0.25 | H22: ='04_MOTOR_CÁLCULO'!M108 -> Preferencial
A23: ='04_MOTOR_CÁLCULO'!A111 -> 0312-4/03 | B23: ='04_MOTOR_CÁLCULO'!B111 -> A | C23: ='04_MOTOR_CÁLCULO'!C111 -> Coleta de outros produtos aquáticos de água doce | D23: ='04_MOTOR_CÁLCULO'!D111 -> PESCA E AQÜICULT | E23: ='04_MOTOR_CÁLCULO'!N111 -> FAP/MPS | F23: ='04_MOTOR_CÁLCULO'!K111 -> 0.75 | G23: ='04_MOTOR_CÁLCULO'!K111-1 -> -0.25 | H23: ='04_MOTOR_CÁLCULO'!M111 -> Preferencial
A24: ='04_MOTOR_CÁLCULO'!A117 -> 0321-3/05 | B24: ='04_MOTOR_CÁLCULO'!B117 -> A | C24: ='04_MOTOR_CÁLCULO'!C117 -> Atividades de apoio à aquicultura em água salgada e salobra | D24: ='04_MOTOR_CÁLCULO'!D117 -> PESCA E AQÜICULT | E24: ='04_MOTOR_CÁLCULO'!N117 -> FAP/MPS | F24: ='04_MOTOR_CÁLCULO'!K117 -> 0.75 | G24: ='04_MOTOR_CÁLCULO'!K117-1 -> -0.25 | H24: ='04_MOTOR_CÁLCULO'!M117 -> Preferencial
A25: ='04_MOTOR_CÁLCULO'!A118 -> 0321-3/99 | B25: ='04_MOTOR_CÁLCULO'!B118 -> A | C25: ='04_MOTOR_CÁLCULO'!C118 -> Cultivos e semicultivos da aquicultura em água salgada e salobra não especificados anteriormente | D25: ='04_MOTOR_CÁLCULO'!D118 -> PESCA E AQÜICULT | E25: ='04_MOTOR_CÁLCULO'!N118 -> FAP/MPS | F25: ='04_MOTOR_CÁLCULO'!K118 -> 0.75 | G25: ='04_MOTOR_CÁLCULO'!K118-1 -> -0.25 | H25: ='04_MOTOR_CÁLCULO'!M118 -> Preferencial
A26: ='04_MOTOR_CÁLCULO'!A119 -> 0322-1/01 | B26: ='04_MOTOR_CÁLCULO'!B119 -> A | C26: ='04_MOTOR_CÁLCULO'!C119 -> Criação de peixes em água doce | D26: ='04_MOTOR_CÁLCULO'!D119 -> PESCA E AQÜICULT | E26: ='04_MOTOR_CÁLCULO'!N119 -> FAP/MPS | F26: ='04_MOTOR_CÁLCULO'!K119 -> 0.75 | G26: ='04_MOTOR_CÁLCULO'!K119-1 -> -0.25 | H26: ='04_MOTOR_CÁLCULO'!M119 -> Preferencial
A27: ='04_MOTOR_CÁLCULO'!A120 -> 0322-1/02 | B27: ='04_MOTOR_CÁLCULO'!B120 -> A | C27: ='04_MOTOR_CÁLCULO'!C120 -> Criação de camarões em água doce | D27: ='04_MOTOR_CÁLCULO'!D120 -> PESCA E AQÜICULT | E27: ='04_MOTOR_CÁLCULO'!N120 -> FAP/MPS | F27: ='04_MOTOR_CÁLCULO'!K120 -> 0.75 | G27: ='04_MOTOR_CÁLCULO'!K120-1 -> -0.25 | H27: ='04_MOTOR_CÁLCULO'!M120 -> Preferencial
A28: ='04_MOTOR_CÁLCULO'!A122 -> 0322-1/04 | B28: ='04_MOTOR_CÁLCULO'!B122 -> A | C28: ='04_MOTOR_CÁLCULO'!C122 -> Criação de peixes ornamentais em água doce | D28: ='04_MOTOR_CÁLCULO'!D122 -> PESCA E AQÜICULT | E28: ='04_MOTOR_CÁLCULO'!N122 -> FAP/MPS | F28: ='04_MOTOR_CÁLCULO'!K122 -> 0.75 | G28: ='04_MOTOR_CÁLCULO'!K122-1 -> -0.25 | H28: ='04_MOTOR_CÁLCULO'!M122 -> Preferencial
A29: ='04_MOTOR_CÁLCULO'!A123 -> 0322-1/05 | B29: ='04_MOTOR_CÁLCULO'!B123 -> A | C29: ='04_MOTOR_CÁLCULO'!C123 -> Ranicultura | D29: ='04_MOTOR_CÁLCULO'!D123 -> PESCA E AQÜICULT | E29: ='04_MOTOR_CÁLCULO'!N123 -> FAP/MPS | F29: ='04_MOTOR_CÁLCULO'!K123 -> 0.75 | G29: ='04_MOTOR_CÁLCULO'!K123-1 -> -0.25 | H29: ='04_MOTOR_CÁLCULO'!M123 -> Preferencial
A30: ='04_MOTOR_CÁLCULO'!A126 -> 0322-1/99 | B30: ='04_MOTOR_CÁLCULO'!B126 -> A | C30: ='04_MOTOR_CÁLCULO'!C126 -> Cultivos e semicultivos da aquicultura em água doce não especificados anteriormente | D30: ='04_MOTOR_CÁLCULO'!D126 -> PESCA E AQÜICULT | E30: ='04_MOTOR_CÁLCULO'!N126 -> FAP/MPS | F30: ='04_MOTOR_CÁLCULO'!K126 -> 0.75 | G30: ='04_MOTOR_CÁLCULO'!K126-1 -> -0.25 | H30: ='04_MOTOR_CÁLCULO'!M126 -> Preferencial
A31: ='04_MOTOR_CÁLCULO'!A130 -> 0600-0/02 | B31: ='04_MOTOR_CÁLCULO'!B130 -> B | C31: ='04_MOTOR_CÁLCULO'!C130 -> Extração e beneficiamento de xisto | D31: ='04_MOTOR_CÁLCULO'!D130 -> EXTRAÇÃO DE PETR | E31: ='04_MOTOR_CÁLCULO'!N130 -> FAP/MPS | F31: ='04_MOTOR_CÁLCULO'!K130 -> 0.75 | G31: ='04_MOTOR_CÁLCULO'!K130-1 -> -0.25 | H31: ='04_MOTOR_CÁLCULO'!M130 -> Preferencial
A32: ='04_MOTOR_CÁLCULO'!A132 -> 0710-3/01 | B32: ='04_MOTOR_CÁLCULO'!B132 -> B | C32: ='04_MOTOR_CÁLCULO'!C132 -> Extração de minério de ferro | D32: ='04_MOTOR_CÁLCULO'!D132 -> EXTRAÇÃO DE MINE | E32: ='04_MOTOR_CÁLCULO'!N132 -> FAP/MPS | F32: ='04_MOTOR_CÁLCULO'!K132 -> 0.75 | G32: ='04_MOTOR_CÁLCULO'!K132-1 -> -0.25 | H32: ='04_MOTOR_CÁLCULO'!M132 -> Preferencial
A33: ='04_MOTOR_CÁLCULO'!A133 -> 0710-3/02 | B33: ='04_MOTOR_CÁLCULO'!B133 -> B | C33: ='04_MOTOR_CÁLCULO'!C133 -> Pelotização, sinterização e outros beneficiamentos de minério de ferro | D33: ='04_MOTOR_CÁLCULO'!D133 -> EXTRAÇÃO DE MINE | E33: ='04_MOTOR_CÁLCULO'!N133 -> FAP/MPS | F33: ='04_MOTOR_CÁLCULO'!K133 -> 0.75 | G33: ='04_MOTOR_CÁLCULO'!K133-1 -> -0.25 | H33: ='04_MOTOR_CÁLCULO'!M133 -> Preferencial
A34: ='04_MOTOR_CÁLCULO'!A134 -> 0721-9/01 | B34: ='04_MOTOR_CÁLCULO'!B134 -> B | C34: ='04_MOTOR_CÁLCULO'!C134 -> Extração de minério de alumínio | D34: ='04_MOTOR_CÁLCULO'!D134 -> EXTRAÇÃO DE MINE | E34: ='04_MOTOR_CÁLCULO'!N134 -> FAP/MPS | F34: ='04_MOTOR_CÁLCULO'!K134 -> 0.75 | G34: ='04_MOTOR_CÁLCULO'!K134-1 -> -0.25 | H34: ='04_MOTOR_CÁLCULO'!M134 -> Preferencial
A35: ='04_MOTOR_CÁLCULO'!A141 -> 0724-3/02 | B35: ='04_MOTOR_CÁLCULO'!B141 -> B | C35: ='04_MOTOR_CÁLCULO'!C141 -> Beneficiamento de minério de metais preciosos | D35: ='04_MOTOR_CÁLCULO'!D141 -> EXTRAÇÃO DE MINE | E35: ='04_MOTOR_CÁLCULO'!N141 -> FAP/MPS | F35: ='04_MOTOR_CÁLCULO'!K141 -> 0.75 | G35: ='04_MOTOR_CÁLCULO'!K141-1 -> -0.25 | H35: ='04_MOTOR_CÁLCULO'!M141 -> Preferencial
A36: ='04_MOTOR_CÁLCULO'!A143 -> 0729-4/01 | B36: ='04_MOTOR_CÁLCULO'!B143 -> B | C36: ='04_MOTOR_CÁLCULO'!C143 -> Extração de minérios de nióbio e titânio | D36: ='04_MOTOR_CÁLCULO'!D143 -> EXTRAÇÃO DE MINE | E36: ='04_MOTOR_CÁLCULO'!N143 -> FAP/MPS | F36: ='04_MOTOR_CÁLCULO'!K143 -> 0.75 | G36: ='04_MOTOR_CÁLCULO'!K143-1 -> -0.25 | H36: ='04_MOTOR_CÁLCULO'!M143 -> Preferencial
A37: ='04_MOTOR_CÁLCULO'!A144 -> 0729-4/02 | B37: ='04_MOTOR_CÁLCULO'!B144 -> B | C37: ='04_MOTOR_CÁLCULO'!C144 -> Extração de minério de tungstênio | D37: ='04_MOTOR_CÁLCULO'!D144 -> EXTRAÇÃO DE MINE | E37: ='04_MOTOR_CÁLCULO'!N144 -> FAP/MPS | F37: ='04_MOTOR_CÁLCULO'!K144 -> 0.75 | G37: ='04_MOTOR_CÁLCULO'!K144-1 -> -0.25 | H37: ='04_MOTOR_CÁLCULO'!M144 -> Preferencial
A38: ='04_MOTOR_CÁLCULO'!A145 -> 0729-4/03 | B38: ='04_MOTOR_CÁLCULO'!B145 -> B | C38: ='04_MOTOR_CÁLCULO'!C145 -> Extração de minério de níquel | D38: ='04_MOTOR_CÁLCULO'!D145 -> EXTRAÇÃO DE MINE | E38: ='04_MOTOR_CÁLCULO'!N145 -> FAP/MPS | F38: ='04_MOTOR_CÁLCULO'!K145 -> 0.75 | G38: ='04_MOTOR_CÁLCULO'!K145-1 -> -0.25 | H38: ='04_MOTOR_CÁLCULO'!M145 -> Preferencial
A39: ='04_MOTOR_CÁLCULO'!A155 -> 0810-0/08 | B39: ='04_MOTOR_CÁLCULO'!B155 -> B | C39: ='04_MOTOR_CÁLCULO'!C155 -> Extração de saibro e beneficiamento associado | D39: ='04_MOTOR_CÁLCULO'!D155 -> EXTRAÇÃO DE MINE | E39: ='04_MOTOR_CÁLCULO'!N155 -> FAP/MPS | F39: ='04_MOTOR_CÁLCULO'!K155 -> 0.75 | G39: ='04_MOTOR_CÁLCULO'!K155-1 -> -0.25 | H39: ='04_MOTOR_CÁLCULO'!M155 -> Preferencial
A40: ='04_MOTOR_CÁLCULO'!A157 -> 0810-0/10 | B40: ='04_MOTOR_CÁLCULO'!B157 -> B | C40: ='04_MOTOR_CÁLCULO'!C157 -> Beneficiamento de gesso e caulim associado à extração | D40: ='04_MOTOR_CÁLCULO'!D157 -> EXTRAÇÃO DE MINE | E40: ='04_MOTOR_CÁLCULO'!N157 -> FAP/MPS | F40: ='04_MOTOR_CÁLCULO'!K157 -> 0.75 | G40: ='04_MOTOR_CÁLCULO'!K157-1 -> -0.25 | H40: ='04_MOTOR_CÁLCULO'!M157 -> Preferencial
A41: ='04_MOTOR_CÁLCULO'!A161 -> 0892-4/02 | B41: ='04_MOTOR_CÁLCULO'!B161 -> B | C41: ='04_MOTOR_CÁLCULO'!C161 -> Extração de sal-gema | D41: ='04_MOTOR_CÁLCULO'!D161 -> EXTRAÇÃO DE MINE | E41: ='04_MOTOR_CÁLCULO'!N161 -> FAP/MPS | F41: ='04_MOTOR_CÁLCULO'!K161 -> 0.75 | G41: ='04_MOTOR_CÁLCULO'!K161-1 -> -0.25 | H41: ='04_MOTOR_CÁLCULO'!M161 -> Preferencial
A42: ='04_MOTOR_CÁLCULO'!A164 -> 0899-1/01 | B42: ='04_MOTOR_CÁLCULO'!B164 -> B | C42: ='04_MOTOR_CÁLCULO'!C164 -> Extração de grafita | D42: ='04_MOTOR_CÁLCULO'!D164 -> EXTRAÇÃO DE MINE | E42: ='04_MOTOR_CÁLCULO'!N164 -> FAP/MPS | F42: ='04_MOTOR_CÁLCULO'!K164 -> 0.75 | G42: ='04_MOTOR_CÁLCULO'!K164-1 -> -0.25 | H42: ='04_MOTOR_CÁLCULO'!M164 -> Preferencial
A43: ='04_MOTOR_CÁLCULO'!A57 -> 0142-3/00 | B43: ='04_MOTOR_CÁLCULO'!B57 -> A | C43: ='04_MOTOR_CÁLCULO'!C57 -> Produção de mudas e outras formas de propagação vegetal, certificadas | D43: ='04_MOTOR_CÁLCULO'!D57 -> AGRICULTURA, PEC | E43: ='04_MOTOR_CÁLCULO'!N57 -> FAP/MPS | F43: ='04_MOTOR_CÁLCULO'!K57 -> 0.75013 | G43: ='04_MOTOR_CÁLCULO'!K57-1 -> -0.24987 | H43: ='04_MOTOR_CÁLCULO'!M57 -> Preferencial
A44: ='04_MOTOR_CÁLCULO'!A129 -> 0600-0/01 | B44: ='04_MOTOR_CÁLCULO'!B129 -> B | C44: ='04_MOTOR_CÁLCULO'!C129 -> Extração de petróleo e gás natural | D44: ='04_MOTOR_CÁLCULO'!D129 -> EXTRAÇÃO DE PETR | E44: ='04_MOTOR_CÁLCULO'!N129 -> FAP/MPS | F44: ='04_MOTOR_CÁLCULO'!K129 -> 0.75156 | G44: ='04_MOTOR_CÁLCULO'!K129-1 -> -0.24844 | H44: ='04_MOTOR_CÁLCULO'!M129 -> Preferencial
A45: ='04_MOTOR_CÁLCULO'!A43 -> 0133-4/10 | B45: ='04_MOTOR_CÁLCULO'!B43 -> A | C45: ='04_MOTOR_CÁLCULO'!C43 -> Cultivo de manga | D45: ='04_MOTOR_CÁLCULO'!D43 -> AGRICULTURA, PEC | E45: ='04_MOTOR_CÁLCULO'!N43 -> FAP/MPS | F45: ='04_MOTOR_CÁLCULO'!K43 -> 0.76516 | G45: ='04_MOTOR_CÁLCULO'!K43-1 -> -0.23484 | H45: ='04_MOTOR_CÁLCULO'!M43 -> Preferencial
A46: ='04_MOTOR_CÁLCULO'!A6 -> 0111-3/02 | B46: ='04_MOTOR_CÁLCULO'!B6 -> A | C46: ='04_MOTOR_CÁLCULO'!C6 -> Cultivo de milho | D46: ='04_MOTOR_CÁLCULO'!D6 -> AGRICULTURA, PEC | E46: ='04_MOTOR_CÁLCULO'!N6 -> FAP/MPS | F46: ='04_MOTOR_CÁLCULO'!K6 -> 0.76858 | G46: ='04_MOTOR_CÁLCULO'!K6-1 -> -0.23142 | H46: ='04_MOTOR_CÁLCULO'!M6 -> Preferencial
A47: ='04_MOTOR_CÁLCULO'!A37 -> 0133-4/04 | B47: ='04_MOTOR_CÁLCULO'!B37 -> A | C47: ='04_MOTOR_CÁLCULO'!C37 -> Cultivo de cítricos, exceto laranja | D47: ='04_MOTOR_CÁLCULO'!D37 -> AGRICULTURA, PEC | E47: ='04_MOTOR_CÁLCULO'!N37 -> FAP/MPS | F47: ='04_MOTOR_CÁLCULO'!K37 -> 0.774005 | G47: ='04_MOTOR_CÁLCULO'!K37-1 -> -0.225995 | H47: ='04_MOTOR_CÁLCULO'!M37 -> Preferencial
A48: ='04_MOTOR_CÁLCULO'!A42 -> 0133-4/09 | B48: ='04_MOTOR_CÁLCULO'!B42 -> A | C48: ='04_MOTOR_CÁLCULO'!C42 -> Cultivo de maracujá | D48: ='04_MOTOR_CÁLCULO'!D42 -> AGRICULTURA, PEC | E48: ='04_MOTOR_CÁLCULO'!N42 -> FAP/MPS | F48: ='04_MOTOR_CÁLCULO'!K42 -> 0.776755 | G48: ='04_MOTOR_CÁLCULO'!K42-1 -> -0.223245 | H48: ='04_MOTOR_CÁLCULO'!M42 -> Preferencial
A49: ='04_MOTOR_CÁLCULO'!A137 -> 0722-7/02 | B49: ='04_MOTOR_CÁLCULO'!B137 -> B | C49: ='04_MOTOR_CÁLCULO'!C137 -> Beneficiamento de minério de estanho | D49: ='04_MOTOR_CÁLCULO'!D137 -> EXTRAÇÃO DE MINE | E49: ='04_MOTOR_CÁLCULO'!N137 -> FAP/MPS | F49: ='04_MOTOR_CÁLCULO'!K137 -> 0.777375 | G49: ='04_MOTOR_CÁLCULO'!K137-1 -> -0.222625 | H49: ='04_MOTOR_CÁLCULO'!M137 -> Preferencial
A50: ='04_MOTOR_CÁLCULO'!A114 -> 0321-3/02 | B50: ='04_MOTOR_CÁLCULO'!B114 -> A | C50: ='04_MOTOR_CÁLCULO'!C114 -> Criação de camarões em água salgada e salobra | D50: ='04_MOTOR_CÁLCULO'!D114 -> PESCA E AQÜICULT | E50: ='04_MOTOR_CÁLCULO'!N114 -> FAP/MPS | F50: ='04_MOTOR_CÁLCULO'!K114 -> 0.78439 | G50: ='04_MOTOR_CÁLCULO'!K114-1 -> -0.21561 | H50: ='04_MOTOR_CÁLCULO'!M114 -> Preferencial
A51: ='04_MOTOR_CÁLCULO'!A96 -> 0210-1/99 | B51: ='04_MOTOR_CÁLCULO'!B96 -> A | C51: ='04_MOTOR_CÁLCULO'!C96 -> Produção de produtos não madeireiros não especificados anteriormente em florestas plantadas | D51: ='04_MOTOR_CÁLCULO'!D96 -> PRODUÇÃO FLOREST | E51: ='04_MOTOR_CÁLCULO'!N96 -> FAP/MPS | F51: ='04_MOTOR_CÁLCULO'!K96 -> 0.823175 | G51: ='04_MOTOR_CÁLCULO'!K96-1 -> -0.176825 | H51: ='04_MOTOR_CÁLCULO'!M96 -> Preferencial
A52: ='04_MOTOR_CÁLCULO'!A76 -> 0159-8/99 | B52: ='04_MOTOR_CÁLCULO'!B76 -> A | C52: ='04_MOTOR_CÁLCULO'!C76 -> Criação de outros animais não especificados anteriormente | D52: ='04_MOTOR_CÁLCULO'!D76 -> AGRICULTURA, PEC | E52: ='04_MOTOR_CÁLCULO'!N76 -> FAP/MPS | F52: ='04_MOTOR_CÁLCULO'!K76 -> 0.824065 | G52: ='04_MOTOR_CÁLCULO'!K76-1 -> -0.175935 | H52: ='04_MOTOR_CÁLCULO'!M76 -> Preferencial
A53: ='04_MOTOR_CÁLCULO'!A168 -> 0910-6/00 | B53: ='04_MOTOR_CÁLCULO'!B168 -> B | C53: ='04_MOTOR_CÁLCULO'!C168 -> Atividades de apoio à extração de petróleo e gás natural | D53: ='04_MOTOR_CÁLCULO'!D168 -> ATIVIDADES DE AP | E53: ='04_MOTOR_CÁLCULO'!N168 -> FAP/MPS | F53: ='04_MOTOR_CÁLCULO'!K168 -> 0.824265 | G53: ='04_MOTOR_CÁLCULO'!K168-1 -> -0.175735 | H53: ='04_MOTOR_CÁLCULO'!M168 -> Preferencial
A54: ='04_MOTOR_CÁLCULO'!A91 -> 0210-1/05 | B54: ='04_MOTOR_CÁLCULO'!B91 -> A | C54: ='04_MOTOR_CÁLCULO'!C91 -> Cultivo de espécies madeireiras, exceto eucalipto, acácia-negra, pinus e teca | D54: ='04_MOTOR_CÁLCULO'!D91 -> PRODUÇÃO FLOREST | E54: ='04_MOTOR_CÁLCULO'!N91 -> FAP/MPS | F54: ='04_MOTOR_CÁLCULO'!K91 -> 0.829875 | G54: ='04_MOTOR_CÁLCULO'!K91-1 -> -0.170125 | H54: ='04_MOTOR_CÁLCULO'!M91 -> Preferencial
A55: ='04_MOTOR_CÁLCULO'!A140 -> 0724-3/01 | B55: ='04_MOTOR_CÁLCULO'!B140 -> B | C55: ='04_MOTOR_CÁLCULO'!C140 -> Extração de minério de metais preciosos | D55: ='04_MOTOR_CÁLCULO'!D140 -> EXTRAÇÃO DE MINE | E55: ='04_MOTOR_CÁLCULO'!N140 -> FAP/MPS | F55: ='04_MOTOR_CÁLCULO'!K140 -> 0.83585 | G55: ='04_MOTOR_CÁLCULO'!K140-1 -> -0.16415 | H55: ='04_MOTOR_CÁLCULO'!M140 -> Preferencial
A56: ='04_MOTOR_CÁLCULO'!A72 -> 0159-8/01 | B56: ='04_MOTOR_CÁLCULO'!B72 -> A | C56: ='04_MOTOR_CÁLCULO'!C72 -> Apicultura | D56: ='04_MOTOR_CÁLCULO'!D72 -> AGRICULTURA, PEC | E56: ='04_MOTOR_CÁLCULO'!N72 -> FAP/MPS | F56: ='04_MOTOR_CÁLCULO'!K72 -> 0.85828 | G56: ='04_MOTOR_CÁLCULO'!K72-1 -> -0.14172 | H56: ='04_MOTOR_CÁLCULO'!M72 -> Preferencial
A57: ='04_MOTOR_CÁLCULO'!A73 -> 0159-8/02 | B57: ='04_MOTOR_CÁLCULO'!B73 -> A | C57: ='04_MOTOR_CÁLCULO'!C73 -> Criação de animais de estimação | D57: ='04_MOTOR_CÁLCULO'!D73 -> AGRICULTURA, PEC | E57: ='04_MOTOR_CÁLCULO'!N73 -> FAP/MPS | F57: ='04_MOTOR_CÁLCULO'!K73 -> 0.86156 | G57: ='04_MOTOR_CÁLCULO'!K73-1 -> -0.13844 | H57: ='04_MOTOR_CÁLCULO'!M73 -> Preferencial
A58: ='04_MOTOR_CÁLCULO'!A146 -> 0729-4/04 | B58: ='04_MOTOR_CÁLCULO'!B146 -> B | C58: ='04_MOTOR_CÁLCULO'!C146 -> Extração de minérios de cobre, chumbo, zinco e outros minerais metálicos não ferrosos não especificados anteriormente | D58: ='04_MOTOR_CÁLCULO'!D146 -> EXTRAÇÃO DE MINE | E58: ='04_MOTOR_CÁLCULO'!N146 -> FAP/MPS | F58: ='04_MOTOR_CÁLCULO'!K146 -> 0.868405 | G58: ='04_MOTOR_CÁLCULO'!K146-1 -> -0.131595 | H58: ='04_MOTOR_CÁLCULO'!M146 -> Preferencial
A59: ='04_MOTOR_CÁLCULO'!A49 -> 0139-3/02 | B59: ='04_MOTOR_CÁLCULO'!B49 -> A | C59: ='04_MOTOR_CÁLCULO'!C49 -> Cultivo de erva-mate | D59: ='04_MOTOR_CÁLCULO'!D49 -> AGRICULTURA, PEC | E59: ='04_MOTOR_CÁLCULO'!N49 -> FAP/MPS | F59: ='04_MOTOR_CÁLCULO'!K49 -> 0.89116 | G59: ='04_MOTOR_CÁLCULO'!K49-1 -> -0.10884 | H59: ='04_MOTOR_CÁLCULO'!M49 -> Baixo
A60: ='04_MOTOR_CÁLCULO'!A260 -> 1411-8/01 | B60: ='04_MOTOR_CÁLCULO'!B260 -> C | C60: ='04_MOTOR_CÁLCULO'!C260 -> Confecção de roupas íntimas | D60: ='04_MOTOR_CÁLCULO'!D260 -> CONFECÇÃO DE ART | E60: ='04_MOTOR_CÁLCULO'!N260 -> CNAE-STG | F60: ='04_MOTOR_CÁLCULO'!K260 -> 0.9 | G60: ='04_MOTOR_CÁLCULO'!K260-1 -> -0.1 | H60: ='04_MOTOR_CÁLCULO'!M260 -> Baixo
A61: ='04_MOTOR_CÁLCULO'!A261 -> 1411-8/02 | B61: ='04_MOTOR_CÁLCULO'!B261 -> C | C61: ='04_MOTOR_CÁLCULO'!C261 -> Facção de roupas íntimas | D61: ='04_MOTOR_CÁLCULO'!D261 -> CONFECÇÃO DE ART | E61: ='04_MOTOR_CÁLCULO'!N261 -> CNAE-STG | F61: ='04_MOTOR_CÁLCULO'!K261 -> 0.9 | G61: ='04_MOTOR_CÁLCULO'!K261-1 -> -0.1 | H61: ='04_MOTOR_CÁLCULO'!M261 -> Baixo
A62: ='04_MOTOR_CÁLCULO'!A262 -> 1412-6/01 | B62: ='04_MOTOR_CÁLCULO'!B262 -> C | C62: ='04_MOTOR_CÁLCULO'!C262 -> Confecção de peças do vestuário, exceto roupas íntimas e as confeccionadas sob medida | D62: ='04_MOTOR_CÁLCULO'!D262 -> CONFECÇÃO DE ART | E62: ='04_MOTOR_CÁLCULO'!N262 -> CNAE-STG | F62: ='04_MOTOR_CÁLCULO'!K262 -> 0.9 | G62: ='04_MOTOR_CÁLCULO'!K262-1 -> -0.1 | H62: ='04_MOTOR_CÁLCULO'!M262 -> Baixo
A63: ='04_MOTOR_CÁLCULO'!A263 -> 1412-6/02 | B63: ='04_MOTOR_CÁLCULO'!B263 -> C | C63: ='04_MOTOR_CÁLCULO'!C263 -> Confecção, sob medida, de peças do vestuário, exceto roupas íntimas | D63: ='04_MOTOR_CÁLCULO'!D263 -> CONFECÇÃO DE ART | E63: ='04_MOTOR_CÁLCULO'!N263 -> CNAE-STG | F63: ='04_MOTOR_CÁLCULO'!K263 -> 0.9 | G63: ='04_MOTOR_CÁLCULO'!K263-1 -> -0.1 | H63: ='04_MOTOR_CÁLCULO'!M263 -> Baixo
A64: ='04_MOTOR_CÁLCULO'!A264 -> 1412-6/03 | B64: ='04_MOTOR_CÁLCULO'!B264 -> C | C64: ='04_MOTOR_CÁLCULO'!C264 -> Facção de peças do vestuário, exceto roupas íntimas | D64: ='04_MOTOR_CÁLCULO'!D264 -> CONFECÇÃO DE ART | E64: ='04_MOTOR_CÁLCULO'!N264 -> CNAE-STG | F64: ='04_MOTOR_CÁLCULO'!K264 -> 0.9 | G64: ='04_MOTOR_CÁLCULO'!K264-1 -> -0.1 | H64: ='04_MOTOR_CÁLCULO'!M264 -> Baixo
A65: ='04_MOTOR_CÁLCULO'!A265 -> 1413-4/01 | B65: ='04_MOTOR_CÁLCULO'!B265 -> C | C65: ='04_MOTOR_CÁLCULO'!C265 -> Confecção de roupas profissionais, exceto sob medida | D65: ='04_MOTOR_CÁLCULO'!D265 -> CONFECÇÃO DE ART | E65: ='04_MOTOR_CÁLCULO'!N265 -> CNAE-STG | F65: ='04_MOTOR_CÁLCULO'!K265 -> 0.9 | G65: ='04_MOTOR_CÁLCULO'!K265-1 -> -0.1 | H65: ='04_MOTOR_CÁLCULO'!M265 -> Baixo
A66: ='04_MOTOR_CÁLCULO'!A266 -> 1413-4/02 | B66: ='04_MOTOR_CÁLCULO'!B266 -> C | C66: ='04_MOTOR_CÁLCULO'!C266 -> Confecção, sob medida, de roupas profissionais | D66: ='04_MOTOR_CÁLCULO'!D266 -> CONFECÇÃO DE ART | E66: ='04_MOTOR_CÁLCULO'!N266 -> CNAE-STG | F66: ='04_MOTOR_CÁLCULO'!K266 -> 0.9 | G66: ='04_MOTOR_CÁLCULO'!K266-1 -> -0.1 | H66: ='04_MOTOR_CÁLCULO'!M266 -> Baixo
A67: ='04_MOTOR_CÁLCULO'!A267 -> 1413-4/03 | B67: ='04_MOTOR_CÁLCULO'!B267 -> C | C67: ='04_MOTOR_CÁLCULO'!C267 -> Facção de roupas profissionais | D67: ='04_MOTOR_CÁLCULO'!D267 -> CONFECÇÃO DE ART | E67: ='04_MOTOR_CÁLCULO'!N267 -> CNAE-STG | F67: ='04_MOTOR_CÁLCULO'!K267 -> 0.9 | G67: ='04_MOTOR_CÁLCULO'!K267-1 -> -0.1 | H67: ='04_MOTOR_CÁLCULO'!M267 -> Baixo
A68: ='04_MOTOR_CÁLCULO'!A268 -> 1414-2/00 | B68: ='04_MOTOR_CÁLCULO'!B268 -> C | C68: ='04_MOTOR_CÁLCULO'!C268 -> Fabricação de acessórios do vestuário, exceto para segurança e proteção | D68: ='04_MOTOR_CÁLCULO'!D268 -> CONFECÇÃO DE ART | E68: ='04_MOTOR_CÁLCULO'!N268 -> CNAE-STG | F68: ='04_MOTOR_CÁLCULO'!K268 -> 0.9 | G68: ='04_MOTOR_CÁLCULO'!K268-1 -> -0.1 | H68: ='04_MOTOR_CÁLCULO'!M268 -> Baixo
A69: ='04_MOTOR_CÁLCULO'!A269 -> 1421-5/00 | B69: ='04_MOTOR_CÁLCULO'!B269 -> C | C69: ='04_MOTOR_CÁLCULO'!C269 -> Fabricação de meias | D69: ='04_MOTOR_CÁLCULO'!D269 -> CONFECÇÃO DE ART | E69: ='04_MOTOR_CÁLCULO'!N269 -> CNAE-STG | F69: ='04_MOTOR_CÁLCULO'!K269 -> 0.9 | G69: ='04_MOTOR_CÁLCULO'!K269-1 -> -0.1 | H69: ='04_MOTOR_CÁLCULO'!M269 -> Baixo
A70: ='04_MOTOR_CÁLCULO'!A270 -> 1422-3/00 | B70: ='04_MOTOR_CÁLCULO'!B270 -> C | C70: ='04_MOTOR_CÁLCULO'!C270 -> Fabricação de artigos do vestuário, produzidos em malharias e tricotagens, exceto meias | D70: ='04_MOTOR_CÁLCULO'!D270 -> CONFECÇÃO DE ART | E70: ='04_MOTOR_CÁLCULO'!N270 -> CNAE-STG | F70: ='04_MOTOR_CÁLCULO'!K270 -> 0.9 | G70: ='04_MOTOR_CÁLCULO'!K270-1 -> -0.1 | H70: ='04_MOTOR_CÁLCULO'!M270 -> Baixo
A71: ='04_MOTOR_CÁLCULO'!A302 -> 1811-3/01 | B71: ='04_MOTOR_CÁLCULO'!B302 -> C | C71: ='04_MOTOR_CÁLCULO'!C302 -> Impressão de jornais | D71: ='04_MOTOR_CÁLCULO'!D302 -> IMPRESSÃO E REPR | E71: ='04_MOTOR_CÁLCULO'!N302 -> CNAE-STG | F71: ='04_MOTOR_CÁLCULO'!K302 -> 0.9 | G71: ='04_MOTOR_CÁLCULO'!K302-1 -> -0.1 | H71: ='04_MOTOR_CÁLCULO'!M302 -> Baixo
A72: ='04_MOTOR_CÁLCULO'!A303 -> 1811-3/02 | B72: ='04_MOTOR_CÁLCULO'!B303 -> C | C72: ='04_MOTOR_CÁLCULO'!C303 -> Impressão de livros, revistas e outras publicações periódicas | D72: ='04_MOTOR_CÁLCULO'!D303 -> IMPRESSÃO E REPR | E72: ='04_MOTOR_CÁLCULO'!N303 -> CNAE-STG | F72: ='04_MOTOR_CÁLCULO'!K303 -> 0.9 | G72: ='04_MOTOR_CÁLCULO'!K303-1 -> -0.1 | H72: ='04_MOTOR_CÁLCULO'!M303 -> Baixo
A73: ='04_MOTOR_CÁLCULO'!A304 -> 1812-1/00 | B73: ='04_MOTOR_CÁLCULO'!B304 -> C | C73: ='04_MOTOR_CÁLCULO'!C304 -> Impressão de material de segurança | D73: ='04_MOTOR_CÁLCULO'!D304 -> IMPRESSÃO E REPR | E73: ='04_MOTOR_CÁLCULO'!N304 -> CNAE-STG | F73: ='04_MOTOR_CÁLCULO'!K304 -> 0.9 | G73: ='04_MOTOR_CÁLCULO'!K304-1 -> -0.1 | H73: ='04_MOTOR_CÁLCULO'!M304 -> Baixo
A74: ='04_MOTOR_CÁLCULO'!A305 -> 1813-0/01 | B74: ='04_MOTOR_CÁLCULO'!B305 -> C | C74: ='04_MOTOR_CÁLCULO'!C305 -> Impressão de material para uso publicitário | D74: ='04_MOTOR_CÁLCULO'!D305 -> IMPRESSÃO E REPR | E74: ='04_MOTOR_CÁLCULO'!N305 -> CNAE-STG | F74: ='04_MOTOR_CÁLCULO'!K305 -> 0.9 | G74: ='04_MOTOR_CÁLCULO'!K305-1 -> -0.1 | H74: ='04_MOTOR_CÁLCULO'!M305 -> Baixo
A75: ='04_MOTOR_CÁLCULO'!A306 -> 1813-0/99 | B75: ='04_MOTOR_CÁLCULO'!B306 -> C | C75: ='04_MOTOR_CÁLCULO'!C306 -> Impressão de material para outros usos | D75: ='04_MOTOR_CÁLCULO'!D306 -> IMPRESSÃO E REPR | E75: ='04_MOTOR_CÁLCULO'!N306 -> CNAE-STG | F75: ='04_MOTOR_CÁLCULO'!K306 -> 0.9 | G75: ='04_MOTOR_CÁLCULO'!K306-1 -> -0.1 | H75: ='04_MOTOR_CÁLCULO'!M306 -> Baixo
A76: ='04_MOTOR_CÁLCULO'!A307 -> 1821-1/00 | B76: ='04_MOTOR_CÁLCULO'!B307 -> C | C76: ='04_MOTOR_CÁLCULO'!C307 -> Serviços de pré-impressão | D76: ='04_MOTOR_CÁLCULO'!D307 -> IMPRESSÃO E REPR | E76: ='04_MOTOR_CÁLCULO'!N307 -> CNAE-STG | F76: ='04_MOTOR_CÁLCULO'!K307 -> 0.9 | G76: ='04_MOTOR_CÁLCULO'!K307-1 -> -0.1 | H76: ='04_MOTOR_CÁLCULO'!M307 -> Baixo
A77: ='04_MOTOR_CÁLCULO'!A308 -> 1822-9/01 | B77: ='04_MOTOR_CÁLCULO'!B308 -> C | C77: ='04_MOTOR_CÁLCULO'!C308 -> Serviços de encadernação e plastificação | D77: ='04_MOTOR_CÁLCULO'!D308 -> IMPRESSÃO E REPR | E77: ='04_MOTOR_CÁLCULO'!N308 -> CNAE-STG | F77: ='04_MOTOR_CÁLCULO'!K308 -> 0.9 | G77: ='04_MOTOR_CÁLCULO'!K308-1 -> -0.1 | H77: ='04_MOTOR_CÁLCULO'!M308 -> Baixo
A78: ='04_MOTOR_CÁLCULO'!A309 -> 1822-9/99 | B78: ='04_MOTOR_CÁLCULO'!B309 -> C | C78: ='04_MOTOR_CÁLCULO'!C309 -> Serviços de acabamentos gráficos, exceto encadernação e plastificação | D78: ='04_MOTOR_CÁLCULO'!D309 -> IMPRESSÃO E REPR | E78: ='04_MOTOR_CÁLCULO'!N309 -> CNAE-STG | F78: ='04_MOTOR_CÁLCULO'!K309 -> 0.9 | G78: ='04_MOTOR_CÁLCULO'!K309-1 -> -0.1 | H78: ='04_MOTOR_CÁLCULO'!M309 -> Baixo
A79: ='04_MOTOR_CÁLCULO'!A310 -> 1830-0/01 | B79: ='04_MOTOR_CÁLCULO'!B310 -> C | C79: ='04_MOTOR_CÁLCULO'!C310 -> Reprodução de som em qualquer suporte | D79: ='04_MOTOR_CÁLCULO'!D310 -> IMPRESSÃO E REPR | E79: ='04_MOTOR_CÁLCULO'!N310 -> CNAE-STG | F79: ='04_MOTOR_CÁLCULO'!K310 -> 0.9 | G79: ='04_MOTOR_CÁLCULO'!K310-1 -> -0.1 | H79: ='04_MOTOR_CÁLCULO'!M310 -> Baixo
A80: ='04_MOTOR_CÁLCULO'!A311 -> 1830-0/02 | B80: ='04_MOTOR_CÁLCULO'!B311 -> C | C80: ='04_MOTOR_CÁLCULO'!C311 -> Reprodução de vídeo em qualquer suporte | D80: ='04_MOTOR_CÁLCULO'!D311 -> IMPRESSÃO E REPR | E80: ='04_MOTOR_CÁLCULO'!N311 -> CNAE-STG | F80: ='04_MOTOR_CÁLCULO'!K311 -> 0.9 | G80: ='04_MOTOR_CÁLCULO'!K311-1 -> -0.1 | H80: ='04_MOTOR_CÁLCULO'!M311 -> Baixo
A81: ='04_MOTOR_CÁLCULO'!A312 -> 1830-0/03 | B81: ='04_MOTOR_CÁLCULO'!B312 -> C | C81: ='04_MOTOR_CÁLCULO'!C312 -> Reprodução de software em qualquer suporte | D81: ='04_MOTOR_CÁLCULO'!D312 -> IMPRESSÃO E REPR | E81: ='04_MOTOR_CÁLCULO'!N312 -> CNAE-STG | F81: ='04_MOTOR_CÁLCULO'!K312 -> 0.9 | G81: ='04_MOTOR_CÁLCULO'!K312-1 -> -0.1 | H81: ='04_MOTOR_CÁLCULO'!M312 -> Baixo
A82: ='04_MOTOR_CÁLCULO'!A432 -> 2610-8/00 | B82: ='04_MOTOR_CÁLCULO'!B432 -> C | C82: ='04_MOTOR_CÁLCULO'!C432 -> Fabricação de componentes eletrônicos | D82: ='04_MOTOR_CÁLCULO'!D432 -> FABRICAÇÃO DE EQ | E82: ='04_MOTOR_CÁLCULO'!N432 -> CNAE-STG | F82: ='04_MOTOR_CÁLCULO'!K432 -> 0.9 | G82: ='04_MOTOR_CÁLCULO'!K432-1 -> -0.1 | H82: ='04_MOTOR_CÁLCULO'!M432 -> Baixo
A83: ='04_MOTOR_CÁLCULO'!A433 -> 2621-3/00 | B83: ='04_MOTOR_CÁLCULO'!B433 -> C | C83: ='04_MOTOR_CÁLCULO'!C433 -> Fabricação de equipamentos de informática | D83: ='04_MOTOR_CÁLCULO'!D433 -> FABRICAÇÃO DE EQ | E83: ='04_MOTOR_CÁLCULO'!N433 -> CNAE-STG | F83: ='04_MOTOR_CÁLCULO'!K433 -> 0.9 | G83: ='04_MOTOR_CÁLCULO'!K433-1 -> -0.1 | H83: ='04_MOTOR_CÁLCULO'!M433 -> Baixo
A84: ='04_MOTOR_CÁLCULO'!A434 -> 2622-1/00 | B84: ='04_MOTOR_CÁLCULO'!B434 -> C | C84: ='04_MOTOR_CÁLCULO'!C434 -> Fabricação de periféricos para equipamentos de informática | D84: ='04_MOTOR_CÁLCULO'!D434 -> FABRICAÇÃO DE EQ | E84: ='04_MOTOR_CÁLCULO'!N434 -> CNAE-STG | F84: ='04_MOTOR_CÁLCULO'!K434 -> 0.9 | G84: ='04_MOTOR_CÁLCULO'!K434-1 -> -0.1 | H84: ='04_MOTOR_CÁLCULO'!M434 -> Baixo
A85: ='04_MOTOR_CÁLCULO'!A435 -> 2631-1/00 | B85: ='04_MOTOR_CÁLCULO'!B435 -> C | C85: ='04_MOTOR_CÁLCULO'!C435 -> Fabricação de equipamentos transmissores de comunicação, peças e acessórios | D85: ='04_MOTOR_CÁLCULO'!D435 -> FABRICAÇÃO DE EQ | E85: ='04_MOTOR_CÁLCULO'!N435 -> CNAE-STG | F85: ='04_MOTOR_CÁLCULO'!K435 -> 0.9 | G85: ='04_MOTOR_CÁLCULO'!K435-1 -> -0.1 | H85: ='04_MOTOR_CÁLCULO'!M435 -> Baixo
A86: ='04_MOTOR_CÁLCULO'!A436 -> 2632-9/00 | B86: ='04_MOTOR_CÁLCULO'!B436 -> C | C86: ='04_MOTOR_CÁLCULO'!C436 -> Fabricação de aparelhos telefônicos e de outros equipamentos de comunicação, peças e acessórios | D86: ='04_MOTOR_CÁLCULO'!D436 -> FABRICAÇÃO DE EQ | E86: ='04_MOTOR_CÁLCULO'!N436 -> CNAE-STG | F86: ='04_MOTOR_CÁLCULO'!K436 -> 0.9 | G86: ='04_MOTOR_CÁLCULO'!K436-1 -> -0.1 | H86: ='04_MOTOR_CÁLCULO'!M436 -> Baixo
A87: ='04_MOTOR_CÁLCULO'!A437 -> 2640-0/00 | B87: ='04_MOTOR_CÁLCULO'!B437 -> C | C87: ='04_MOTOR_CÁLCULO'!C437 -> Fabricação de aparelhos de recepção, reprodução, gravação e amplificação de áudio e vídeo | D87: ='04_MOTOR_CÁLCULO'!D437 -> FABRICAÇÃO DE EQ | E87: ='04_MOTOR_CÁLCULO'!N437 -> CNAE-STG | F87: ='04_MOTOR_CÁLCULO'!K437 -> 0.9 | G87: ='04_MOTOR_CÁLCULO'!K437-1 -> -0.1 | H87: ='04_MOTOR_CÁLCULO'!M437 -> Baixo
A88: ='04_MOTOR_CÁLCULO'!A438 -> 2651-5/00 | B88: ='04_MOTOR_CÁLCULO'!B438 -> C | C88: ='04_MOTOR_CÁLCULO'!C438 -> Fabricação de aparelhos e equipamentos de medida, teste e controle | D88: ='04_MOTOR_CÁLCULO'!D438 -> FABRICAÇÃO DE EQ | E88: ='04_MOTOR_CÁLCULO'!N438 -> CNAE-STG | F88: ='04_MOTOR_CÁLCULO'!K438 -> 0.9 | G88: ='04_MOTOR_CÁLCULO'!K438-1 -> -0.1 | H88: ='04_MOTOR_CÁLCULO'!M438 -> Baixo
A89: ='04_MOTOR_CÁLCULO'!A439 -> 2652-3/00 | B89: ='04_MOTOR_CÁLCULO'!B439 -> C | C89: ='04_MOTOR_CÁLCULO'!C439 -> Fabricação de cronômetros e relógios | D89: ='04_MOTOR_CÁLCULO'!D439 -> FABRICAÇÃO DE EQ | E89: ='04_MOTOR_CÁLCULO'!N439 -> CNAE-STG | F89: ='04_MOTOR_CÁLCULO'!K439 -> 0.9 | G89: ='04_MOTOR_CÁLCULO'!K439-1 -> -0.1 | H89: ='04_MOTOR_CÁLCULO'!M439 -> Baixo
A90: ='04_MOTOR_CÁLCULO'!A440 -> 2660-4/00 | B90: ='04_MOTOR_CÁLCULO'!B440 -> C | C90: ='04_MOTOR_CÁLCULO'!C440 -> Fabricação de aparelhos eletromédicos e eletroterapêuticos e equipamentos de irradiação | D90: ='04_MOTOR_CÁLCULO'!D440 -> FABRICAÇÃO DE EQ | E90: ='04_MOTOR_CÁLCULO'!N440 -> CNAE-STG | F90: ='04_MOTOR_CÁLCULO'!K440 -> 0.9 | G90: ='04_MOTOR_CÁLCULO'!K440-1 -> -0.1 | H90: ='04_MOTOR_CÁLCULO'!M440 -> Baixo
A91: ='04_MOTOR_CÁLCULO'!A441 -> 2670-1/01 | B91: ='04_MOTOR_CÁLCULO'!B441 -> C | C91: ='04_MOTOR_CÁLCULO'!C441 -> Fabricação de equipamentos e instrumentos ópticos, peças e acessórios | D91: ='04_MOTOR_CÁLCULO'!D441 -> FABRICAÇÃO DE EQ | E91: ='04_MOTOR_CÁLCULO'!N441 -> CNAE-STG | F91: ='04_MOTOR_CÁLCULO'!K441 -> 0.9 | G91: ='04_MOTOR_CÁLCULO'!K441-1 -> -0.1 | H91: ='04_MOTOR_CÁLCULO'!M441 -> Baixo
A92: ='04_MOTOR_CÁLCULO'!A442 -> 2670-1/02 | B92: ='04_MOTOR_CÁLCULO'!B442 -> C | C92: ='04_MOTOR_CÁLCULO'!C442 -> Fabricação de aparelhos fotográficos e cinematográficos, peças e acessórios | D92: ='04_MOTOR_CÁLCULO'!D442 -> FABRICAÇÃO DE EQ | E92: ='04_MOTOR_CÁLCULO'!N442 -> CNAE-STG | F92: ='04_MOTOR_CÁLCULO'!K442 -> 0.9 | G92: ='04_MOTOR_CÁLCULO'!K442-1 -> -0.1 | H92: ='04_MOTOR_CÁLCULO'!M442 -> Baixo
A93: ='04_MOTOR_CÁLCULO'!A443 -> 2680-9/00 | B93: ='04_MOTOR_CÁLCULO'!B443 -> C | C93: ='04_MOTOR_CÁLCULO'!C443 -> Fabricação de mídias virgens, magnéticas e ópticas | D93: ='04_MOTOR_CÁLCULO'!D443 -> FABRICAÇÃO DE EQ | E93: ='04_MOTOR_CÁLCULO'!N443 -> CNAE-STG | F93: ='04_MOTOR_CÁLCULO'!K443 -> 0.9 | G93: ='04_MOTOR_CÁLCULO'!K443-1 -> -0.1 | H93: ='04_MOTOR_CÁLCULO'!M443 -> Baixo
A94: ='04_MOTOR_CÁLCULO'!A525 -> 3211-6/01 | B94: ='04_MOTOR_CÁLCULO'!B525 -> C | C94: ='04_MOTOR_CÁLCULO'!C525 -> Lapidação de gemas | D94: ='04_MOTOR_CÁLCULO'!D525 -> FABRICAÇÃO DE PR | E94: ='04_MOTOR_CÁLCULO'!N525 -> CNAE-STG | F94: ='04_MOTOR_CÁLCULO'!K525 -> 0.9 | G94: ='04_MOTOR_CÁLCULO'!K525-1 -> -0.1 | H94: ='04_MOTOR_CÁLCULO'!M525 -> Baixo
A95: ='04_MOTOR_CÁLCULO'!A526 -> 3211-6/02 | B95: ='04_MOTOR_CÁLCULO'!B526 -> C | C95: ='04_MOTOR_CÁLCULO'!C526 -> Fabricação de artefatos de joalheria e ourivesaria | D95: ='04_MOTOR_CÁLCULO'!D526 -> FABRICAÇÃO DE PR | E95: ='04_MOTOR_CÁLCULO'!N526 -> CNAE-STG | F95: ='04_MOTOR_CÁLCULO'!K526 -> 0.9 | G95: ='04_MOTOR_CÁLCULO'!K526-1 -> -0.1 | H95: ='04_MOTOR_CÁLCULO'!M526 -> Baixo
A96: ='04_MOTOR_CÁLCULO'!A527 -> 3211-6/03 | B96: ='04_MOTOR_CÁLCULO'!B527 -> C | C96: ='04_MOTOR_CÁLCULO'!C527 -> Cunhagem de moedas e medalhas | D96: ='04_MOTOR_CÁLCULO'!D527 -> FABRICAÇÃO DE PR | E96: ='04_MOTOR_CÁLCULO'!N527 -> CNAE-STG | F96: ='04_MOTOR_CÁLCULO'!K527 -> 0.9 | G96: ='04_MOTOR_CÁLCULO'!K527-1 -> -0.1 | H96: ='04_MOTOR_CÁLCULO'!M527 -> Baixo
A97: ='04_MOTOR_CÁLCULO'!A528 -> 3212-4/00 | B97: ='04_MOTOR_CÁLCULO'!B528 -> C | C97: ='04_MOTOR_CÁLCULO'!C528 -> Fabricação de bijuterias e artefatos semelhantes | D97: ='04_MOTOR_CÁLCULO'!D528 -> FABRICAÇÃO DE PR | E97: ='04_MOTOR_CÁLCULO'!N528 -> CNAE-STG | F97: ='04_MOTOR_CÁLCULO'!K528 -> 0.9 | G97: ='04_MOTOR_CÁLCULO'!K528-1 -> -0.1 | H97: ='04_MOTOR_CÁLCULO'!M528 -> Baixo
A98: ='04_MOTOR_CÁLCULO'!A529 -> 3220-5/00 | B98: ='04_MOTOR_CÁLCULO'!B529 -> C | C98: ='04_MOTOR_CÁLCULO'!C529 -> Fabricação de instrumentos musicais, peças e acessórios | D98: ='04_MOTOR_CÁLCULO'!D529 -> FABRICAÇÃO DE PR | E98: ='04_MOTOR_CÁLCULO'!N529 -> CNAE-STG | F98: ='04_MOTOR_CÁLCULO'!K529 -> 0.9 | G98: ='04_MOTOR_CÁLCULO'!K529-1 -> -0.1 | H98: ='04_MOTOR_CÁLCULO'!M529 -> Baixo
A99: ='04_MOTOR_CÁLCULO'!A530 -> 3230-2/00 | B99: ='04_MOTOR_CÁLCULO'!B530 -> C | C99: ='04_MOTOR_CÁLCULO'!C530 -> Fabricação de artefatos para pesca e esporte | D99: ='04_MOTOR_CÁLCULO'!D530 -> FABRICAÇÃO DE PR | E99: ='04_MOTOR_CÁLCULO'!N530 -> CNAE-STG | F99: ='04_MOTOR_CÁLCULO'!K530 -> 0.9 | G99: ='04_MOTOR_CÁLCULO'!K530-1 -> -0.1 | H99: ='04_MOTOR_CÁLCULO'!M530 -> Baixo
A100: ='04_MOTOR_CÁLCULO'!A531 -> 3240-0/01 | B100: ='04_MOTOR_CÁLCULO'!B531 -> C | C100: ='04_MOTOR_CÁLCULO'!C531 -> Fabricação de jogos eletrônicos | D100: ='04_MOTOR_CÁLCULO'!D531 -> FABRICAÇÃO DE PR | E100: ='04_MOTOR_CÁLCULO'!N531 -> CNAE-STG | F100: ='04_MOTOR_CÁLCULO'!K531 -> 0.9 | G100: ='04_MOTOR_CÁLCULO'!K531-1 -> -0.1 | H100: ='04_MOTOR_CÁLCULO'!M531 -> Baixo
...

Sheet 09_SEM_DADOS_FAP
A1: CNAEs STG SEM DADOS FAP — USANDO FALLBACK CNAE-STG | 1,169 subclasses
A2: Subclasses presentes na tabela STG mas ausentes nos PDFs FAP/MPS. Relatividade = coeficiente CNAE original (0,90 / 1,00 / 1,15).
A3: PRIORIDADE DE ATUALIZAÇÃO: Seções C (Indústria), G (Comércio), H (Transporte) e Q (Saúde) concentram 73% das subclasses sem FAP.
A4: Cód. CNAE | B4: Sec. | C4: Descrição Subclasse | D4: Divisão | E4: Seção Completa | F4: Class. STG | G4: Coef. STG | H4: Ação Recomendada
A5: 0159-8/03 | B5: A | C5: Criação de escargô | D5: AGRICULTURA, PECUÁRIA E SERVIÇOS RELACIONADOS | E5: AGRICULTURA, PECUÁRIA, PRODUÇÃO FLORESTAL, PESCA E AQUICULTURA | F5: Médio | G5: 1 | H5: 🟢 Baixa — coeficiente CNAE adequado
A6: 0159-8/04 | B6: A | C6: Criação de bicho-da-seda | D6: AGRICULTURA, PECUÁRIA E SERVIÇOS RELACIONADOS | E6: AGRICULTURA, PECUÁRIA, PRODUÇÃO FLORESTAL, PESCA E AQUICULTURA | F6: Médio | G6: 1 | H6: 🟢 Baixa — coeficiente CNAE adequado
A7: 0312-4/02 | B7: A | C7: Pesca de crustáceos e moluscos em água doce | D7: PESCA E AQÜICULTURA | E7: AGRICULTURA, PECUÁRIA, PRODUÇÃO FLORESTAL, PESCA E AQUICULTURA | F7: Alto | G7: 1.15 | H7: 🟢 Baixa — coeficiente CNAE adequado
A8: 0322-1/03 | B8: A | C8: Criação de ostras e mexilhões em água doce | D8: PESCA E AQÜICULTURA | E8: AGRICULTURA, PECUÁRIA, PRODUÇÃO FLORESTAL, PESCA E AQUICULTURA | F8: Alto | G8: 1.15 | H8: 🟢 Baixa — coeficiente CNAE adequado
A9: 1011-2/01 | B9: C | C9: Frigorífico - abate de bovinos | D9: FABRICAÇÃO DE PRODUTOS ALIMENTÍCIOS | E9: INDÚSTRIAS DE TRANSFORMAÇÃO | F9: Alto | G9: 1.15 | H9: 🔴 Alta — obter dados BRP/CNseg
A10: 1011-2/02 | B10: C | C10: Frigorífico - abate de equinos | D10: FABRICAÇÃO DE PRODUTOS ALIMENTÍCIOS | E10: INDÚSTRIAS DE TRANSFORMAÇÃO | F10: Alto | G10: 1.15 | H10: 🔴 Alta — obter dados BRP/CNseg
A11: 1011-2/03 | B11: C | C11: Frigorífico - abate de ovinos e caprinos | D11: FABRICAÇÃO DE PRODUTOS ALIMENTÍCIOS | E11: INDÚSTRIAS DE TRANSFORMAÇÃO | F11: Alto | G11: 1.15 | H11: 🔴 Alta — obter dados BRP/CNseg
A12: 1011-2/04 | B12: C | C12: Frigorífico - abate de bufalinos | D12: FABRICAÇÃO DE PRODUTOS ALIMENTÍCIOS | E12: INDÚSTRIAS DE TRANSFORMAÇÃO | F12: Alto | G12: 1.15 | H12: 🔴 Alta — obter dados BRP/CNseg
A13: 1011-2/05 | B13: C | C13: Matadouro - abate de reses sob contrato, exceto abate de suínos | D13: FABRICAÇÃO DE PRODUTOS ALIMENTÍCIOS | E13: INDÚSTRIAS DE TRANSFORMAÇÃO | F13: Alto | G13: 1.15 | H13: 🔴 Alta — obter dados BRP/CNseg
A14: 1012-1/01 | B14: C | C14: Abate de aves | D14: FABRICAÇÃO DE PRODUTOS ALIMENTÍCIOS | E14: INDÚSTRIAS DE TRANSFORMAÇÃO | F14: Alto | G14: 1.15 | H14: 🔴 Alta — obter dados BRP/CNseg
A15: 1012-1/02 | B15: C | C15: Abate de pequenos animais | D15: FABRICAÇÃO DE PRODUTOS ALIMENTÍCIOS | E15: INDÚSTRIAS DE TRANSFORMAÇÃO | F15: Alto | G15: 1.15 | H15: 🔴 Alta — obter dados BRP/CNseg
A16: 1012-1/03 | B16: C | C16: Frigorífico - abate de suínos | D16: FABRICAÇÃO DE PRODUTOS ALIMENTÍCIOS | E16: INDÚSTRIAS DE TRANSFORMAÇÃO | F16: Alto | G16: 1.15 | H16: 🔴 Alta — obter dados BRP/CNseg
... A1173: 9900-8/00 | B1173: U | C1173: Organismos internacionais e outras instituições extraterritoriais | D1173: ORGANISMOS INTERNACIONAIS E OUTRAS INSTITUIÇÕES EXTRATERRITORIAIS | E1173: ORGANISMOS INTERNACIONAIS E OUTRAS INSTITUIÇÕES EXTRATERRITORIAIS | F1173: Baixo | G1173: 0.9 | H1173: 🟢 Baixa — coeficiente CNAE adequado
A1176: RESUMO POR SEÇÃO — CNAEs sem dados FAP
A1177: Seção | B1177: Descrição | C1177: Qtde | D1177: % do Total | E1177: Baixo | F1177: Médio | G1177: Alto | H1177: Prioridade
A1178: C | B1178: INDÚSTRIAS DE TRANSFORMAÇÃO | C1178: 420 | D1178: 35.9% | E1178: 62 | F1178: 216 | G1178: 142 | H1178: 🔴 Alta — obter dados BRP/CNseg
A1179: G | B1179: COMÉRCIO; REPARAÇÃO DE VEÍCULOS AUTOMOTO | C1179: 226 | D1179: 19.3% | E1179: 188 | F1179: 36 | G1179: 2 | H1179: 🟡 Média — avaliar na revisão anual
A1180: H | B1180: TRANSPORTE, ARMAZENAGEM E CORREIO | C1180: 70 | D1180: 6.0% | E1180: 0 | F1180: 27 | G1180: 43 | H1180: 🔴 Alta — obter dados BRP/CNseg
A1181: K | B1181: ATIVIDADES FINANCEIRAS, DE SEGUROS E SER | C1181: 65 | D1181: 5.6% | E1181: 65 | F1181: 0 | G1181: 0 | H1181: 🟢 Baixa — coeficiente CNAE adequado
A1182: N | B1182: ATIVIDADES ADMINISTRATIVAS E SERVIÇOS CO | C1182: 54 | D1182: 4.6% | E1182: 42 | F1182: 9 | G1182: 3 | H1182: 🟡 Média — avaliar na revisão anual
A1183: Q | B1183: SAÚDE HUMANA E SERVIÇOS SOCIAIS | C1183: 53 | D1183: 4.5% | E1183: 1 | F1183: 47 | G1183: 5 | H1183: 🟡 Média — avaliar na revisão anual
A1184: J | B1184: INFORMAÇÃO E COMUNICAÇÃO | C1184: 47 | D1184: 4.0% | E1184: 33 | F1184: 14 | G1184: 0 | H1184: 🟢 Baixa — coeficiente CNAE adequado
A1185: F | B1185: CONSTRUÇÃO | C1185: 47 | D1185: 4.0% | E1185: 1 | F1185: 0 | G1185: 46 | H1185: 🔴 Alta — obter dados BRP/CNseg
A1186: M | B1186: ATIVIDADES PROFISSIONAIS, CIENTÍFICAS E | C1186: 40 | D1186: 3.4% | E1186: 29 | F1186: 11 | G1186: 0 | H1186: 🟢 Baixa — coeficiente CNAE adequado
A1187: S | B1187: OUTRAS ATIVIDADES DE SERVIÇOS | C1187: 37 | D1187: 3.2% | E1187: 27 | F1187: 10 | G1187: 0 | H1187: 🟢 Baixa — coeficiente CNAE adequado
A1188: R | B1188: ARTES, CULTURA, ESPORTE E RECREAÇÃO | C1188: 28 | D1188: 2.4% | E1188: 17 | F1188: 11 | G1188: 0 | H1188: 🟡 Média — avaliar na revisão anual
A1189: P | B1189: EDUCAÇÃO | C1189: 23 | D1189: 2.0% | E1189: 23 | F1189: 0 | G1189: 0 | H1189: 🟢 Baixa — coeficiente CNAE adequado
... A1197: U | B1197: ORGANISMOS INTERNACIONAIS E OUTRAS INSTI | C1197: 1 | D1197: 0.1% | E1197: 1 | F1197: 0 | G1197: 0 | H1197: 🟢 Baixa — coeficiente CNAE adequado
